Workbook

Sheet Guide
A1: Macro Tracker — Layer 1 (Macro Permission)
A2: Purpose: one weekly bias per instrument — LONG / SHORT / FLAT — with an expiry date. This is a filter, never an entry signal.
A4: ROUTINE (every 2 days) | E4: SHEET INDEX
A5: 1. Claude runs the full update cycle every 2 days (Prompts sheet → P0) and logs it on the Update Log. | E5: Sheet (click to open) | F5: What it's for | G5: When
A6: 2. User reads the Update Log (mark OK / Question / Revert) and the Calendar: what changed, what is coming. | E6: Bias ↗ | F6: FINAL BIAS per pair — what Layers 2–4 may trade | G6: Read weekly
A7: 3. User opens Bias Builder: model bias vs AI bias, then sets the User bias and User read per pair / currency. | E7: Compare ↗ | F7: Two currencies side by side — does the evidence back the call? | G7: Before a new idea
A8: 4. Bias: User enters today’s date in “Last reviewed” and writes the invalidation for each pair. | E8: Scorecard ↗ | F8: Macro data per currency → −1/0/+1 scores and stance | G8: Fill weekly
A9: 4b. Journal: User logs one line per instrument — bias, key driver, next catalyst — and every trade in the trade journal to the right (entry, stop, R, plan followed, emotion). | E9: Risk & Gold ↗ | F9: VIX risk regime + gold drivers → gold bias | G9: Fill weekly
A10: 5. After a tier-1 event (CPI, jobs, central-bank decision): run P8 for that event, or P4 for that currency. | E10: Key Levels ↗ | F10: Price levels where big players acted, with distance to price | G10: Fill weekly
E11: Hub ↗ | F11: Links out + one-line story per currency, risk barometer | G11: Fill weekly / monthly
A12: UNITS & CONVENTIONS | E12: Journal ↗ | F12: Bias journal (one row per bias) + trade journal on the right (one row per trade) — the User’s tuning data | G12: Log weekly
A13: • Percentages are typed as plain numbers: 3.1 means 3.1%. | E13: Calendar ↗ | F13: Economic calendar — this week + 4-month overview, colour-coded by country and type | G13: Open daily
A14: • Yield changes are in basis points (bp): 100 bp = 1 percentage point. | E14: Events ↗ | F14: The event list behind the Calendar | G14: Claude weekly
A15: • Text that starts with 'EXAMPLE:' is illustrative — the User overwrites it with their own read. | E15: Sources ↗ | F15: Where every input comes from, and who fills it | G15: Reference
A16: • Dates: type them as dates (e.g. 21-9-2026), never as a formula like =TODAY(). | E16: Bias Builder ↗ | F16: Per-country evidence (central bank, market pricing, treasury, indicators) + AI bias vs yours | G16: Before setting a bias
E17: Update Log ↗ | F17: What each update run changed — newest at the top | G17: After every run
A18: RULES / THRESHOLDS (every formula reads from here) | E18: Prompts ↗ | F18: All update prompts (P0 full cycle … P9) + the update rules | G18: To run or schedule
A19: Rule | B19: Value | C19: What it does | E19: COLOUR LEGEND
A20: Inflation 'near target' band (pp) | B20: 0.5 | C20: Core CPI falling AND within this distance of target (or below) = −1. Above target and not falling = +1. | E20: CELL TYPES — what the User may touch
A21: Unemployment change (pp) | B21: 0.2 | C21: Unemployment down ≥ this over 3 months = +1 (tight). Up ≥ this = −1 (weakening). | E21: 3.10 | F21: Input — type here | G21: Every sheet
A22: PMI expansion level | B22: 52 | C22: Composite PMI ≥ this = +1. | E22: 1 | F22: Formula — calculated, don't overwrite | G22: Every sheet
A23: PMI contraction level | B23: 48 | C23: Composite PMI ≤ this = −1. | E23: -1 | F23: Linked — pulled from another sheet | G23: Bias, Compare, Risk & Gold, Hub
A24: 2Y yield move (bp, 1 month) | B24: 15 | C24: Market repricing proxy. 2Y up ≥ this = +1 (hawkish repricing), down ≥ this = −1. | E24: Column header | F24: Table header | G24: Every sheet
A25: Currency stance cut-off (score) | B25: 2 | C25: Total ≥ +2 = HAWKISH, ≤ −2 = DOVISH, otherwise NEUTRAL. | E25: Fed ↗ | F25: Hyperlink — opens a website or sheet | G25: Hub, this sheet
A26: Pair score difference needed | B26: 2 | C26: Base score minus quote score must be ≥ this for a LONG signal (≤ −this for SHORT). | E26: Help text | F26: Note / explanation — read only | G26: Every sheet
A27: 2Y differential confirmation (bp) | B27: 10 | C27: The 2Y yield spread must have moved ≥ this in the same direction over 1 month, otherwise FLAT. | E27: ⚠ Warning | F27: Warning — check before relying on it | G27: Scorecard, Key Levels
A28: VIX calm level | B28: 18 | C28: From investing Layer 3: VIX below this (and S&P above 200-day) = RISK-ON. | E28: — | F28: Not applicable for this row | G28: Bias (gold row)
A29: VIX stress level | B29: 30 | C29: From investing Layer 3: VIX above this = RISK-OFF. | E29: Give me a brief… | F29: Prompt — copy and paste into Claude | G29: Hub
A30: Real-yield move for gold (bp) | B30: 15 | C30: US 10Y real yield down ≥ this over 1 month = +1 for gold; up ≥ this = −1. | E30: SIGNALS — colour changes by itself
A31: Dollar move for gold (%) | B31: 1 | C31: Dollar index down ≥ this % over 1 month = +1 for gold; up ≥ this = −1. | E31: LONG | F31: Long / hawkish / supportive: LONG · HAWKISH · RISK-ON · ACTIVE · OK · BACKS THE CALL · STRONG · YES | G31: Bias, Compare, Scorecard, Risk & Gold, Hub, Journal
A32: Gold score cut-off | B32: 2 | C32: Gold total ≥ +2 = LONG, ≤ −2 = SHORT. | E32: SHORT | F32: Short / dovish / against: SHORT · DOVISH · RISK-OFF · EXPIRED · STALE · AGAINST · WEAK · NO | G32: Bias, Compare, Scorecard, Risk & Gold, Hub, Journal
A33: Key level 'near' distance (%) | B33: 0.5 | C33: Key Levels flags a level as NEAR when price is within this % of it. | E33: NOT REVIEWED | F33: Needs attention: ENTER DATA · NOT REVIEWED · NOT CHECKED · CAUTION · MIXED · PARTLY · MODERATE · NEAR · yields NO | G33: Every sheet except Guide
A34: Bias valid for (days) | B34: 7 | C34: After this many days without review the bias shows EXPIRED — treat as FLAT. | E34: FLAT | F34: No edge — stand aside: FLAT · NEUTRAL | G34: Bias, Compare, Scorecard, Risk & Gold, Hub, Journal
A35: Starting thresholds are Claude's suggestions, not tested values — tune them after journaling a few months. | E35: +1 | F35: Score above zero (green) — supports the currency / gold | G35: Scorecard, Risk & Gold
E36: −1 | F36: Score below zero (red) — works against it | G36: Scorecard, Risk & Gold
A37: DATA SOURCES | E37: ■■■ | F37: Bar: green = base currency wins this factor | G37: Compare
A38: Fixed sources | B38: Every input has ONE fixed source — see the Sources sheet ↗ | E38: ■■■ | F38: Bar: red = quote currency wins this factor | G38: Compare
A39: US data | B39: FRED: core CPI, unemployment, 2Y, real yield, VIX, S&P 500, HY spread | E39: KEY LEVEL TYPES
A40: EUR / GBP / JPY data | B40: Eurostat · ONS · Statistics Bureau of Japan · Bundesbank · Japan MoF | E40: Policy line | F40: Government / central bank acted here | G40: Key Levels
A41: PMIs + prices | B41: S&P Global / HCOB final PMIs · TradingView (prices, 2Y yields, DXY, VIX, S&P, barometer) | E41: Options / GEX | F41: Big option strikes or expiries | G41: Key Levels
A42: Calendar | B42: Forex Factory weekly feed + Fed / ECB / BoE / BoJ calendars | E42: Structural | F42: Prior highs & lows, round numbers | G42: Key Levels
E43: Session | F43: Intraday: PDH/PDL, session ranges | G43: Key Levels
E44: 3 | F44: Strength 3 = strongest level (bold red) | G44: Key Levels
E45: SHEET TABS
E46: Navy tab | F46: guide, rules, legend | G46: Guide
E47: Green tab | F47: Reading with decisions | G47: Bias, Compare
E48: Blue tab | F48: Fill in weekly inputs | G48: Scorecard, Risk & Gold, Key Levels, Hub, Journal
E49: Gold tab | F49: Open daily — the economic calendar | G49: Calendar
E50: Grey tab | F50: Reference — where each input comes from | G50: Sources, Update Log, Prompts
E52: CALENDAR
E53: High | F53: Impact column (Events) / high-impact day (month view) | G53: Calendar, Events
E54: Medium | F54: Medium impact (Events impact column) | G54: Calendar, Events
E55: Holiday | F55: Bank holiday | G55: Calendar, Events
E56: Today | F56: Today (Calendar + Events). Country and event-type colours: see the KEY on the Calendar sheet | G56: Calendar, Events
E57: Claude | F57: Filled by: Claude updates these inputs | G57: Sources
E58: User | F58: Filled by: User — own judgement / notes | G58: Sources

Sheet Calendar
A1: Economic Calendar | AA1: ← Guide
A2: Open this every morning. Week view + four-month overview, fed by the Events sheet. Times are Amsterdam time (CET/CEST).
A4: TODAY
A5: Today | D5: =TODAY() -> 46310 | F5: Week to show (0 = this week, 1 = next, −1 = last) | H5: 0 | J5: =COUNTIFS(Events!$A$5:$A$304,TODAY(),Events!$K$5:$K$304,">="&$AC$5)&" event(s) today" -> 11 event(s) today | AC5: =IF($D$6="High only",3,IF($D$6="High + Medium",2,1)) -> 2
A6: Show events | D6: High + Medium | F6: Week starting (Monday) | H6: =TODAY()-WEEKDAY(TODAY(),3)+IF(WEEKDAY(TODAY(),2)>5,7,0)+7*$H$5 -> 46307
A7: Next high-impact event | D7: =IFERROR(INDEX(Events!$C$5:$C$304,MATCH(_xlfn.MINIFS(Events!$L$5:$L$304,Events!$D$5:$D$304,"High",Events!$L$5:$L$304,">="&NOW()),Events!$L$5:$L$304,0))&" "&INDEX(Events!$F$5:$F$304,MATCH(_xlfn.MINIFS(Events!$L$5:$L$304,Events!$D$5:$D$304,"High",Events!$L$5:$L$304,">="&NOW()),Events!$L$5:$L$304,0))&" — "&TEXT(_xlfn.MINIFS(Events!$L$5:$L$304,Events!$D$5:$D$304,"High",Events!$L$5:$L$304,">="&NOW()),"ddd d mmm hh:mm")&" (in "&INT(_xlfn.MINIFS(Events!$L$5:$L$304,Events!$D$5:$D$304,"High",Events!$L$5:$L$304,">="&NOW()))-TODAY()&" days)","none scheduled") -> USD Core PPI m/m — Thu 15 Oct 14:30 (in 0 days)
A9: THIS WEEK | M9: MONTH AT A GLANCE
A10: # | B10: =$H$6+0 -> 46307 | D10: =$H$6+1 -> 46308 | F10: =$H$6+2 -> 46309 | H10: =$H$6+3 -> 46310 | J10: =$H$6+4 -> 46311 | M10: =TEXT(DATE(YEAR($H$6),MONTH($H$6),1),"mmmm yyyy") -> October 2026 | U10: =TEXT(EDATE(DATE(YEAR($H$6),MONTH($H$6),1),1),"mmmm yyyy") -> November 2026
A11: 1 | B11: =IF($AC11="","",IFERROR(INDEX({"CB","SPK","GOV","INF","JOB","BIZ","HOL"},MATCH(INDEX(Events!$E$5:$E$304,$AC11),{"Central bank","CB speech","Government","Inflation","Jobs","Growth & business","Holiday"},0)),"?")) -> HOL | C11: =IF($AC11="","",IF(INDEX(Events!$D$5:$D$304,$AC11)="High","● ",IF(INDEX(Events!$D$5:$D$304,$AC11)="Medium","○ "," "))&IF(INDEX(Events!$B$5:$B$304,$AC11)="","all day",TEXT(INDEX(Events!$B$5:$B$304,$AC11),"hh:mm"))&" "&INDEX(Events!$C$5:$C$304,$AC11)&" "&INDEX(Events!$F$5:$F$304,$AC11)) -> all day JPY Bank Holiday | D11: =IF($AD11="","",IFERROR(INDEX({"CB","SPK","GOV","INF","JOB","BIZ","HOL"},MATCH(INDEX(Events!$E$5:$E$304,$AD11),{"Central bank","CB speech","Government","Inflation","Jobs","Growth & business","Holiday"},0)),"?")) | E11: =IF($AD11="","",IF(INDEX(Events!$D$5:$D$304,$AD11)="High","● ",IF(INDEX(Events!$D$5:$D$304,$AD11)="Medium","○ "," "))&IF(INDEX(Events!$B$5:$B$304,$AD11)="","all day",TEXT(INDEX(Events!$B$5:$B$304,$AD11),"hh:mm"))&" "&INDEX(Events!$C$5:$C$304,$AD11)&" "&INDEX(Events!$F$5:$F$304,$AD11)) | F11: =IF($AE11="","",IFERROR(INDEX({"CB","SPK","GOV","INF","JOB","BIZ","HOL"},MATCH(INDEX(Events!$E$5:$E$304,$AE11),{"Central bank","CB speech","Government","Inflation","Jobs","Growth & business","Holiday"},0)),"?")) -> SPK | G11: =IF($AE11="","",IF(INDEX(Events!$D$5:$D$304,$AE11)="High","● ",IF(INDEX(Events!$D$5:$D$304,$AE11)="Medium","○ "," "))&IF(INDEX(Events!$B$5:$B$304,$AE11)="","all day",TEXT(INDEX(Events!$B$5:$B$304,$AE11),"hh:mm"))&" "&INDEX(Events!$C$5:$C$304,$AE11)&" "&INDEX(Events!$F$5:$F$304,$AE11)) -> ○ 04:10 EUR ECB President Lagarde Speaks | H11: =IF($AF11="","",IFERROR(INDEX({"CB","SPK","GOV","INF","JOB","BIZ","HOL"},MATCH(INDEX(Events!$E$5:$E$304,$AF11),{"Central bank","CB speech","Government","Inflation","Jobs","Growth & business","Holiday"},0)),"?")) -> JOB | I11: =IF($AF11="","",IF(INDEX(Events!$D$5:$D$304,$AF11)="High","● ",IF(INDEX(Events!$D$5:$D$304,$AF11)="Medium","○ "," "))&IF(INDEX(Events!$B$5:$B$304,$AF11)="","all day",TEXT(INDEX(Events!$B$5:$B$304,$AF11),"hh:mm"))&" "&INDEX(Events!$C$5:$C$304,$AF11)&" "&INDEX(Events!$F$5:$F$304,$AF11)) -> ● 02:30 AUD Employment Change | J11: =IF($AG11="","",IFERROR(INDEX({"CB","SPK","GOV","INF","JOB","BIZ","HOL"},MATCH(INDEX(Events!$E$5:$E$304,$AG11),{"Central bank","CB speech","Government","Inflation","Jobs","Growth & business","Holiday"},0)),"?")) -> SPK | K11: =IF($AG11="","",IF(INDEX(Events!$D$5:$D$304,$AG11)="High","● ",IF(INDEX(Events!$D$5:$D$304,$AG11)="Medium","○ "," "))&IF(INDEX(Events!$B$5:$B$304,$AG11)="","all day",TEXT(INDEX(Events!$B$5:$B$304,$AG11),"hh:mm"))&" "&INDEX(Events!$C$5:$C$304,$AG11)&" "&INDEX(Events!$F$5:$F$304,$AG11)) -> ● 04:00 GBP BOE Gov Bailey Speaks | M11: Mo | N11: Tu | O11: We | P11: Th | Q11: Fr | R11: Sa | S11: Su | U11: Mo | V11: Tu | W11: We | X11: Th | Y11: Fr | Z11: Sa | AA11: Su | AC11: =IFERROR(MATCH(TEXT(B$10,"yyyymmdd")&"|"&$A11,Events!$M$5:$M$304,0),"") -> 23 | AD11: =IFERROR(MATCH(TEXT(D$10,"yyyymmdd")&"|"&$A11,Events!$M$5:$M$304,0),"") | AE11: =IFERROR(MATCH(TEXT(F$10,"yyyymmdd")&"|"&$A11,Events!$M$5:$M$304,0),"") -> 25 | AF11: =IFERROR(MATCH(TEXT(H$10,"yyyymmdd")&"|"&$A11,Events!$M$5:$M$304,0),"") -> 33 | AG11: =IFERROR(MATCH(TEXT(J$10,"yyyymmdd")&"|"&$A11,Events!$M$5:$M$304,0),"") -> 44
A12: 2 | B12: =IF($AC12="","",IFERROR(INDEX({"CB","SPK","GOV","INF","JOB","BIZ","HOL"},MATCH(INDEX(Events!$E$5:$E$304,$AC12),{"Central bank","CB speech","Government","Inflation","Jobs","Growth & business","Holiday"},0)),"?")) -> HOL | C12: =IF($AC12="","",IF(INDEX(Events!$D$5:$D$304,$AC12)="High","● ",IF(INDEX(Events!$D$5:$D$304,$AC12)="Medium","○ "," "))&IF(INDEX(Events!$B$5:$B$304,$AC12)="","all day",TEXT(INDEX(Events!$B$5:$B$304,$AC12),"hh:mm"))&" "&INDEX(Events!$C$5:$C$304,$AC12)&" "&INDEX(Events!$F$5:$F$304,$AC12)) -> all day USD Bank Holiday | D12: =IF($AD12="","",IFERROR(INDEX({"CB","SPK","GOV","INF","JOB","BIZ","HOL"},MATCH(INDEX(Events!$E$5:$E$304,$AD12),{"Central bank","CB speech","Government","Inflation","Jobs","Growth & business","Holiday"},0)),"?")) | E12: =IF($AD12="","",IF(INDEX(Events!$D$5:$D$304,$AD12)="High","● ",IF(INDEX(Events!$D$5:$D$304,$AD12)="Medium","○ "," "))&IF(INDEX(Events!$B$5:$B$304,$AD12)="","all day",TEXT(INDEX(Events!$B$5:$B$304,$AD12),"hh:mm"))&" "&INDEX(Events!$C$5:$C$304,$AD12)&" "&INDEX(Events!$F$5:$F$304,$AD12)) | F12: =IF($AE12="","",IFERROR(INDEX({"CB","SPK","GOV","INF","JOB","BIZ","HOL"},MATCH(INDEX(Events!$E$5:$E$304,$AE12),{"Central bank","CB speech","Government","Inflation","Jobs","Growth & business","Holiday"},0)),"?")) -> SPK | G12: =IF($AE12="","",IF(INDEX(Events!$D$5:$D$304,$AE12)="High","● ",IF(INDEX(Events!$D$5:$D$304,$AE12)="Medium","○ "," "))&IF(INDEX(Events!$B$5:$B$304,$AE12)="","all day",TEXT(INDEX(Events!$B$5:$B$304,$AE12),"hh:mm"))&" "&INDEX(Events!$C$5:$C$304,$AE12)&" "&INDEX(Events!$F$5:$F$304,$AE12)) -> ○ 07:30 GBP BOE Gov Bailey Speaks | H12: =IF($AF12="","",IFERROR(INDEX({"CB","SPK","GOV","INF","JOB","BIZ","HOL"},MATCH(INDEX(Events!$E$5:$E$304,$AF12),{"Central bank","CB speech","Government","Inflation","Jobs","Growth & business","Holiday"},0)),"?")) -> JOB | I12: =IF($AF12="","",IF(INDEX(Events!$D$5:$D$304,$AF12)="High","● ",IF(INDEX(Events!$D$5:$D$304,$AF12)="Medium","○ "," "))&IF(INDEX(Events!$B$5:$B$304,$AF12)="","all day",TEXT(INDEX(Events!$B$5:$B$304,$AF12),"hh:mm"))&" "&INDEX(Events!$C$5:$C$304,$AF12)&" "&INDEX(Events!$F$5:$F$304,$AF12)) -> ● 02:30 AUD Unemployment Rate | J12: =IF($AG12="","",IFERROR(INDEX({"CB","SPK","GOV","INF","JOB","BIZ","HOL"},MATCH(INDEX(Events!$E$5:$E$304,$AG12),{"Central bank","CB speech","Government","Inflation","Jobs","Growth & business","Holiday"},0)),"?")) -> SPK | K12: =IF($AG12="","",IF(INDEX(Events!$D$5:$D$304,$AG12)="High","● ",IF(INDEX(Events!$D$5:$D$304,$AG12)="Medium","○ "," "))&IF(INDEX(Events!$B$5:$B$304,$AG12)="","all day",TEXT(INDEX(Events!$B$5:$B$304,$AG12),"hh:mm"))&" "&INDEX(Events!$C$5:$C$304,$AG12)&" "&INDEX(Events!$F$5:$F$304,$AG12)) -> ● 05:30 USD Fed Chairman Warsh Speaks | M12: =(DATE(YEAR($H$6),MONTH($H$6),1)-WEEKDAY(DATE(YEAR($H$6),MONTH($H$6),1),3))+0 -> 46293 | N12: =(DATE(YEAR($H$6),MONTH($H$6),1)-WEEKDAY(DATE(YEAR($H$6),MONTH($H$6),1),3))+1 -> 46294 | O12: =(DATE(YEAR($H$6),MONTH($H$6),1)-WEEKDAY(DATE(YEAR($H$6),MONTH($H$6),1),3))+2 -> 46295 | P12: =(DATE(YEAR($H$6),MONTH($H$6),1)-WEEKDAY(DATE(YEAR($H$6),MONTH($H$6),1),3))+3 -> 46296 | Q12: =(DATE(YEAR($H$6),MONTH($H$6),1)-WEEKDAY(DATE(YEAR($H$6),MONTH($H$6),1),3))+4 -> 46297 | R12: =(DATE(YEAR($H$6),MONTH($H$6),1)-WEEKDAY(DATE(YEAR($H$6),MONTH($H$6),1),3))+5 -> 46298 | S12: =(DATE(YEAR($H$6),MONTH($H$6),1)-WEEKDAY(DATE(YEAR($H$6),MONTH($H$6),1),3))+6 -> 46299 | U12: =(EDATE(DATE(YEAR($H$6),MONTH($H$6),1),1)-WEEKDAY(EDATE(DATE(YEAR($H$6),MONTH($H$6),1),1),3))+0 -> 46321 | V12: =(EDATE(DATE(YEAR($H$6),MONTH($H$6),1),1)-WEEKDAY(EDATE(DATE(YEAR($H$6),MONTH($H$6),1),1),3))+1 -> 46322 | W12: =(EDATE(DATE(YEAR($H$6),MONTH($H$6),1),1)-WEEKDAY(EDATE(DATE(YEAR($H$6),MONTH($H$6),1),1),3))+2 -> 46323 | X12: =(EDATE(DATE(YEAR($H$6),MONTH($H$6),1),1)-WEEKDAY(EDATE(DATE(YEAR($H$6),MONTH($H$6),1),1),3))+3 -> 46324 | Y12: =(EDATE(DATE(YEAR($H$6),MONTH($H$6),1),1)-WEEKDAY(EDATE(DATE(YEAR($H$6),MONTH($H$6),1),1),3))+4 -> 46325 | Z12: =(EDATE(DATE(YEAR($H$6),MONTH($H$6),1),1)-WEEKDAY(EDATE(DATE(YEAR($H$6),MONTH($H$6),1),1),3))+5 -> 46326 | AA12: =(EDATE(DATE(YEAR($H$6),MONTH($H$6),1),1)-WEEKDAY(EDATE(DATE(YEAR($H$6),MONTH($H$6),1),1),3))+6 -> 46327 | AC12: =IFERROR(MATCH(TEXT(B$10,"yyyymmdd")&"|"&$A12,Events!$M$5:$M$304,0),"") -> 24 | AD12: =IFERROR(MATCH(TEXT(D$10,"yyyymmdd")&"|"&$A12,Events!$M$5:$M$304,0),"") | AE12: =IFERROR(MATCH(TEXT(F$10,"yyyymmdd")&"|"&$A12,Events!$M$5:$M$304,0),"") -> 26 | AF12: =IFERROR(MATCH(TEXT(H$10,"yyyymmdd")&"|"&$A12,Events!$M$5:$M$304,0),"") -> 34 | AG12: =IFERROR(MATCH(TEXT(J$10,"yyyymmdd")&"|"&$A12,Events!$M$5:$M$304,0),"") -> 45
A13: 3 | B13: =IF($AC13="","",IFERROR(INDEX({"CB","SPK","GOV","INF","JOB","BIZ","HOL"},MATCH(INDEX(Events!$E$5:$E$304,$AC13),{"Central bank","CB speech","Government","Inflation","Jobs","Growth & business","Holiday"},0)),"?")) | C13: =IF($AC13="","",IF(INDEX(Events!$D$5:$D$304,$AC13)="High","● ",IF(INDEX(Events!$D$5:$D$304,$AC13)="Medium","○ "," "))&IF(INDEX(Events!$B$5:$B$304,$AC13)="","all day",TEXT(INDEX(Events!$B$5:$B$304,$AC13),"hh:mm"))&" "&INDEX(Events!$C$5:$C$304,$AC13)&" "&INDEX(Events!$F$5:$F$304,$AC13)) | D13: =IF($AD13="","",IFERROR(INDEX({"CB","SPK","GOV","INF","JOB","BIZ","HOL"},MATCH(INDEX(Events!$E$5:$E$304,$AD13),{"Central bank","CB speech","Government","Inflation","Jobs","Growth & business","Holiday"},0)),"?")) | E13: =IF($AD13="","",IF(INDEX(Events!$D$5:$D$304,$AD13)="High","● ",IF(INDEX(Events!$D$5:$D$304,$AD13)="Medium","○ "," "))&IF(INDEX(Events!$B$5:$B$304,$AD13)="","all day",TEXT(INDEX(Events!$B$5:$B$304,$AD13),"hh:mm"))&" "&INDEX(Events!$C$5:$C$304,$AD13)&" "&INDEX(Events!$F$5:$F$304,$AD13)) | F13: =IF($AE13="","",IFERROR(INDEX({"CB","SPK","GOV","INF","JOB","BIZ","HOL"},MATCH(INDEX(Events!$E$5:$E$304,$AE13),{"Central bank","CB speech","Government","Inflation","Jobs","Growth & business","Holiday"},0)),"?")) -> SPK | G13: =IF($AE13="","",IF(INDEX(Events!$D$5:$D$304,$AE13)="High","● ",IF(INDEX(Events!$D$5:$D$304,$AE13)="Medium","○ "," "))&IF(INDEX(Events!$B$5:$B$304,$AE13)="","all day",TEXT(INDEX(Events!$B$5:$B$304,$AE13),"hh:mm"))&" "&INDEX(Events!$C$5:$C$304,$AE13)&" "&INDEX(Events!$F$5:$F$304,$AE13)) -> ○ 10:30 EUR ECB President Lagarde Speaks | H13: =IF($AF13="","",IFERROR(INDEX({"CB","SPK","GOV","INF","JOB","BIZ","HOL"},MATCH(INDEX(Events!$E$5:$E$304,$AF13),{"Central bank","CB speech","Government","Inflation","Jobs","Growth & business","Holiday"},0)),"?")) -> BIZ | I13: =IF($AF13="","",IF(INDEX(Events!$D$5:$D$304,$AF13)="High","● ",IF(INDEX(Events!$D$5:$D$304,$AF13)="Medium","○ "," "))&IF(INDEX(Events!$B$5:$B$304,$AF13)="","all day",TEXT(INDEX(Events!$B$5:$B$304,$AF13),"hh:mm"))&" "&INDEX(Events!$C$5:$C$304,$AF13)&" "&INDEX(Events!$F$5:$F$304,$AF13)) -> ● 08:00 GBP GDP m/m | J13: =IF($AG13="","",IFERROR(INDEX({"CB","SPK","GOV","INF","JOB","BIZ","HOL"},MATCH(INDEX(Events!$E$5:$E$304,$AG13),{"Central bank","CB speech","Government","Inflation","Jobs","Growth & business","Holiday"},0)),"?")) | K13: =IF($AG13="","",IF(INDEX(Events!$D$5:$D$304,$AG13)="High","● ",IF(INDEX(Events!$D$5:$D$304,$AG13)="Medium","○ "," "))&IF(INDEX(Events!$B$5:$B$304,$AG13)="","all day",TEXT(INDEX(Events!$B$5:$B$304,$AG13),"hh:mm"))&" "&INDEX(Events!$C$5:$C$304,$AG13)&" "&INDEX(Events!$F$5:$F$304,$AG13)) | M13: =(DATE(YEAR($H$6),MONTH($H$6),1)-WEEKDAY(DATE(YEAR($H$6),MONTH($H$6),1),3))+7 -> 46300 | N13: =(DATE(YEAR($H$6),MONTH($H$6),1)-WEEKDAY(DATE(YEAR($H$6),MONTH($H$6),1),3))+8 -> 46301 | O13: =(DATE(YEAR($H$6),MONTH($H$6),1)-WEEKDAY(DATE(YEAR($H$6),MONTH($H$6),1),3))+9 -> 46302 | P13: =(DATE(YEAR($H$6),MONTH($H$6),1)-WEEKDAY(DATE(YEAR($H$6),MONTH($H$6),1),3))+10 -> 46303 | Q13: =(DATE(YEAR($H$6),MONTH($H$6),1)-WEEKDAY(DATE(YEAR($H$6),MONTH($H$6),1),3))+11 -> 46304 | R13: =(DATE(YEAR($H$6),MONTH($H$6),1)-WEEKDAY(DATE(YEAR($H$6),MONTH($H$6),1),3))+12 -> 46305 | S13: =(DATE(YEAR($H$6),MONTH($H$6),1)-WEEKDAY(DATE(YEAR($H$6),MONTH($H$6),1),3))+13 -> 46306 | U13: =(EDATE(DATE(YEAR($H$6),MONTH($H$6),1),1)-WEEKDAY(EDATE(DATE(YEAR($H$6),MONTH($H$6),1),1),3))+7 -> 46328 | V13: =(EDATE(DATE(YEAR($H$6),MONTH($H$6),1),1)-WEEKDAY(EDATE(DATE(YEAR($H$6),MONTH($H$6),1),1),3))+8 -> 46329 | W13: =(EDATE(DATE(YEAR($H$6),MONTH($H$6),1),1)-WEEKDAY(EDATE(DATE(YEAR($H$6),MONTH($H$6),1),1),3))+9 -> 46330 | X13: =(EDATE(DATE(YEAR($H$6),MONTH($H$6),1),1)-WEEKDAY(EDATE(DATE(YEAR($H$6),MONTH($H$6),1),1),3))+10 -> 46331 | Y13: =(EDATE(DATE(YEAR($H$6),MONTH($H$6),1),1)-WEEKDAY(EDATE(DATE(YEAR($H$6),MONTH($H$6),1),1),3))+11 -> 46332 | Z13: =(EDATE(DATE(YEAR($H$6),MONTH($H$6),1),1)-WEEKDAY(EDATE(DATE(YEAR($H$6),MONTH($H$6),1),1),3))+12 -> 46333 | AA13: =(EDATE(DATE(YEAR($H$6),MONTH($H$6),1),1)-WEEKDAY(EDATE(DATE(YEAR($H$6),MONTH($H$6),1),1),3))+13 -> 46334 | AC13: =IFERROR(MATCH(TEXT(B$10,"yyyymmdd")&"|"&$A13,Events!$M$5:$M$304,0),"") | AD13: =IFERROR(MATCH(TEXT(D$10,"yyyymmdd")&"|"&$A13,Events!$M$5:$M$304,0),"") | AE13: =IFERROR(MATCH(TEXT(F$10,"yyyymmdd")&"|"&$A13,Events!$M$5:$M$304,0),"") -> 27 | AF13: =IFERROR(MATCH(TEXT(H$10,"yyyymmdd")&"|"&$A13,Events!$M$5:$M$304,0),"") -> 35 | AG13: =IFERROR(MATCH(TEXT(J$10,"yyyymmdd")&"|"&$A13,Events!$M$5:$M$304,0),"")
A14: 4 | B14: =IF($AC14="","",IFERROR(INDEX({"CB","SPK","GOV","INF","JOB","BIZ","HOL"},MATCH(INDEX(Events!$E$5:$E$304,$AC14),{"Central bank","CB speech","Government","Inflation","Jobs","Growth & business","Holiday"},0)),"?")) | C14: =IF($AC14="","",IF(INDEX(Events!$D$5:$D$304,$AC14)="High","● ",IF(INDEX(Events!$D$5:$D$304,$AC14)="Medium","○ "," "))&IF(INDEX(Events!$B$5:$B$304,$AC14)="","all day",TEXT(INDEX(Events!$B$5:$B$304,$AC14),"hh:mm"))&" "&INDEX(Events!$C$5:$C$304,$AC14)&" "&INDEX(Events!$F$5:$F$304,$AC14)) | D14: =IF($AD14="","",IFERROR(INDEX({"CB","SPK","GOV","INF","JOB","BIZ","HOL"},MATCH(INDEX(Events!$E$5:$E$304,$AD14),{"Central bank","CB speech","Government","Inflation","Jobs","Growth & business","Holiday"},0)),"?")) | E14: =IF($AD14="","",IF(INDEX(Events!$D$5:$D$304,$AD14)="High","● ",IF(INDEX(Events!$D$5:$D$304,$AD14)="Medium","○ "," "))&IF(INDEX(Events!$B$5:$B$304,$AD14)="","all day",TEXT(INDEX(Events!$B$5:$B$304,$AD14),"hh:mm"))&" "&INDEX(Events!$C$5:$C$304,$AD14)&" "&INDEX(Events!$F$5:$F$304,$AD14)) | F14: =IF($AE14="","",IFERROR(INDEX({"CB","SPK","GOV","INF","JOB","BIZ","HOL"},MATCH(INDEX(Events!$E$5:$E$304,$AE14),{"Central bank","CB speech","Government","Inflation","Jobs","Growth & business","Holiday"},0)),"?")) -> GOV | G14: =IF($AE14="","",IF(INDEX(Events!$D$5:$D$304,$AE14)="High","● ",IF(INDEX(Events!$D$5:$D$304,$AE14)="Medium","○ "," "))&IF(INDEX(Events!$B$5:$B$304,$AE14)="","all day",TEXT(INDEX(Events!$B$5:$B$304,$AE14),"hh:mm"))&" "&INDEX(Events!$C$5:$C$304,$AE14)&" "&INDEX(Events!$F$5:$F$304,$AE14)) -> ○ 12:15 EUR EU Economic Summit | H14: =IF($AF14="","",IFERROR(INDEX({"CB","SPK","GOV","INF","JOB","BIZ","HOL"},MATCH(INDEX(Events!$E$5:$E$304,$AF14),{"Central bank","CB speech","Government","Inflation","Jobs","Growth & business","Holiday"},0)),"?")) -> SPK | I14: =IF($AF14="","",IF(INDEX(Events!$D$5:$D$304,$AF14)="High","● ",IF(INDEX(Events!$D$5:$D$304,$AF14)="Medium","○ "," "))&IF(INDEX(Events!$B$5:$B$304,$AF14)="","all day",TEXT(INDEX(Events!$B$5:$B$304,$AF14),"hh:mm"))&" "&INDEX(Events!$C$5:$C$304,$AF14)&" "&INDEX(Events!$F$5:$F$304,$AF14)) -> ○ 09:30 GBP BOE Gov Bailey Speaks | J14: =IF($AG14="","",IFERROR(INDEX({"CB","SPK","GOV","INF","JOB","BIZ","HOL"},MATCH(INDEX(Events!$E$5:$E$304,$AG14),{"Central bank","CB speech","Government","Inflation","Jobs","Growth & business","Holiday"},0)),"?")) | K14: =IF($AG14="","",IF(INDEX(Events!$D$5:$D$304,$AG14)="High","● ",IF(INDEX(Events!$D$5:$D$304,$AG14)="Medium","○ "," "))&IF(INDEX(Events!$B$5:$B$304,$AG14)="","all day",TEXT(INDEX(Events!$B$5:$B$304,$AG14),"hh:mm"))&" "&INDEX(Events!$C$5:$C$304,$AG14)&" "&INDEX(Events!$F$5:$F$304,$AG14)) | M14: =(DATE(YEAR($H$6),MONTH($H$6),1)-WEEKDAY(DATE(YEAR($H$6),MONTH($H$6),1),3))+14 -> 46307 | N14: =(DATE(YEAR($H$6),MONTH($H$6),1)-WEEKDAY(DATE(YEAR($H$6),MONTH($H$6),1),3))+15 -> 46308 | O14: =(DATE(YEAR($H$6),MONTH($H$6),1)-WEEKDAY(DATE(YEAR($H$6),MONTH($H$6),1),3))+16 -> 46309 | P14: =(DATE(YEAR($H$6),MONTH($H$6),1)-WEEKDAY(DATE(YEAR($H$6),MONTH($H$6),1),3))+17 -> 46310 | Q14: =(DATE(YEAR($H$6),MONTH($H$6),1)-WEEKDAY(DATE(YEAR($H$6),MONTH($H$6),1),3))+18 -> 46311 | R14: =(DATE(YEAR($H$6),MONTH($H$6),1)-WEEKDAY(DATE(YEAR($H$6),MONTH($H$6),1),3))+19 -> 46312 | S14: =(DATE(YEAR($H$6),MONTH($H$6),1)-WEEKDAY(DATE(YEAR($H$6),MONTH($H$6),1),3))+20 -> 46313 | U14: =(EDATE(DATE(YEAR($H$6),MONTH($H$6),1),1)-WEEKDAY(EDATE(DATE(YEAR($H$6),MONTH($H$6),1),1),3))+14 -> 46335 | V14: =(EDATE(DATE(YEAR($H$6),MONTH($H$6),1),1)-WEEKDAY(EDATE(DATE(YEAR($H$6),MONTH($H$6),1),1),3))+15 -> 46336 | W14: =(EDATE(DATE(YEAR($H$6),MONTH($H$6),1),1)-WEEKDAY(EDATE(DATE(YEAR($H$6),MONTH($H$6),1),1),3))+16 -> 46337 | X14: =(EDATE(DATE(YEAR($H$6),MONTH($H$6),1),1)-WEEKDAY(EDATE(DATE(YEAR($H$6),MONTH($H$6),1),1),3))+17 -> 46338 | Y14: =(EDATE(DATE(YEAR($H$6),MONTH($H$6),1),1)-WEEKDAY(EDATE(DATE(YEAR($H$6),MONTH($H$6),1),1),3))+18 -> 46339 | Z14: =(EDATE(DATE(YEAR($H$6),MONTH($H$6),1),1)-WEEKDAY(EDATE(DATE(YEAR($H$6),MONTH($H$6),1),1),3))+19 -> 46340 | AA14: =(EDATE(DATE(YEAR($H$6),MONTH($H$6),1),1)-WEEKDAY(EDATE(DATE(YEAR($H$6),MONTH($H$6),1),1),3))+20 -> 46341 | AC14: =IFERROR(MATCH(TEXT(B$10,"yyyymmdd")&"|"&$A14,Events!$M$5:$M$304,0),"") | AD14: =IFERROR(MATCH(TEXT(D$10,"yyyymmdd")&"|"&$A14,Events!$M$5:$M$304,0),"") | AE14: =IFERROR(MATCH(TEXT(F$10,"yyyymmdd")&"|"&$A14,Events!$M$5:$M$304,0),"") -> 28 | AF14: =IFERROR(MATCH(TEXT(H$10,"yyyymmdd")&"|"&$A14,Events!$M$5:$M$304,0),"") -> 36 | AG14: =IFERROR(MATCH(TEXT(J$10,"yyyymmdd")&"|"&$A14,Events!$M$5:$M$304,0),"")
A15: 5 | B15: =IF($AC15="","",IFERROR(INDEX({"CB","SPK","GOV","INF","JOB","BIZ","HOL"},MATCH(INDEX(Events!$E$5:$E$304,$AC15),{"Central bank","CB speech","Government","Inflation","Jobs","Growth & business","Holiday"},0)),"?")) | C15: =IF($AC15="","",IF(INDEX(Events!$D$5:$D$304,$AC15)="High","● ",IF(INDEX(Events!$D$5:$D$304,$AC15)="Medium","○ "," "))&IF(INDEX(Events!$B$5:$B$304,$AC15)="","all day",TEXT(INDEX(Events!$B$5:$B$304,$AC15),"hh:mm"))&" "&INDEX(Events!$C$5:$C$304,$AC15)&" "&INDEX(Events!$F$5:$F$304,$AC15)) | D15: =IF($AD15="","",IFERROR(INDEX({"CB","SPK","GOV","INF","JOB","BIZ","HOL"},MATCH(INDEX(Events!$E$5:$E$304,$AD15),{"Central bank","CB speech","Government","Inflation","Jobs","Growth & business","Holiday"},0)),"?")) | E15: =IF($AD15="","",IF(INDEX(Events!$D$5:$D$304,$AD15)="High","● ",IF(INDEX(Events!$D$5:$D$304,$AD15)="Medium","○ "," "))&IF(INDEX(Events!$B$5:$B$304,$AD15)="","all day",TEXT(INDEX(Events!$B$5:$B$304,$AD15),"hh:mm"))&" "&INDEX(Events!$C$5:$C$304,$AD15)&" "&INDEX(Events!$F$5:$F$304,$AD15)) | F15: =IF($AE15="","",IFERROR(INDEX({"CB","SPK","GOV","INF","JOB","BIZ","HOL"},MATCH(INDEX(Events!$E$5:$E$304,$AE15),{"Central bank","CB speech","Government","Inflation","Jobs","Growth & business","Holiday"},0)),"?")) -> INF | G15: =IF($AE15="","",IF(INDEX(Events!$D$5:$D$304,$AE15)="High","● ",IF(INDEX(Events!$D$5:$D$304,$AE15)="Medium","○ "," "))&IF(INDEX(Events!$B$5:$B$304,$AE15)="","all day",TEXT(INDEX(Events!$B$5:$B$304,$AE15),"hh:mm"))&" "&INDEX(Events!$C$5:$C$304,$AE15)&" "&INDEX(Events!$F$5:$F$304,$AE15)) -> ● 14:30 USD Core CPI m/m | H15: =IF($AF15="","",IFERROR(INDEX({"CB","SPK","GOV","INF","JOB","BIZ","HOL"},MATCH(INDEX(Events!$E$5:$E$304,$AF15),{"Central bank","CB speech","Government","Inflation","Jobs","Growth & business","Holiday"},0)),"?")) -> GOV | I15: =IF($AF15="","",IF(INDEX(Events!$D$5:$D$304,$AF15)="High","● ",IF(INDEX(Events!$D$5:$D$304,$AF15)="Medium","○ "," "))&IF(INDEX(Events!$B$5:$B$304,$AF15)="","all day",TEXT(INDEX(Events!$B$5:$B$304,$AF15),"hh:mm"))&" "&INDEX(Events!$C$5:$C$304,$AF15)&" "&INDEX(Events!$F$5:$F$304,$AF15)) -> ○ 12:15 EUR EU Economic Summit | J15: =IF($AG15="","",IFERROR(INDEX({"CB","SPK","GOV","INF","JOB","BIZ","HOL"},MATCH(INDEX(Events!$E$5:$E$304,$AG15),{"Central bank","CB speech","Government","Inflation","Jobs","Growth & business","Holiday"},0)),"?")) | K15: =IF($AG15="","",IF(INDEX(Events!$D$5:$D$304,$AG15)="High","● ",IF(INDEX(Events!$D$5:$D$304,$AG15)="Medium","○ "," "))&IF(INDEX(Events!$B$5:$B$304,$AG15)="","all day",TEXT(INDEX(Events!$B$5:$B$304,$AG15),"hh:mm"))&" "&INDEX(Events!$C$5:$C$304,$AG15)&" "&INDEX(Events!$F$5:$F$304,$AG15)) | M15: =(DATE(YEAR($H$6),MONTH($H$6),1)-WEEKDAY(DATE(YEAR($H$6),MONTH($H$6),1),3))+21 -> 46314 | N15: =(DATE(YEAR($H$6),MONTH($H$6),1)-WEEKDAY(DATE(YEAR($H$6),MONTH($H$6),1),3))+22 -> 46315 | O15: =(DATE(YEAR($H$6),MONTH($H$6),1)-WEEKDAY(DATE(YEAR($H$6),MONTH($H$6),1),3))+23 -> 46316 | P15: =(DATE(YEAR($H$6),MONTH($H$6),1)-WEEKDAY(DATE(YEAR($H$6),MONTH($H$6),1),3))+24 -> 46317 | Q15: =(DATE(YEAR($H$6),MONTH($H$6),1)-WEEKDAY(DATE(YEAR($H$6),MONTH($H$6),1),3))+25 -> 46318 | R15: =(DATE(YEAR($H$6),MONTH($H$6),1)-WEEKDAY(DATE(YEAR($H$6),MONTH($H$6),1),3))+26 -> 46319 | S15: =(DATE(YEAR($H$6),MONTH($H$6),1)-WEEKDAY(DATE(YEAR($H$6),MONTH($H$6),1),3))+27 -> 46320 | U15: =(EDATE(DATE(YEAR($H$6),MONTH($H$6),1),1)-WEEKDAY(EDATE(DATE(YEAR($H$6),MONTH($H$6),1),1),3))+21 -> 46342 | V15: =(EDATE(DATE(YEAR($H$6),MONTH($H$6),1),1)-WEEKDAY(EDATE(DATE(YEAR($H$6),MONTH($H$6),1),1),3))+22 -> 46343 | W15: =(EDATE(DATE(YEAR($H$6),MONTH($H$6),1),1)-WEEKDAY(EDATE(DATE(YEAR($H$6),MONTH($H$6),1),1),3))+23 -> 46344 | X15: =(EDATE(DATE(YEAR($H$6),MONTH($H$6),1),1)-WEEKDAY(EDATE(DATE(YEAR($H$6),MONTH($H$6),1),1),3))+24 -> 46345 | Y15: =(EDATE(DATE(YEAR($H$6),MONTH($H$6),1),1)-WEEKDAY(EDATE(DATE(YEAR($H$6),MONTH($H$6),1),1),3))+25 -> 46346 | Z15: =(EDATE(DATE(YEAR($H$6),MONTH($H$6),1),1)-WEEKDAY(EDATE(DATE(YEAR($H$6),MONTH($H$6),1),1),3))+26 -> 46347 | AA15: =(EDATE(DATE(YEAR($H$6),MONTH($H$6),1),1)-WEEKDAY(EDATE(DATE(YEAR($H$6),MONTH($H$6),1),1),3))+27 -> 46348 | AC15: =IFERROR(MATCH(TEXT(B$10,"yyyymmdd")&"|"&$A15,Events!$M$5:$M$304,0),"") | AD15: =IFERROR(MATCH(TEXT(D$10,"yyyymmdd")&"|"&$A15,Events!$M$5:$M$304,0),"") | AE15: =IFERROR(MATCH(TEXT(F$10,"yyyymmdd")&"|"&$A15,Events!$M$5:$M$304,0),"") -> 29 | AF15: =IFERROR(MATCH(TEXT(H$10,"yyyymmdd")&"|"&$A15,Events!$M$5:$M$304,0),"") -> 37 | AG15: =IFERROR(MATCH(TEXT(J$10,"yyyymmdd")&"|"&$A15,Events!$M$5:$M$304,0),"")
A16: 6 | B16: =IF($AC16="","",IFERROR(INDEX({"CB","SPK","GOV","INF","JOB","BIZ","HOL"},MATCH(INDEX(Events!$E$5:$E$304,$AC16),{"Central bank","CB speech","Government","Inflation","Jobs","Growth & business","Holiday"},0)),"?")) | C16: =IF($AC16="","",IF(INDEX(Events!$D$5:$D$304,$AC16)="High","● ",IF(INDEX(Events!$D$5:$D$304,$AC16)="Medium","○ "," "))&IF(INDEX(Events!$B$5:$B$304,$AC16)="","all day",TEXT(INDEX(Events!$B$5:$B$304,$AC16),"hh:mm"))&" "&INDEX(Events!$C$5:$C$304,$AC16)&" "&INDEX(Events!$F$5:$F$304,$AC16)) | D16: =IF($AD16="","",IFERROR(INDEX({"CB","SPK","GOV","INF","JOB","BIZ","HOL"},MATCH(INDEX(Events!$E$5:$E$304,$AD16),{"Central bank","CB speech","Government","Inflation","Jobs","Growth & business","Holiday"},0)),"?")) | E16: =IF($AD16="","",IF(INDEX(Events!$D$5:$D$304,$AD16)="High","● ",IF(INDEX(Events!$D$5:$D$304,$AD16)="Medium","○ "," "))&IF(INDEX(Events!$B$5:$B$304,$AD16)="","all day",TEXT(INDEX(Events!$B$5:$B$304,$AD16),"hh:mm"))&" "&INDEX(Events!$C$5:$C$304,$AD16)&" "&INDEX(Events!$F$5:$F$304,$AD16)) | F16: =IF($AE16="","",IFERROR(INDEX({"CB","SPK","GOV","INF","JOB","BIZ","HOL"},MATCH(INDEX(Events!$E$5:$E$304,$AE16),{"Central bank","CB speech","Government","Inflation","Jobs","Growth & business","Holiday"},0)),"?")) -> INF | G16: =IF($AE16="","",IF(INDEX(Events!$D$5:$D$304,$AE16)="High","● ",IF(INDEX(Events!$D$5:$D$304,$AE16)="Medium","○ "," "))&IF(INDEX(Events!$B$5:$B$304,$AE16)="","all day",TEXT(INDEX(Events!$B$5:$B$304,$AE16),"hh:mm"))&" "&INDEX(Events!$C$5:$C$304,$AE16)&" "&INDEX(Events!$F$5:$F$304,$AE16)) -> ● 14:30 USD Core CPI y/y | H16: =IF($AF16="","",IFERROR(INDEX({"CB","SPK","GOV","INF","JOB","BIZ","HOL"},MATCH(INDEX(Events!$E$5:$E$304,$AF16),{"Central bank","CB speech","Government","Inflation","Jobs","Growth & business","Holiday"},0)),"?")) -> INF | I16: =IF($AF16="","",IF(INDEX(Events!$D$5:$D$304,$AF16)="High","● ",IF(INDEX(Events!$D$5:$D$304,$AF16)="Medium","○ "," "))&IF(INDEX(Events!$B$5:$B$304,$AF16)="","all day",TEXT(INDEX(Events!$B$5:$B$304,$AF16),"hh:mm"))&" "&INDEX(Events!$C$5:$C$304,$AF16)&" "&INDEX(Events!$F$5:$F$304,$AF16)) -> ● 14:30 USD Core PPI m/m | J16: =IF($AG16="","",IFERROR(INDEX({"CB","SPK","GOV","INF","JOB","BIZ","HOL"},MATCH(INDEX(Events!$E$5:$E$304,$AG16),{"Central bank","CB speech","Government","Inflation","Jobs","Growth & business","Holiday"},0)),"?")) | K16: =IF($AG16="","",IF(INDEX(Events!$D$5:$D$304,$AG16)="High","● ",IF(INDEX(Events!$D$5:$D$304,$AG16)="Medium","○ "," "))&IF(INDEX(Events!$B$5:$B$304,$AG16)="","all day",TEXT(INDEX(Events!$B$5:$B$304,$AG16),"hh:mm"))&" "&INDEX(Events!$C$5:$C$304,$AG16)&" "&INDEX(Events!$F$5:$F$304,$AG16)) | M16: =(DATE(YEAR($H$6),MONTH($H$6),1)-WEEKDAY(DATE(YEAR($H$6),MONTH($H$6),1),3))+28 -> 46321 | N16: =(DATE(YEAR($H$6),MONTH($H$6),1)-WEEKDAY(DATE(YEAR($H$6),MONTH($H$6),1),3))+29 -> 46322 | O16: =(DATE(YEAR($H$6),MONTH($H$6),1)-WEEKDAY(DATE(YEAR($H$6),MONTH($H$6),1),3))+30 -> 46323 | P16: =(DATE(YEAR($H$6),MONTH($H$6),1)-WEEKDAY(DATE(YEAR($H$6),MONTH($H$6),1),3))+31 -> 46324 | Q16: =(DATE(YEAR($H$6),MONTH($H$6),1)-WEEKDAY(DATE(YEAR($H$6),MONTH($H$6),1),3))+32 -> 46325 | R16: =(DATE(YEAR($H$6),MONTH($H$6),1)-WEEKDAY(DATE(YEAR($H$6),MONTH($H$6),1),3))+33 -> 46326 | S16: =(DATE(YEAR($H$6),MONTH($H$6),1)-WEEKDAY(DATE(YEAR($H$6),MONTH($H$6),1),3))+34 -> 46327 | U16: =(EDATE(DATE(YEAR($H$6),MONTH($H$6),1),1)-WEEKDAY(EDATE(DATE(YEAR($H$6),MONTH($H$6),1),1),3))+28 -> 46349 | V16: =(EDATE(DATE(YEAR($H$6),MONTH($H$6),1),1)-WEEKDAY(EDATE(DATE(YEAR($H$6),MONTH($H$6),1),1),3))+29 -> 46350 | W16: =(EDATE(DATE(YEAR($H$6),MONTH($H$6),1),1)-WEEKDAY(EDATE(DATE(YEAR($H$6),MONTH($H$6),1),1),3))+30 -> 46351 | X16: =(EDATE(DATE(YEAR($H$6),MONTH($H$6),1),1)-WEEKDAY(EDATE(DATE(YEAR($H$6),MONTH($H$6),1),1),3))+31 -> 46352 | Y16: =(EDATE(DATE(YEAR($H$6),MONTH($H$6),1),1)-WEEKDAY(EDATE(DATE(YEAR($H$6),MONTH($H$6),1),1),3))+32 -> 46353 | Z16: =(EDATE(DATE(YEAR($H$6),MONTH($H$6),1),1)-WEEKDAY(EDATE(DATE(YEAR($H$6),MONTH($H$6),1),1),3))+33 -> 46354 | AA16: =(EDATE(DATE(YEAR($H$6),MONTH($H$6),1),1)-WEEKDAY(EDATE(DATE(YEAR($H$6),MONTH($H$6),1),1),3))+34 -> 46355 | AC16: =IFERROR(MATCH(TEXT(B$10,"yyyymmdd")&"|"&$A16,Events!$M$5:$M$304,0),"") | AD16: =IFERROR(MATCH(TEXT(D$10,"yyyymmdd")&"|"&$A16,Events!$M$5:$M$304,0),"") | AE16: =IFERROR(MATCH(TEXT(F$10,"yyyymmdd")&"|"&$A16,Events!$M$5:$M$304,0),"") -> 30 | AF16: =IFERROR(MATCH(TEXT(H$10,"yyyymmdd")&"|"&$A16,Events!$M$5:$M$304,0),"") -> 38 | AG16: =IFERROR(MATCH(TEXT(J$10,"yyyymmdd")&"|"&$A16,Events!$M$5:$M$304,0),"")
A17: 7 | B17: =IF($AC17="","",IFERROR(INDEX({"CB","SPK","GOV","INF","JOB","BIZ","HOL"},MATCH(INDEX(Events!$E$5:$E$304,$AC17),{"Central bank","CB speech","Government","Inflation","Jobs","Growth & business","Holiday"},0)),"?")) | C17: =IF($AC17="","",IF(INDEX(Events!$D$5:$D$304,$AC17)="High","● ",IF(INDEX(Events!$D$5:$D$304,$AC17)="Medium","○ "," "))&IF(INDEX(Events!$B$5:$B$304,$AC17)="","all day",TEXT(INDEX(Events!$B$5:$B$304,$AC17),"hh:mm"))&" "&INDEX(Events!$C$5:$C$304,$AC17)&" "&INDEX(Events!$F$5:$F$304,$AC17)) | D17: =IF($AD17="","",IFERROR(INDEX({"CB","SPK","GOV","INF","JOB","BIZ","HOL"},MATCH(INDEX(Events!$E$5:$E$304,$AD17),{"Central bank","CB speech","Government","Inflation","Jobs","Growth & business","Holiday"},0)),"?")) | E17: =IF($AD17="","",IF(INDEX(Events!$D$5:$D$304,$AD17)="High","● ",IF(INDEX(Events!$D$5:$D$304,$AD17)="Medium","○ "," "))&IF(INDEX(Events!$B$5:$B$304,$AD17)="","all day",TEXT(INDEX(Events!$B$5:$B$304,$AD17),"hh:mm"))&" "&INDEX(Events!$C$5:$C$304,$AD17)&" "&INDEX(Events!$F$5:$F$304,$AD17)) | F17: =IF($AE17="","",IFERROR(INDEX({"CB","SPK","GOV","INF","JOB","BIZ","HOL"},MATCH(INDEX(Events!$E$5:$E$304,$AE17),{"Central bank","CB speech","Government","Inflation","Jobs","Growth & business","Holiday"},0)),"?")) -> INF | G17: =IF($AE17="","",IF(INDEX(Events!$D$5:$D$304,$AE17)="High","● ",IF(INDEX(Events!$D$5:$D$304,$AE17)="Medium","○ "," "))&IF(INDEX(Events!$B$5:$B$304,$AE17)="","all day",TEXT(INDEX(Events!$B$5:$B$304,$AE17),"hh:mm"))&" "&INDEX(Events!$C$5:$C$304,$AE17)&" "&INDEX(Events!$F$5:$F$304,$AE17)) -> ● 14:30 USD CPI m/m | H17: =IF($AF17="","",IFERROR(INDEX({"CB","SPK","GOV","INF","JOB","BIZ","HOL"},MATCH(INDEX(Events!$E$5:$E$304,$AF17),{"Central bank","CB speech","Government","Inflation","Jobs","Growth & business","Holiday"},0)),"?")) -> BIZ | I17: =IF($AF17="","",IF(INDEX(Events!$D$5:$D$304,$AF17)="High","● ",IF(INDEX(Events!$D$5:$D$304,$AF17)="Medium","○ "," "))&IF(INDEX(Events!$B$5:$B$304,$AF17)="","all day",TEXT(INDEX(Events!$B$5:$B$304,$AF17),"hh:mm"))&" "&INDEX(Events!$C$5:$C$304,$AF17)&" "&INDEX(Events!$F$5:$F$304,$AF17)) -> ● 14:30 USD Core Retail Sales m/m | J17: =IF($AG17="","",IFERROR(INDEX({"CB","SPK","GOV","INF","JOB","BIZ","HOL"},MATCH(INDEX(Events!$E$5:$E$304,$AG17),{"Central bank","CB speech","Government","Inflation","Jobs","Growth & business","Holiday"},0)),"?")) | K17: =IF($AG17="","",IF(INDEX(Events!$D$5:$D$304,$AG17)="High","● ",IF(INDEX(Events!$D$5:$D$304,$AG17)="Medium","○ "," "))&IF(INDEX(Events!$B$5:$B$304,$AG17)="","all day",TEXT(INDEX(Events!$B$5:$B$304,$AG17),"hh:mm"))&" "&INDEX(Events!$C$5:$C$304,$AG17)&" "&INDEX(Events!$F$5:$F$304,$AG17)) | M17: =(DATE(YEAR($H$6),MONTH($H$6),1)-WEEKDAY(DATE(YEAR($H$6),MONTH($H$6),1),3))+35 -> 46328 | N17: =(DATE(YEAR($H$6),MONTH($H$6),1)-WEEKDAY(DATE(YEAR($H$6),MONTH($H$6),1),3))+36 -> 46329 | O17: =(DATE(YEAR($H$6),MONTH($H$6),1)-WEEKDAY(DATE(YEAR($H$6),MONTH($H$6),1),3))+37 -> 46330 | P17: =(DATE(YEAR($H$6),MONTH($H$6),1)-WEEKDAY(DATE(YEAR($H$6),MONTH($H$6),1),3))+38 -> 46331 | Q17: =(DATE(YEAR($H$6),MONTH($H$6),1)-WEEKDAY(DATE(YEAR($H$6),MONTH($H$6),1),3))+39 -> 46332 | R17: =(DATE(YEAR($H$6),MONTH($H$6),1)-WEEKDAY(DATE(YEAR($H$6),MONTH($H$6),1),3))+40 -> 46333 | S17: =(DATE(YEAR($H$6),MONTH($H$6),1)-WEEKDAY(DATE(YEAR($H$6),MONTH($H$6),1),3))+41 -> 46334 | U17: =(EDATE(DATE(YEAR($H$6),MONTH($H$6),1),1)-WEEKDAY(EDATE(DATE(YEAR($H$6),MONTH($H$6),1),1),3))+35 -> 46356 | V17: =(EDATE(DATE(YEAR($H$6),MONTH($H$6),1),1)-WEEKDAY(EDATE(DATE(YEAR($H$6),MONTH($H$6),1),1),3))+36 -> 46357 | W17: =(EDATE(DATE(YEAR($H$6),MONTH($H$6),1),1)-WEEKDAY(EDATE(DATE(YEAR($H$6),MONTH($H$6),1),1),3))+37 -> 46358 | X17: =(EDATE(DATE(YEAR($H$6),MONTH($H$6),1),1)-WEEKDAY(EDATE(DATE(YEAR($H$6),MONTH($H$6),1),1),3))+38 -> 46359 | Y17: =(EDATE(DATE(YEAR($H$6),MONTH($H$6),1),1)-WEEKDAY(EDATE(DATE(YEAR($H$6),MONTH($H$6),1),1),3))+39 -> 46360 | Z17: =(EDATE(DATE(YEAR($H$6),MONTH($H$6),1),1)-WEEKDAY(EDATE(DATE(YEAR($H$6),MONTH($H$6),1),1),3))+40 -> 46361 | AA17: =(EDATE(DATE(YEAR($H$6),MONTH($H$6),1),1)-WEEKDAY(EDATE(DATE(YEAR($H$6),MONTH($H$6),1),1),3))+41 -> 46362 | AC17: =IFERROR(MATCH(TEXT(B$10,"yyyymmdd")&"|"&$A17,Events!$M$5:$M$304,0),"") | AD17: =IFERROR(MATCH(TEXT(D$10,"yyyymmdd")&"|"&$A17,Events!$M$5:$M$304,0),"") | AE17: =IFERROR(MATCH(TEXT(F$10,"yyyymmdd")&"|"&$A17,Events!$M$5:$M$304,0),"") -> 31 | AF17: =IFERROR(MATCH(TEXT(H$10,"yyyymmdd")&"|"&$A17,Events!$M$5:$M$304,0),"") -> 39 | AG17: =IFERROR(MATCH(TEXT(J$10,"yyyymmdd")&"|"&$A17,Events!$M$5:$M$304,0),"")
A18: 8 | B18: =IF($AC18="","",IFERROR(INDEX({"CB","SPK","GOV","INF","JOB","BIZ","HOL"},MATCH(INDEX(Events!$E$5:$E$304,$AC18),{"Central bank","CB speech","Government","Inflation","Jobs","Growth & business","Holiday"},0)),"?")) | C18: =IF($AC18="","",IF(INDEX(Events!$D$5:$D$304,$AC18)="High","● ",IF(INDEX(Events!$D$5:$D$304,$AC18)="Medium","○ "," "))&IF(INDEX(Events!$B$5:$B$304,$AC18)="","all day",TEXT(INDEX(Events!$B$5:$B$304,$AC18),"hh:mm"))&" "&INDEX(Events!$C$5:$C$304,$AC18)&" "&INDEX(Events!$F$5:$F$304,$AC18)) | D18: =IF($AD18="","",IFERROR(INDEX({"CB","SPK","GOV","INF","JOB","BIZ","HOL"},MATCH(INDEX(Events!$E$5:$E$304,$AD18),{"Central bank","CB speech","Government","Inflation","Jobs","Growth & business","Holiday"},0)),"?")) | E18: =IF($AD18="","",IF(INDEX(Events!$D$5:$D$304,$AD18)="High","● ",IF(INDEX(Events!$D$5:$D$304,$AD18)="Medium","○ "," "))&IF(INDEX(Events!$B$5:$B$304,$AD18)="","all day",TEXT(INDEX(Events!$B$5:$B$304,$AD18),"hh:mm"))&" "&INDEX(Events!$C$5:$C$304,$AD18)&" "&INDEX(Events!$F$5:$F$304,$AD18)) | F18: =IF($AE18="","",IFERROR(INDEX({"CB","SPK","GOV","INF","JOB","BIZ","HOL"},MATCH(INDEX(Events!$E$5:$E$304,$AE18),{"Central bank","CB speech","Government","Inflation","Jobs","Growth & business","Holiday"},0)),"?")) -> INF | G18: =IF($AE18="","",IF(INDEX(Events!$D$5:$D$304,$AE18)="High","● ",IF(INDEX(Events!$D$5:$D$304,$AE18)="Medium","○ "," "))&IF(INDEX(Events!$B$5:$B$304,$AE18)="","all day",TEXT(INDEX(Events!$B$5:$B$304,$AE18),"hh:mm"))&" "&INDEX(Events!$C$5:$C$304,$AE18)&" "&INDEX(Events!$F$5:$F$304,$AE18)) -> ● 14:30 USD CPI y/y | H18: =IF($AF18="","",IFERROR(INDEX({"CB","SPK","GOV","INF","JOB","BIZ","HOL"},MATCH(INDEX(Events!$E$5:$E$304,$AF18),{"Central bank","CB speech","Government","Inflation","Jobs","Growth & business","Holiday"},0)),"?")) -> INF | I18: =IF($AF18="","",IF(INDEX(Events!$D$5:$D$304,$AF18)="High","● ",IF(INDEX(Events!$D$5:$D$304,$AF18)="Medium","○ "," "))&IF(INDEX(Events!$B$5:$B$304,$AF18)="","all day",TEXT(INDEX(Events!$B$5:$B$304,$AF18),"hh:mm"))&" "&INDEX(Events!$C$5:$C$304,$AF18)&" "&INDEX(Events!$F$5:$F$304,$AF18)) -> ● 14:30 USD PPI m/m | J18: =IF($AG18="","",IFERROR(INDEX({"CB","SPK","GOV","INF","JOB","BIZ","HOL"},MATCH(INDEX(Events!$E$5:$E$304,$AG18),{"Central bank","CB speech","Government","Inflation","Jobs","Growth & business","Holiday"},0)),"?")) | K18: =IF($AG18="","",IF(INDEX(Events!$D$5:$D$304,$AG18)="High","● ",IF(INDEX(Events!$D$5:$D$304,$AG18)="Medium","○ "," "))&IF(INDEX(Events!$B$5:$B$304,$AG18)="","all day",TEXT(INDEX(Events!$B$5:$B$304,$AG18),"hh:mm"))&" "&INDEX(Events!$C$5:$C$304,$AG18)&" "&INDEX(Events!$F$5:$F$304,$AG18)) | AC18: =IFERROR(MATCH(TEXT(B$10,"yyyymmdd")&"|"&$A18,Events!$M$5:$M$304,0),"") | AD18: =IFERROR(MATCH(TEXT(D$10,"yyyymmdd")&"|"&$A18,Events!$M$5:$M$304,0),"") | AE18: =IFERROR(MATCH(TEXT(F$10,"yyyymmdd")&"|"&$A18,Events!$M$5:$M$304,0),"") -> 32 | AF18: =IFERROR(MATCH(TEXT(H$10,"yyyymmdd")&"|"&$A18,Events!$M$5:$M$304,0),"") -> 40 | AG18: =IFERROR(MATCH(TEXT(J$10,"yyyymmdd")&"|"&$A18,Events!$M$5:$M$304,0),"")
A19: 9 | B19: =IF($AC19="","",IFERROR(INDEX({"CB","SPK","GOV","INF","JOB","BIZ","HOL"},MATCH(INDEX(Events!$E$5:$E$304,$AC19),{"Central bank","CB speech","Government","Inflation","Jobs","Growth & business","Holiday"},0)),"?")) | C19: =IF($AC19="","",IF(INDEX(Events!$D$5:$D$304,$AC19)="High","● ",IF(INDEX(Events!$D$5:$D$304,$AC19)="Medium","○ "," "))&IF(INDEX(Events!$B$5:$B$304,$AC19)="","all day",TEXT(INDEX(Events!$B$5:$B$304,$AC19),"hh:mm"))&" "&INDEX(Events!$C$5:$C$304,$AC19)&" "&INDEX(Events!$F$5:$F$304,$AC19)) | D19: =IF($AD19="","",IFERROR(INDEX({"CB","SPK","GOV","INF","JOB","BIZ","HOL"},MATCH(INDEX(Events!$E$5:$E$304,$AD19),{"Central bank","CB speech","Government","Inflation","Jobs","Growth & business","Holiday"},0)),"?")) | E19: =IF($AD19="","",IF(INDEX(Events!$D$5:$D$304,$AD19)="High","● ",IF(INDEX(Events!$D$5:$D$304,$AD19)="Medium","○ "," "))&IF(INDEX(Events!$B$5:$B$304,$AD19)="","all day",TEXT(INDEX(Events!$B$5:$B$304,$AD19),"hh:mm"))&" "&INDEX(Events!$C$5:$C$304,$AD19)&" "&INDEX(Events!$F$5:$F$304,$AD19)) | F19: =IF($AE19="","",IFERROR(INDEX({"CB","SPK","GOV","INF","JOB","BIZ","HOL"},MATCH(INDEX(Events!$E$5:$E$304,$AE19),{"Central bank","CB speech","Government","Inflation","Jobs","Growth & business","Holiday"},0)),"?")) | G19: =IF($AE19="","",IF(INDEX(Events!$D$5:$D$304,$AE19)="High","● ",IF(INDEX(Events!$D$5:$D$304,$AE19)="Medium","○ "," "))&IF(INDEX(Events!$B$5:$B$304,$AE19)="","all day",TEXT(INDEX(Events!$B$5:$B$304,$AE19),"hh:mm"))&" "&INDEX(Events!$C$5:$C$304,$AE19)&" "&INDEX(Events!$F$5:$F$304,$AE19)) | H19: =IF($AF19="","",IFERROR(INDEX({"CB","SPK","GOV","INF","JOB","BIZ","HOL"},MATCH(INDEX(Events!$E$5:$E$304,$AF19),{"Central bank","CB speech","Government","Inflation","Jobs","Growth & business","Holiday"},0)),"?")) -> BIZ | I19: =IF($AF19="","",IF(INDEX(Events!$D$5:$D$304,$AF19)="High","● ",IF(INDEX(Events!$D$5:$D$304,$AF19)="Medium","○ "," "))&IF(INDEX(Events!$B$5:$B$304,$AF19)="","all day",TEXT(INDEX(Events!$B$5:$B$304,$AF19),"hh:mm"))&" "&INDEX(Events!$C$5:$C$304,$AF19)&" "&INDEX(Events!$F$5:$F$304,$AF19)) -> ● 14:30 USD Retail Sales m/m | J19: =IF($AG19="","",IFERROR(INDEX({"CB","SPK","GOV","INF","JOB","BIZ","HOL"},MATCH(INDEX(Events!$E$5:$E$304,$AG19),{"Central bank","CB speech","Government","Inflation","Jobs","Growth & business","Holiday"},0)),"?")) | K19: =IF($AG19="","",IF(INDEX(Events!$D$5:$D$304,$AG19)="High","● ",IF(INDEX(Events!$D$5:$D$304,$AG19)="Medium","○ "," "))&IF(INDEX(Events!$B$5:$B$304,$AG19)="","all day",TEXT(INDEX(Events!$B$5:$B$304,$AG19),"hh:mm"))&" "&INDEX(Events!$C$5:$C$304,$AG19)&" "&INDEX(Events!$F$5:$F$304,$AG19)) | M19: =TEXT(EDATE(DATE(YEAR($H$6),MONTH($H$6),1),2),"mmmm yyyy") -> December 2026 | U19: =TEXT(EDATE(DATE(YEAR($H$6),MONTH($H$6),1),3),"mmmm yyyy") -> January 2027 | AC19: =IFERROR(MATCH(TEXT(B$10,"yyyymmdd")&"|"&$A19,Events!$M$5:$M$304,0),"") | AD19: =IFERROR(MATCH(TEXT(D$10,"yyyymmdd")&"|"&$A19,Events!$M$5:$M$304,0),"") | AE19: =IFERROR(MATCH(TEXT(F$10,"yyyymmdd")&"|"&$A19,Events!$M$5:$M$304,0),"") | AF19: =IFERROR(MATCH(TEXT(H$10,"yyyymmdd")&"|"&$A19,Events!$M$5:$M$304,0),"") -> 41 | AG19: =IFERROR(MATCH(TEXT(J$10,"yyyymmdd")&"|"&$A19,Events!$M$5:$M$304,0),"")
A20: 10 | B20: =IF($AC20="","",IFERROR(INDEX({"CB","SPK","GOV","INF","JOB","BIZ","HOL"},MATCH(INDEX(Events!$E$5:$E$304,$AC20),{"Central bank","CB speech","Government","Inflation","Jobs","Growth & business","Holiday"},0)),"?")) | C20: =IF($AC20="","",IF(INDEX(Events!$D$5:$D$304,$AC20)="High","● ",IF(INDEX(Events!$D$5:$D$304,$AC20)="Medium","○ "," "))&IF(INDEX(Events!$B$5:$B$304,$AC20)="","all day",TEXT(INDEX(Events!$B$5:$B$304,$AC20),"hh:mm"))&" "&INDEX(Events!$C$5:$C$304,$AC20)&" "&INDEX(Events!$F$5:$F$304,$AC20)) | D20: =IF($AD20="","",IFERROR(INDEX({"CB","SPK","GOV","INF","JOB","BIZ","HOL"},MATCH(INDEX(Events!$E$5:$E$304,$AD20),{"Central bank","CB speech","Government","Inflation","Jobs","Growth & business","Holiday"},0)),"?")) | E20: =IF($AD20="","",IF(INDEX(Events!$D$5:$D$304,$AD20)="High","● ",IF(INDEX(Events!$D$5:$D$304,$AD20)="Medium","○ "," "))&IF(INDEX(Events!$B$5:$B$304,$AD20)="","all day",TEXT(INDEX(Events!$B$5:$B$304,$AD20),"hh:mm"))&" "&INDEX(Events!$C$5:$C$304,$AD20)&" "&INDEX(Events!$F$5:$F$304,$AD20)) | F20: =IF($AE20="","",IFERROR(INDEX({"CB","SPK","GOV","INF","JOB","BIZ","HOL"},MATCH(INDEX(Events!$E$5:$E$304,$AE20),{"Central bank","CB speech","Government","Inflation","Jobs","Growth & business","Holiday"},0)),"?")) | G20: =IF($AE20="","",IF(INDEX(Events!$D$5:$D$304,$AE20)="High","● ",IF(INDEX(Events!$D$5:$D$304,$AE20)="Medium","○ "," "))&IF(INDEX(Events!$B$5:$B$304,$AE20)="","all day",TEXT(INDEX(Events!$B$5:$B$304,$AE20),"hh:mm"))&" "&INDEX(Events!$C$5:$C$304,$AE20)&" "&INDEX(Events!$F$5:$F$304,$AE20)) | H20: =IF($AF20="","",IFERROR(INDEX({"CB","SPK","GOV","INF","JOB","BIZ","HOL"},MATCH(INDEX(Events!$E$5:$E$304,$AF20),{"Central bank","CB speech","Government","Inflation","Jobs","Growth & business","Holiday"},0)),"?")) -> BIZ | I20: =IF($AF20="","",IF(INDEX(Events!$D$5:$D$304,$AF20)="High","● ",IF(INDEX(Events!$D$5:$D$304,$AF20)="Medium","○ "," "))&IF(INDEX(Events!$B$5:$B$304,$AF20)="","all day",TEXT(INDEX(Events!$B$5:$B$304,$AF20),"hh:mm"))&" "&INDEX(Events!$C$5:$C$304,$AF20)&" "&INDEX(Events!$F$5:$F$304,$AF20)) -> ○ 14:30 USD Philly Fed Manufacturing Index | J20: =IF($AG20="","",IFERROR(INDEX({"CB","SPK","GOV","INF","JOB","BIZ","HOL"},MATCH(INDEX(Events!$E$5:$E$304,$AG20),{"Central bank","CB speech","Government","Inflation","Jobs","Growth & business","Holiday"},0)),"?")) | K20: =IF($AG20="","",IF(INDEX(Events!$D$5:$D$304,$AG20)="High","● ",IF(INDEX(Events!$D$5:$D$304,$AG20)="Medium","○ "," "))&IF(INDEX(Events!$B$5:$B$304,$AG20)="","all day",TEXT(INDEX(Events!$B$5:$B$304,$AG20),"hh:mm"))&" "&INDEX(Events!$C$5:$C$304,$AG20)&" "&INDEX(Events!$F$5:$F$304,$AG20)) | M20: Mo | N20: Tu | O20: We | P20: Th | Q20: Fr | R20: Sa | S20: Su | U20: Mo | V20: Tu | W20: We | X20: Th | Y20: Fr | Z20: Sa | AA20: Su | AC20: =IFERROR(MATCH(TEXT(B$10,"yyyymmdd")&"|"&$A20,Events!$M$5:$M$304,0),"") | AD20: =IFERROR(MATCH(TEXT(D$10,"yyyymmdd")&"|"&$A20,Events!$M$5:$M$304,0),"") | AE20: =IFERROR(MATCH(TEXT(F$10,"yyyymmdd")&"|"&$A20,Events!$M$5:$M$304,0),"") | AF20: =IFERROR(MATCH(TEXT(H$10,"yyyymmdd")&"|"&$A20,Events!$M$5:$M$304,0),"") -> 42 | AG20: =IFERROR(MATCH(TEXT(J$10,"yyyymmdd")&"|"&$A20,Events!$M$5:$M$304,0),"")
A21: 11 | B21: =IF($AC21="","",IFERROR(INDEX({"CB","SPK","GOV","INF","JOB","BIZ","HOL"},MATCH(INDEX(Events!$E$5:$E$304,$AC21),{"Central bank","CB speech","Government","Inflation","Jobs","Growth & business","Holiday"},0)),"?")) | C21: =IF($AC21="","",IF(INDEX(Events!$D$5:$D$304,$AC21)="High","● ",IF(INDEX(Events!$D$5:$D$304,$AC21)="Medium","○ "," "))&IF(INDEX(Events!$B$5:$B$304,$AC21)="","all day",TEXT(INDEX(Events!$B$5:$B$304,$AC21),"hh:mm"))&" "&INDEX(Events!$C$5:$C$304,$AC21)&" "&INDEX(Events!$F$5:$F$304,$AC21)) | D21: =IF($AD21="","",IFERROR(INDEX({"CB","SPK","GOV","INF","JOB","BIZ","HOL"},MATCH(INDEX(Events!$E$5:$E$304,$AD21),{"Central bank","CB speech","Government","Inflation","Jobs","Growth & business","Holiday"},0)),"?")) | E21: =IF($AD21="","",IF(INDEX(Events!$D$5:$D$304,$AD21)="High","● ",IF(INDEX(Events!$D$5:$D$304,$AD21)="Medium","○ "," "))&IF(INDEX(Events!$B$5:$B$304,$AD21)="","all day",TEXT(INDEX(Events!$B$5:$B$304,$AD21),"hh:mm"))&" "&INDEX(Events!$C$5:$C$304,$AD21)&" "&INDEX(Events!$F$5:$F$304,$AD21)) | F21: =IF($AE21="","",IFERROR(INDEX({"CB","SPK","GOV","INF","JOB","BIZ","HOL"},MATCH(INDEX(Events!$E$5:$E$304,$AE21),{"Central bank","CB speech","Government","Inflation","Jobs","Growth & business","Holiday"},0)),"?")) | G21: =IF($AE21="","",IF(INDEX(Events!$D$5:$D$304,$AE21)="High","● ",IF(INDEX(Events!$D$5:$D$304,$AE21)="Medium","○ "," "))&IF(INDEX(Events!$B$5:$B$304,$AE21)="","all day",TEXT(INDEX(Events!$B$5:$B$304,$AE21),"hh:mm"))&" "&INDEX(Events!$C$5:$C$304,$AE21)&" "&INDEX(Events!$F$5:$F$304,$AE21)) | H21: =IF($AF21="","",IFERROR(INDEX({"CB","SPK","GOV","INF","JOB","BIZ","HOL"},MATCH(INDEX(Events!$E$5:$E$304,$AF21),{"Central bank","CB speech","Government","Inflation","Jobs","Growth & business","Holiday"},0)),"?")) -> JOB | I21: =IF($AF21="","",IF(INDEX(Events!$D$5:$D$304,$AF21)="High","● ",IF(INDEX(Events!$D$5:$D$304,$AF21)="Medium","○ "," "))&IF(INDEX(Events!$B$5:$B$304,$AF21)="","all day",TEXT(INDEX(Events!$B$5:$B$304,$AF21),"hh:mm"))&" "&INDEX(Events!$C$5:$C$304,$AF21)&" "&INDEX(Events!$F$5:$F$304,$AF21)) -> ○ 14:30 USD Unemployment Claims | J21: =IF($AG21="","",IFERROR(INDEX({"CB","SPK","GOV","INF","JOB","BIZ","HOL"},MATCH(INDEX(Events!$E$5:$E$304,$AG21),{"Central bank","CB speech","Government","Inflation","Jobs","Growth & business","Holiday"},0)),"?")) | K21: =IF($AG21="","",IF(INDEX(Events!$D$5:$D$304,$AG21)="High","● ",IF(INDEX(Events!$D$5:$D$304,$AG21)="Medium","○ "," "))&IF(INDEX(Events!$B$5:$B$304,$AG21)="","all day",TEXT(INDEX(Events!$B$5:$B$304,$AG21),"hh:mm"))&" "&INDEX(Events!$C$5:$C$304,$AG21)&" "&INDEX(Events!$F$5:$F$304,$AG21)) | M21: =(EDATE(DATE(YEAR($H$6),MONTH($H$6),1),2)-WEEKDAY(EDATE(DATE(YEAR($H$6),MONTH($H$6),1),2),3))+0 -> 46356 | N21: =(EDATE(DATE(YEAR($H$6),MONTH($H$6),1),2)-WEEKDAY(EDATE(DATE(YEAR($H$6),MONTH($H$6),1),2),3))+1 -> 46357 | O21: =(EDATE(DATE(YEAR($H$6),MONTH($H$6),1),2)-WEEKDAY(EDATE(DATE(YEAR($H$6),MONTH($H$6),1),2),3))+2 -> 46358 | P21: =(EDATE(DATE(YEAR($H$6),MONTH($H$6),1),2)-WEEKDAY(EDATE(DATE(YEAR($H$6),MONTH($H$6),1),2),3))+3 -> 46359 | Q21: =(EDATE(DATE(YEAR($H$6),MONTH($H$6),1),2)-WEEKDAY(EDATE(DATE(YEAR($H$6),MONTH($H$6),1),2),3))+4 -> 46360 | R21: =(EDATE(DATE(YEAR($H$6),MONTH($H$6),1),2)-WEEKDAY(EDATE(DATE(YEAR($H$6),MONTH($H$6),1),2),3))+5 -> 46361 | S21: =(EDATE(DATE(YEAR($H$6),MONTH($H$6),1),2)-WEEKDAY(EDATE(DATE(YEAR($H$6),MONTH($H$6),1),2),3))+6 -> 46362 | U21: =(EDATE(DATE(YEAR($H$6),MONTH($H$6),1),3)-WEEKDAY(EDATE(DATE(YEAR($H$6),MONTH($H$6),1),3),3))+0 -> 46384 | V21: =(EDATE(DATE(YEAR($H$6),MONTH($H$6),1),3)-WEEKDAY(EDATE(DATE(YEAR($H$6),MONTH($H$6),1),3),3))+1 -> 46385 | W21: =(EDATE(DATE(YEAR($H$6),MONTH($H$6),1),3)-WEEKDAY(EDATE(DATE(YEAR($H$6),MONTH($H$6),1),3),3))+2 -> 46386 | X21: =(EDATE(DATE(YEAR($H$6),MONTH($H$6),1),3)-WEEKDAY(EDATE(DATE(YEAR($H$6),MONTH($H$6),1),3),3))+3 -> 46387 | Y21: =(EDATE(DATE(YEAR($H$6),MONTH($H$6),1),3)-WEEKDAY(EDATE(DATE(YEAR($H$6),MONTH($H$6),1),3),3))+4 -> 46388 | Z21: =(EDATE(DATE(YEAR($H$6),MONTH($H$6),1),3)-WEEKDAY(EDATE(DATE(YEAR($H$6),MONTH($H$6),1),3),3))+5 -> 46389 | AA21: =(EDATE(DATE(YEAR($H$6),MONTH($H$6),1),3)-WEEKDAY(EDATE(DATE(YEAR($H$6),MONTH($H$6),1),3),3))+6 -> 46390 | AC21: =IFERROR(MATCH(TEXT(B$10,"yyyymmdd")&"|"&$A21,Events!$M$5:$M$304,0),"") | AD21: =IFERROR(MATCH(TEXT(D$10,"yyyymmdd")&"|"&$A21,Events!$M$5:$M$304,0),"") | AE21: =IFERROR(MATCH(TEXT(F$10,"yyyymmdd")&"|"&$A21,Events!$M$5:$M$304,0),"") | AF21: =IFERROR(MATCH(TEXT(H$10,"yyyymmdd")&"|"&$A21,Events!$M$5:$M$304,0),"") -> 43 | AG21: =IFERROR(MATCH(TEXT(J$10,"yyyymmdd")&"|"&$A21,Events!$M$5:$M$304,0),"")
A22: 12 | B22: =IF($AC22="","",IFERROR(INDEX({"CB","SPK","GOV","INF","JOB","BIZ","HOL"},MATCH(INDEX(Events!$E$5:$E$304,$AC22),{"Central bank","CB speech","Government","Inflation","Jobs","Growth & business","Holiday"},0)),"?")) | C22: =IF($AC22="","",IF(INDEX(Events!$D$5:$D$304,$AC22)="High","● ",IF(INDEX(Events!$D$5:$D$304,$AC22)="Medium","○ "," "))&IF(INDEX(Events!$B$5:$B$304,$AC22)="","all day",TEXT(INDEX(Events!$B$5:$B$304,$AC22),"hh:mm"))&" "&INDEX(Events!$C$5:$C$304,$AC22)&" "&INDEX(Events!$F$5:$F$304,$AC22)) | D22: =IF($AD22="","",IFERROR(INDEX({"CB","SPK","GOV","INF","JOB","BIZ","HOL"},MATCH(INDEX(Events!$E$5:$E$304,$AD22),{"Central bank","CB speech","Government","Inflation","Jobs","Growth & business","Holiday"},0)),"?")) | E22: =IF($AD22="","",IF(INDEX(Events!$D$5:$D$304,$AD22)="High","● ",IF(INDEX(Events!$D$5:$D$304,$AD22)="Medium","○ "," "))&IF(INDEX(Events!$B$5:$B$304,$AD22)="","all day",TEXT(INDEX(Events!$B$5:$B$304,$AD22),"hh:mm"))&" "&INDEX(Events!$C$5:$C$304,$AD22)&" "&INDEX(Events!$F$5:$F$304,$AD22)) | F22: =IF($AE22="","",IFERROR(INDEX({"CB","SPK","GOV","INF","JOB","BIZ","HOL"},MATCH(INDEX(Events!$E$5:$E$304,$AE22),{"Central bank","CB speech","Government","Inflation","Jobs","Growth & business","Holiday"},0)),"?")) | G22: =IF($AE22="","",IF(INDEX(Events!$D$5:$D$304,$AE22)="High","● ",IF(INDEX(Events!$D$5:$D$304,$AE22)="Medium","○ "," "))&IF(INDEX(Events!$B$5:$B$304,$AE22)="","all day",TEXT(INDEX(Events!$B$5:$B$304,$AE22),"hh:mm"))&" "&INDEX(Events!$C$5:$C$304,$AE22)&" "&INDEX(Events!$F$5:$F$304,$AE22)) | H22: =IF($AF22="","",IFERROR(INDEX({"CB","SPK","GOV","INF","JOB","BIZ","HOL"},MATCH(INDEX(Events!$E$5:$E$304,$AF22),{"Central bank","CB speech","Government","Inflation","Jobs","Growth & business","Holiday"},0)),"?")) | I22: =IF($AF22="","",IF(INDEX(Events!$D$5:$D$304,$AF22)="High","● ",IF(INDEX(Events!$D$5:$D$304,$AF22)="Medium","○ "," "))&IF(INDEX(Events!$B$5:$B$304,$AF22)="","all day",TEXT(INDEX(Events!$B$5:$B$304,$AF22),"hh:mm"))&" "&INDEX(Events!$C$5:$C$304,$AF22)&" "&INDEX(Events!$F$5:$F$304,$AF22)) | J22: =IF($AG22="","",IFERROR(INDEX({"CB","SPK","GOV","INF","JOB","BIZ","HOL"},MATCH(INDEX(Events!$E$5:$E$304,$AG22),{"Central bank","CB speech","Government","Inflation","Jobs","Growth & business","Holiday"},0)),"?")) | K22: =IF($AG22="","",IF(INDEX(Events!$D$5:$D$304,$AG22)="High","● ",IF(INDEX(Events!$D$5:$D$304,$AG22)="Medium","○ "," "))&IF(INDEX(Events!$B$5:$B$304,$AG22)="","all day",TEXT(INDEX(Events!$B$5:$B$304,$AG22),"hh:mm"))&" "&INDEX(Events!$C$5:$C$304,$AG22)&" "&INDEX(Events!$F$5:$F$304,$AG22)) | M22: =(EDATE(DATE(YEAR($H$6),MONTH($H$6),1),2)-WEEKDAY(EDATE(DATE(YEAR($H$6),MONTH($H$6),1),2),3))+7 -> 46363 | N22: =(EDATE(DATE(YEAR($H$6),MONTH($H$6),1),2)-WEEKDAY(EDATE(DATE(YEAR($H$6),MONTH($H$6),1),2),3))+8 -> 46364 | O22: =(EDATE(DATE(YEAR($H$6),MONTH($H$6),1),2)-WEEKDAY(EDATE(DATE(YEAR($H$6),MONTH($H$6),1),2),3))+9 -> 46365 | P22: =(EDATE(DATE(YEAR($H$6),MONTH($H$6),1),2)-WEEKDAY(EDATE(DATE(YEAR($H$6),MONTH($H$6),1),2),3))+10 -> 46366 | Q22: =(EDATE(DATE(YEAR($H$6),MONTH($H$6),1),2)-WEEKDAY(EDATE(DATE(YEAR($H$6),MONTH($H$6),1),2),3))+11 -> 46367 | R22: =(EDATE(DATE(YEAR($H$6),MONTH($H$6),1),2)-WEEKDAY(EDATE(DATE(YEAR($H$6),MONTH($H$6),1),2),3))+12 -> 46368 | S22: =(EDATE(DATE(YEAR($H$6),MONTH($H$6),1),2)-WEEKDAY(EDATE(DATE(YEAR($H$6),MONTH($H$6),1),2),3))+13 -> 46369 | U22: =(EDATE(DATE(YEAR($H$6),MONTH($H$6),1),3)-WEEKDAY(EDATE(DATE(YEAR($H$6),MONTH($H$6),1),3),3))+7 -> 46391 | V22: =(EDATE(DATE(YEAR($H$6),MONTH($H$6),1),3)-WEEKDAY(EDATE(DATE(YEAR($H$6),MONTH($H$6),1),3),3))+8 -> 46392 | W22: =(EDATE(DATE(YEAR($H$6),MONTH($H$6),1),3)-WEEKDAY(EDATE(DATE(YEAR($H$6),MONTH($H$6),1),3),3))+9 -> 46393 | X22: =(EDATE(DATE(YEAR($H$6),MONTH($H$6),1),3)-WEEKDAY(EDATE(DATE(YEAR($H$6),MONTH($H$6),1),3),3))+10 -> 46394 | Y22: =(EDATE(DATE(YEAR($H$6),MONTH($H$6),1),3)-WEEKDAY(EDATE(DATE(YEAR($H$6),MONTH($H$6),1),3),3))+11 -> 46395 | Z22: =(EDATE(DATE(YEAR($H$6),MONTH($H$6),1),3)-WEEKDAY(EDATE(DATE(YEAR($H$6),MONTH($H$6),1),3),3))+12 -> 46396 | AA22: =(EDATE(DATE(YEAR($H$6),MONTH($H$6),1),3)-WEEKDAY(EDATE(DATE(YEAR($H$6),MONTH($H$6),1),3),3))+13 -> 46397 | AC22: =IFERROR(MATCH(TEXT(B$10,"yyyymmdd")&"|"&$A22,Events!$M$5:$M$304,0),"") | AD22: =IFERROR(MATCH(TEXT(D$10,"yyyymmdd")&"|"&$A22,Events!$M$5:$M$304,0),"") | AE22: =IFERROR(MATCH(TEXT(F$10,"yyyymmdd")&"|"&$A22,Events!$M$5:$M$304,0),"") | AF22: =IFERROR(MATCH(TEXT(H$10,"yyyymmdd")&"|"&$A22,Events!$M$5:$M$304,0),"") | AG22: =IFERROR(MATCH(TEXT(J$10,"yyyymmdd")&"|"&$A22,Events!$M$5:$M$304,0),"")
B23: ● high impact ○ medium impact · left tag = type of event, event colour = country · yellow = today · pick “All” above to add low-impact events; change the week number to look ahead. | M23: =(EDATE(DATE(YEAR($H$6),MONTH($H$6),1),2)-WEEKDAY(EDATE(DATE(YEAR($H$6),MONTH($H$6),1),2),3))+14 -> 46370 | N23: =(EDATE(DATE(YEAR($H$6),MONTH($H$6),1),2)-WEEKDAY(EDATE(DATE(YEAR($H$6),MONTH($H$6),1),2),3))+15 -> 46371 | O23: =(EDATE(DATE(YEAR($H$6),MONTH($H$6),1),2)-WEEKDAY(EDATE(DATE(YEAR($H$6),MONTH($H$6),1),2),3))+16 -> 46372 | P23: =(EDATE(DATE(YEAR($H$6),MONTH($H$6),1),2)-WEEKDAY(EDATE(DATE(YEAR($H$6),MONTH($H$6),1),2),3))+17 -> 46373 | Q23: =(EDATE(DATE(YEAR($H$6),MONTH($H$6),1),2)-WEEKDAY(EDATE(DATE(YEAR($H$6),MONTH($H$6),1),2),3))+18 -> 46374 | R23: =(EDATE(DATE(YEAR($H$6),MONTH($H$6),1),2)-WEEKDAY(EDATE(DATE(YEAR($H$6),MONTH($H$6),1),2),3))+19 -> 46375 | S23: =(EDATE(DATE(YEAR($H$6),MONTH($H$6),1),2)-WEEKDAY(EDATE(DATE(YEAR($H$6),MONTH($H$6),1),2),3))+20 -> 46376 | U23: =(EDATE(DATE(YEAR($H$6),MONTH($H$6),1),3)-WEEKDAY(EDATE(DATE(YEAR($H$6),MONTH($H$6),1),3),3))+14 -> 46398 | V23: =(EDATE(DATE(YEAR($H$6),MONTH($H$6),1),3)-WEEKDAY(EDATE(DATE(YEAR($H$6),MONTH($H$6),1),3),3))+15 -> 46399 | W23: =(EDATE(DATE(YEAR($H$6),MONTH($H$6),1),3)-WEEKDAY(EDATE(DATE(YEAR($H$6),MONTH($H$6),1),3),3))+16 -> 46400 | X23: =(EDATE(DATE(YEAR($H$6),MONTH($H$6),1),3)-WEEKDAY(EDATE(DATE(YEAR($H$6),MONTH($H$6),1),3),3))+17 -> 46401 | Y23: =(EDATE(DATE(YEAR($H$6),MONTH($H$6),1),3)-WEEKDAY(EDATE(DATE(YEAR($H$6),MONTH($H$6),1),3),3))+18 -> 46402 | Z23: =(EDATE(DATE(YEAR($H$6),MONTH($H$6),1),3)-WEEKDAY(EDATE(DATE(YEAR($H$6),MONTH($H$6),1),3),3))+19 -> 46403 | AA23: =(EDATE(DATE(YEAR($H$6),MONTH($H$6),1),3)-WEEKDAY(EDATE(DATE(YEAR($H$6),MONTH($H$6),1),3),3))+20 -> 46404
M24: =(EDATE(DATE(YEAR($H$6),MONTH($H$6),1),2)-WEEKDAY(EDATE(DATE(YEAR($H$6),MONTH($H$6),1),2),3))+21 -> 46377 | N24: =(EDATE(DATE(YEAR($H$6),MONTH($H$6),1),2)-WEEKDAY(EDATE(DATE(YEAR($H$6),MONTH($H$6),1),2),3))+22 -> 46378 | O24: =(EDATE(DATE(YEAR($H$6),MONTH($H$6),1),2)-WEEKDAY(EDATE(DATE(YEAR($H$6),MONTH($H$6),1),2),3))+23 -> 46379 | P24: =(EDATE(DATE(YEAR($H$6),MONTH($H$6),1),2)-WEEKDAY(EDATE(DATE(YEAR($H$6),MONTH($H$6),1),2),3))+24 -> 46380 | Q24: =(EDATE(DATE(YEAR($H$6),MONTH($H$6),1),2)-WEEKDAY(EDATE(DATE(YEAR($H$6),MONTH($H$6),1),2),3))+25 -> 46381 | R24: =(EDATE(DATE(YEAR($H$6),MONTH($H$6),1),2)-WEEKDAY(EDATE(DATE(YEAR($H$6),MONTH($H$6),1),2),3))+26 -> 46382 | S24: =(EDATE(DATE(YEAR($H$6),MONTH($H$6),1),2)-WEEKDAY(EDATE(DATE(YEAR($H$6),MONTH($H$6),1),2),3))+27 -> 46383 | U24: =(EDATE(DATE(YEAR($H$6),MONTH($H$6),1),3)-WEEKDAY(EDATE(DATE(YEAR($H$6),MONTH($H$6),1),3),3))+21 -> 46405 | V24: =(EDATE(DATE(YEAR($H$6),MONTH($H$6),1),3)-WEEKDAY(EDATE(DATE(YEAR($H$6),MONTH($H$6),1),3),3))+22 -> 46406 | W24: =(EDATE(DATE(YEAR($H$6),MONTH($H$6),1),3)-WEEKDAY(EDATE(DATE(YEAR($H$6),MONTH($H$6),1),3),3))+23 -> 46407 | X24: =(EDATE(DATE(YEAR($H$6),MONTH($H$6),1),3)-WEEKDAY(EDATE(DATE(YEAR($H$6),MONTH($H$6),1),3),3))+24 -> 46408 | Y24: =(EDATE(DATE(YEAR($H$6),MONTH($H$6),1),3)-WEEKDAY(EDATE(DATE(YEAR($H$6),MONTH($H$6),1),3),3))+25 -> 46409 | Z24: =(EDATE(DATE(YEAR($H$6),MONTH($H$6),1),3)-WEEKDAY(EDATE(DATE(YEAR($H$6),MONTH($H$6),1),3),3))+26 -> 46410 | AA24: =(EDATE(DATE(YEAR($H$6),MONTH($H$6),1),3)-WEEKDAY(EDATE(DATE(YEAR($H$6),MONTH($H$6),1),3),3))+27 -> 46411
A25: KEY | M25: =(EDATE(DATE(YEAR($H$6),MONTH($H$6),1),2)-WEEKDAY(EDATE(DATE(YEAR($H$6),MONTH($H$6),1),2),3))+28 -> 46384 | N25: =(EDATE(DATE(YEAR($H$6),MONTH($H$6),1),2)-WEEKDAY(EDATE(DATE(YEAR($H$6),MONTH($H$6),1),2),3))+29 -> 46385 | O25: =(EDATE(DATE(YEAR($H$6),MONTH($H$6),1),2)-WEEKDAY(EDATE(DATE(YEAR($H$6),MONTH($H$6),1),2),3))+30 -> 46386 | P25: =(EDATE(DATE(YEAR($H$6),MONTH($H$6),1),2)-WEEKDAY(EDATE(DATE(YEAR($H$6),MONTH($H$6),1),2),3))+31 -> 46387 | Q25: =(EDATE(DATE(YEAR($H$6),MONTH($H$6),1),2)-WEEKDAY(EDATE(DATE(YEAR($H$6),MONTH($H$6),1),2),3))+32 -> 46388 | R25: =(EDATE(DATE(YEAR($H$6),MONTH($H$6),1),2)-WEEKDAY(EDATE(DATE(YEAR($H$6),MONTH($H$6),1),2),3))+33 -> 46389 | S25: =(EDATE(DATE(YEAR($H$6),MONTH($H$6),1),2)-WEEKDAY(EDATE(DATE(YEAR($H$6),MONTH($H$6),1),2),3))+34 -> 46390 | U25: =(EDATE(DATE(YEAR($H$6),MONTH($H$6),1),3)-WEEKDAY(EDATE(DATE(YEAR($H$6),MONTH($H$6),1),3),3))+28 -> 46412 | V25: =(EDATE(DATE(YEAR($H$6),MONTH($H$6),1),3)-WEEKDAY(EDATE(DATE(YEAR($H$6),MONTH($H$6),1),3),3))+29 -> 46413 | W25: =(EDATE(DATE(YEAR($H$6),MONTH($H$6),1),3)-WEEKDAY(EDATE(DATE(YEAR($H$6),MONTH($H$6),1),3),3))+30 -> 46414 | X25: =(EDATE(DATE(YEAR($H$6),MONTH($H$6),1),3)-WEEKDAY(EDATE(DATE(YEAR($H$6),MONTH($H$6),1),3),3))+31 -> 46415 | Y25: =(EDATE(DATE(YEAR($H$6),MONTH($H$6),1),3)-WEEKDAY(EDATE(DATE(YEAR($H$6),MONTH($H$6),1),3),3))+32 -> 46416 | Z25: =(EDATE(DATE(YEAR($H$6),MONTH($H$6),1),3)-WEEKDAY(EDATE(DATE(YEAR($H$6),MONTH($H$6),1),3),3))+33 -> 46417 | AA25: =(EDATE(DATE(YEAR($H$6),MONTH($H$6),1),3)-WEEKDAY(EDATE(DATE(YEAR($H$6),MONTH($H$6),1),3),3))+34 -> 46418
B26: COUNTRY — colour of the event | D26: TYPE — the tag in front | F26: IMPACT & MARKERS | M26: =(EDATE(DATE(YEAR($H$6),MONTH($H$6),1),2)-WEEKDAY(EDATE(DATE(YEAR($H$6),MONTH($H$6),1),2),3))+35 -> 46391 | N26: =(EDATE(DATE(YEAR($H$6),MONTH($H$6),1),2)-WEEKDAY(EDATE(DATE(YEAR($H$6),MONTH($H$6),1),2),3))+36 -> 46392 | O26: =(EDATE(DATE(YEAR($H$6),MONTH($H$6),1),2)-WEEKDAY(EDATE(DATE(YEAR($H$6),MONTH($H$6),1),2),3))+37 -> 46393 | P26: =(EDATE(DATE(YEAR($H$6),MONTH($H$6),1),2)-WEEKDAY(EDATE(DATE(YEAR($H$6),MONTH($H$6),1),2),3))+38 -> 46394 | Q26: =(EDATE(DATE(YEAR($H$6),MONTH($H$6),1),2)-WEEKDAY(EDATE(DATE(YEAR($H$6),MONTH($H$6),1),2),3))+39 -> 46395 | R26: =(EDATE(DATE(YEAR($H$6),MONTH($H$6),1),2)-WEEKDAY(EDATE(DATE(YEAR($H$6),MONTH($H$6),1),2),3))+40 -> 46396 | S26: =(EDATE(DATE(YEAR($H$6),MONTH($H$6),1),2)-WEEKDAY(EDATE(DATE(YEAR($H$6),MONTH($H$6),1),2),3))+41 -> 46397 | U26: =(EDATE(DATE(YEAR($H$6),MONTH($H$6),1),3)-WEEKDAY(EDATE(DATE(YEAR($H$6),MONTH($H$6),1),3),3))+35 -> 46419 | V26: =(EDATE(DATE(YEAR($H$6),MONTH($H$6),1),3)-WEEKDAY(EDATE(DATE(YEAR($H$6),MONTH($H$6),1),3),3))+36 -> 46420 | W26: =(EDATE(DATE(YEAR($H$6),MONTH($H$6),1),3)-WEEKDAY(EDATE(DATE(YEAR($H$6),MONTH($H$6),1),3),3))+37 -> 46421 | X26: =(EDATE(DATE(YEAR($H$6),MONTH($H$6),1),3)-WEEKDAY(EDATE(DATE(YEAR($H$6),MONTH($H$6),1),3),3))+38 -> 46422 | Y26: =(EDATE(DATE(YEAR($H$6),MONTH($H$6),1),3)-WEEKDAY(EDATE(DATE(YEAR($H$6),MONTH($H$6),1),3),3))+39 -> 46423 | Z26: =(EDATE(DATE(YEAR($H$6),MONTH($H$6),1),3)-WEEKDAY(EDATE(DATE(YEAR($H$6),MONTH($H$6),1),3),3))+40 -> 46424 | AA26: =(EDATE(DATE(YEAR($H$6),MONTH($H$6),1),3)-WEEKDAY(EDATE(DATE(YEAR($H$6),MONTH($H$6),1),3),3))+41 -> 46425
B27: USD | C27: United States — flag red | D27: CB | E27: Central-bank decision / press conference | F27: ● | G27: High impact | M27: Months follow the week being viewed. Purple = central-bank decision · pink = other high-impact day · navy = today · blue = the week on the left.
B28: EUR | C28: Euro area — light EU blue | D28: SPK | E28: Central-bank speech, minutes, testimony | F28: ○ | G28: Medium impact
B29: GBP | C29: United Kingdom — navy | D29: GOV | E29: Government / Treasury: budget, auctions | F29: Today | G29: Today (empty slots) — gold header = today
B30: JPY | C30: Japan — white with the red sun | D30: INF | E30: Inflation: CPI, PPI, PCE, inflation expectations | F30: 21 | G30: Month view: central-bank decision day
B31: AUD | C31: Australia — orange | D31: JOB | E31: Jobs: payrolls, unemployment, claims | F31: 21 | G31: Month view: other high-impact day
B32: NZD | C32: New Zealand — black (silver fern) | D32: BIZ | E32: Growth & business: PMI, GDP, retail, sentiment | F32: 21 | G32: Month view: today
B33: CAD | C33: Canada — light red (maple leaf) | D33: HOL | E33: Bank holiday — thin liquidity | F33: 21 | G33: Month view: the week shown on the left
B34: CHF | C34: Switzerland — grey with the red cross
B35: CNY | C35: China — yellow star on red
B36: XAU | C36: Gold — gold

Sheet Bias
A1: Bias Board — Layer 1 permission | S1: ← Guide
A2: FINAL BIAS = what Layers 2–4 are allowed to trade. FLAT or EXPIRED = no macro permission.
A4: Pair | B4: Base | C4: Quote | D4: Base score | E4: Quote score | F4: Score diff | G4: 2Y spread now (bp) | H4: 2Y spread 1M ago (bp) | I4: Δ 2Y spread (bp) | J4: Macro signal | K4: Yields confirm? | L4: Risk override | M4: FINAL BIAS | N4: Last reviewed | O4: Valid until | P4: Status | Q4: Invalidation — what would flip it? | R4: AI bias | S4: User bias
A5: EURUSD | B5: EUR | C5: USD | D5: =IFERROR(INDEX(Scorecard!$Q$5:$Q$12,MATCH(B5,Scorecard!$A$5:$A$12,0)),"") -> 1 | E5: =IFERROR(INDEX(Scorecard!$Q$5:$Q$12,MATCH(C5,Scorecard!$A$5:$A$12,0)),"") -> 2 | F5: =IF(OR(D5="",E5=""),"",D5-E5) -> -1 | G5: =IFERROR((INDEX(Scorecard!$K$5:$K$12,MATCH(B5,Scorecard!$A$5:$A$12,0))-INDEX(Scorecard!$K$5:$K$12,MATCH(C5,Scorecard!$A$5:$A$12,0)))*100,"") -> -170 | H5: =IFERROR((INDEX(Scorecard!$L$5:$L$12,MATCH(B5,Scorecard!$A$5:$A$12,0))-INDEX(Scorecard!$L$5:$L$12,MATCH(C5,Scorecard!$A$5:$A$12,0)))*100,"") -> -139 | I5: =IF(OR(G5="",H5=""),"",ROUND(G5-H5,1)) -> -31 | J5: =IF(F5="","",IF(F5>=Guide!$B$26,"LONG",IF(F5<=-Guide!$B$26,"SHORT","FLAT"))) -> FLAT | K5: =IF(J5="LONG",IF(I5>=Guide!$B$27,"YES","NO"),IF(J5="SHORT",IF(I5<=-Guide!$B$27,"YES","NO"),"—")) -> — | L5: =IF(AND('Risk & Gold'!$B$8="RISK-OFF",OR(AND(C5="JPY",J5="LONG"),AND(B5="JPY",J5="SHORT"))),"YES: JPY haven","—") -> — | M5: =IF(F5="","ENTER DATA",IF(L5<>"—","FLAT",IF(K5="YES",J5,"FLAT"))) -> FLAT | N5: 46284 | O5: =IF(N5="","",N5+Guide!$B$34) -> 46291 | P5: =IF(N5="","NOT REVIEWED",IF(TODAY()>O5,"EXPIRED","ACTIVE")) -> EXPIRED | Q5: EXAMPLE: FLAT until USD–EUR score gap reaches 2 and the 2Y spread confirms | R5: ='Bias Builder'!C6 -> SHORT | S5: =IF('Bias Builder'!F6="","—",'Bias Builder'!F6) -> FLAT
A6: GBPUSD | B6: GBP | C6: USD | D6: =IFERROR(INDEX(Scorecard!$Q$5:$Q$12,MATCH(B6,Scorecard!$A$5:$A$12,0)),"") -> 2 | E6: =IFERROR(INDEX(Scorecard!$Q$5:$Q$12,MATCH(C6,Scorecard!$A$5:$A$12,0)),"") -> 2 | F6: =IF(OR(D6="",E6=""),"",D6-E6) -> 0 | G6: =IFERROR((INDEX(Scorecard!$K$5:$K$12,MATCH(B6,Scorecard!$A$5:$A$12,0))-INDEX(Scorecard!$K$5:$K$12,MATCH(C6,Scorecard!$A$5:$A$12,0)))*100,"") -> 10 | H6: =IFERROR((INDEX(Scorecard!$L$5:$L$12,MATCH(B6,Scorecard!$A$5:$A$12,0))-INDEX(Scorecard!$L$5:$L$12,MATCH(C6,Scorecard!$A$5:$A$12,0)))*100,"") -> 27 | I6: =IF(OR(G6="",H6=""),"",ROUND(G6-H6,1)) -> -17 | J6: =IF(F6="","",IF(F6>=Guide!$B$26,"LONG",IF(F6<=-Guide!$B$26,"SHORT","FLAT"))) -> FLAT | K6: =IF(J6="LONG",IF(I6>=Guide!$B$27,"YES","NO"),IF(J6="SHORT",IF(I6<=-Guide!$B$27,"YES","NO"),"—")) -> — | L6: =IF(AND('Risk & Gold'!$B$8="RISK-OFF",OR(AND(C6="JPY",J6="LONG"),AND(B6="JPY",J6="SHORT"))),"YES: JPY haven","—") -> — | M6: =IF(F6="","ENTER DATA",IF(L6<>"—","FLAT",IF(K6="YES",J6,"FLAT"))) -> FLAT | O6: =IF(N6="","",N6+Guide!$B$34) | P6: =IF(N6="","NOT REVIEWED",IF(TODAY()>O6,"EXPIRED","ACTIVE")) -> NOT REVIEWED | R6: ='Bias Builder'!C7 -> FLAT | S6: =IF('Bias Builder'!F7="","—",'Bias Builder'!F7) -> FLAT
A7: USDJPY | B7: USD | C7: JPY | D7: =IFERROR(INDEX(Scorecard!$Q$5:$Q$12,MATCH(B7,Scorecard!$A$5:$A$12,0)),"") -> 2 | E7: =IFERROR(INDEX(Scorecard!$Q$5:$Q$12,MATCH(C7,Scorecard!$A$5:$A$12,0)),"") -> 1 | F7: =IF(OR(D7="",E7=""),"",D7-E7) -> 1 | G7: =IFERROR((INDEX(Scorecard!$K$5:$K$12,MATCH(B7,Scorecard!$A$5:$A$12,0))-INDEX(Scorecard!$K$5:$K$12,MATCH(C7,Scorecard!$A$5:$A$12,0)))*100,"") -> 285 | H7: =IFERROR((INDEX(Scorecard!$L$5:$L$12,MATCH(B7,Scorecard!$A$5:$A$12,0))-INDEX(Scorecard!$L$5:$L$12,MATCH(C7,Scorecard!$A$5:$A$12,0)))*100,"") -> 281 | I7: =IF(OR(G7="",H7=""),"",ROUND(G7-H7,1)) -> 4 | J7: =IF(F7="","",IF(F7>=Guide!$B$26,"LONG",IF(F7<=-Guide!$B$26,"SHORT","FLAT"))) -> FLAT | K7: =IF(J7="LONG",IF(I7>=Guide!$B$27,"YES","NO"),IF(J7="SHORT",IF(I7<=-Guide!$B$27,"YES","NO"),"—")) -> — | L7: =IF(AND('Risk & Gold'!$B$8="RISK-OFF",OR(AND(C7="JPY",J7="LONG"),AND(B7="JPY",J7="SHORT"))),"YES: JPY haven","—") -> — | M7: =IF(F7="","ENTER DATA",IF(L7<>"—","FLAT",IF(K7="YES",J7,"FLAT"))) -> FLAT | O7: =IF(N7="","",N7+Guide!$B$34) | P7: =IF(N7="","NOT REVIEWED",IF(TODAY()>O7,"EXPIRED","ACTIVE")) -> NOT REVIEWED | R7: ='Bias Builder'!C8 -> LONG | S7: =IF('Bias Builder'!F8="","—",'Bias Builder'!F8) -> LONG
A8: XAUUSD | B8: XAU | C8: USD | D8: — | E8: — | F8: ='Risk & Gold'!E17 -> -2 | G8: — | H8: — | I8: — | J8: ='Risk & Gold'!B18 -> SHORT | K8: — | L8: — | M8: ='Risk & Gold'!B18 -> SHORT | N8: 46284 | O8: =IF(N8="","",N8+Guide!$B$34) -> 46291 | P8: =IF(N8="","NOT REVIEWED",IF(TODAY()>O8,"EXPIRED","ACTIVE")) -> EXPIRED | Q8: Turns LONG if real yields fall ≥15 bp or dollar drops ≥1% (research stays +1). Turns SHORT if dollar rises ≥1% AND research drops to 0. | R8: ='Bias Builder'!C9 -> SHORT | S8: =IF('Bias Builder'!F9="","—",'Bias Builder'!F9) -> SHORT
A10: HOW FINAL BIAS IS DECIDED
A11: 1. Score diff (base − quote) ≥ +2 → LONG signal, ≤ −2 → SHORT signal, else FLAT.
A12: 2. The 2Y yield spread must have moved the same way over the last month (≥ 10 bp), otherwise FLAT — the market has to confirm the thesis.
A13: 3. In RISK-OFF, any trade against JPY is overridden to FLAT.
A14: 4. Gold comes from the Risk & Gold sheet.
A15: 5. Unreviewed for 7+ days = EXPIRED = treat as FLAT.

Sheet Bias Builder
A1: Bias Builder | J1: ← Guide
A2: What each central bank and treasury is saying, what the market prices, and the key numbers — then the AI read next to the User’s. Blue = Claude fills (prompts P4 + P7); “User read” rows and the User bias column are the User’s. Indicators in grey/green come from Scorecard and update themselves.
A4: AI BIAS vs MODEL vs USER
A5: Pair | B5: Model bias (Bias sheet) | C5: AI bias (Claude) | D5: AI — key driver | F5: User bias | G5: AI confidence | H5: Agreement | I5: Next high-impact catalyst
A6: EURUSD | B6: =Bias!M5 -> FLAT | C6: SHORT | D6: Fed hike ~90% priced by Dec vs ECB hold on 29 Oct; US PMI 58.4 vs EZ 53.1; DXY +3%. Model is FLAT (score gap −1, 2Y spread confirms). Risk: EUR shorts at a 2020 high can squeeze. | F6: FLAT | G6: Medium | H6: =IF(TRIM(F6)="","User: —",IF(AND(UPPER(TRIM(B6))=UPPER(TRIM(C6)),UPPER(TRIM(C6))=UPPER(TRIM(F6))),"ALL AGREE",IF(OR(UPPER(TRIM(B6))=UPPER(TRIM(C6)),UPPER(TRIM(C6))=UPPER(TRIM(F6)),UPPER(TRIM(B6))=UPPER(TRIM(F6))),"2 OF 3","SPLIT"))) -> 2 OF 3 | I6: =IFERROR(IF(MIN(IF(_xlfn.MINIFS(Events!$L$5:$L$304,Events!$C$5:$C$304,"EUR",Events!$D$5:$D$304,"High",Events!$L$5:$L$304,">="&NOW())=0,9000000000,_xlfn.MINIFS(Events!$L$5:$L$304,Events!$C$5:$C$304,"EUR",Events!$D$5:$D$304,"High",Events!$L$5:$L$304,">="&NOW())),IF(_xlfn.MINIFS(Events!$L$5:$L$304,Events!$C$5:$C$304,"USD",Events!$D$5:$D$304,"High",Events!$L$5:$L$304,">="&NOW())=0,9000000000,_xlfn.MINIFS(Events!$L$5:$L$304,Events!$C$5:$C$304,"USD",Events!$D$5:$D$304,"High",Events!$L$5:$L$304,">="&NOW())))>900000000,"none scheduled",TEXT(MIN(IF(_xlfn.MINIFS(Events!$L$5:$L$304,Events!$C$5:$C$304,"EUR",Events!$D$5:$D$304,"High",Events!$L$5:$L$304,">="&NOW())=0,9000000000,_xlfn.MINIFS(Events!$L$5:$L$304,Events!$C$5:$C$304,"EUR",Events!$D$5:$D$304,"High",Events!$L$5:$L$304,">="&NOW())),IF(_xlfn.MINIFS(Events!$L$5:$L$304,Events!$C$5:$C$304,"USD",Events!$D$5:$D$304,"High",Events!$L$5:$L$304,">="&NOW())=0,9000000000,_xlfn.MINIFS(Events!$L$5:$L$304,Events!$C$5:$C$304,"USD",Events!$D$5:$D$304,"High",Events!$L$5:$L$304,">="&NOW()))),"ddd d mmm")&" "&INDEX(Events!$C$5:$C$304,MATCH(MIN(IF(_xlfn.MINIFS(Events!$L$5:$L$304,Events!$C$5:$C$304,"EUR",Events!$D$5:$D$304,"High",Events!$L$5:$L$304,">="&NOW())=0,9000000000,_xlfn.MINIFS(Events!$L$5:$L$304,Events!$C$5:$C$304,"EUR",Events!$D$5:$D$304,"High",Events!$L$5:$L$304,">="&NOW())),IF(_xlfn.MINIFS(Events!$L$5:$L$304,Events!$C$5:$C$304,"USD",Events!$D$5:$D$304,"High",Events!$L$5:$L$304,">="&NOW())=0,9000000000,_xlfn.MINIFS(Events!$L$5:$L$304,Events!$C$5:$C$304,"USD",Events!$D$5:$D$304,"High",Events!$L$5:$L$304,">="&NOW()))),Events!$L$5:$L$304,0))&" "&INDEX(Events!$F$5:$F$304,MATCH(MIN(IF(_xlfn.MINIFS(Events!$L$5:$L$304,Events!$C$5:$C$304,"EUR",Events!$D$5:$D$304,"High",Events!$L$5:$L$304,">="&NOW())=0,9000000000,_xlfn.MINIFS(Events!$L$5:$L$304,Events!$C$5:$C$304,"EUR",Events!$D$5:$D$304,"High",Events!$L$5:$L$304,">="&NOW())),IF(_xlfn.MINIFS(Events!$L$5:$L$304,Events!$C$5:$C$304,"USD",Events!$D$5:$D$304,"High",Events!$L$5:$L$304,">="&NOW())=0,9000000000,_xlfn.MINIFS(Events!$L$5:$L$304,Events!$C$5:$C$304,"USD",Events!$D$5:$D$304,"High",Events!$L$5:$L$304,">="&NOW()))),Events!$L$5:$L$304,0))),"none scheduled") -> Thu 15 Oct USD Core PPI m/m
A7: GBPUSD | B7: =Bias!M6 -> FLAT | C7: FLAT | D7: Both central banks hiking: BoE ~95% for 5 Nov vs Fed ~90% by Dec. Budget (28 Oct) and gilt stress are a two-way risk. Agrees with model FLAT. | F7: FLAT | G7: Low | H7: =IF(TRIM(F7)="","User: —",IF(AND(UPPER(TRIM(B7))=UPPER(TRIM(C7)),UPPER(TRIM(C7))=UPPER(TRIM(F7))),"ALL AGREE",IF(OR(UPPER(TRIM(B7))=UPPER(TRIM(C7)),UPPER(TRIM(C7))=UPPER(TRIM(F7)),UPPER(TRIM(B7))=UPPER(TRIM(F7))),"2 OF 3","SPLIT"))) -> ALL AGREE | I7: =IFERROR(IF(MIN(IF(_xlfn.MINIFS(Events!$L$5:$L$304,Events!$C$5:$C$304,"GBP",Events!$D$5:$D$304,"High",Events!$L$5:$L$304,">="&NOW())=0,9000000000,_xlfn.MINIFS(Events!$L$5:$L$304,Events!$C$5:$C$304,"GBP",Events!$D$5:$D$304,"High",Events!$L$5:$L$304,">="&NOW())),IF(_xlfn.MINIFS(Events!$L$5:$L$304,Events!$C$5:$C$304,"USD",Events!$D$5:$D$304,"High",Events!$L$5:$L$304,">="&NOW())=0,9000000000,_xlfn.MINIFS(Events!$L$5:$L$304,Events!$C$5:$C$304,"USD",Events!$D$5:$D$304,"High",Events!$L$5:$L$304,">="&NOW())))>900000000,"none scheduled",TEXT(MIN(IF(_xlfn.MINIFS(Events!$L$5:$L$304,Events!$C$5:$C$304,"GBP",Events!$D$5:$D$304,"High",Events!$L$5:$L$304,">="&NOW())=0,9000000000,_xlfn.MINIFS(Events!$L$5:$L$304,Events!$C$5:$C$304,"GBP",Events!$D$5:$D$304,"High",Events!$L$5:$L$304,">="&NOW())),IF(_xlfn.MINIFS(Events!$L$5:$L$304,Events!$C$5:$C$304,"USD",Events!$D$5:$D$304,"High",Events!$L$5:$L$304,">="&NOW())=0,9000000000,_xlfn.MINIFS(Events!$L$5:$L$304,Events!$C$5:$C$304,"USD",Events!$D$5:$D$304,"High",Events!$L$5:$L$304,">="&NOW()))),"ddd d mmm")&" "&INDEX(Events!$C$5:$C$304,MATCH(MIN(IF(_xlfn.MINIFS(Events!$L$5:$L$304,Events!$C$5:$C$304,"GBP",Events!$D$5:$D$304,"High",Events!$L$5:$L$304,">="&NOW())=0,9000000000,_xlfn.MINIFS(Events!$L$5:$L$304,Events!$C$5:$C$304,"GBP",Events!$D$5:$D$304,"High",Events!$L$5:$L$304,">="&NOW())),IF(_xlfn.MINIFS(Events!$L$5:$L$304,Events!$C$5:$C$304,"USD",Events!$D$5:$D$304,"High",Events!$L$5:$L$304,">="&NOW())=0,9000000000,_xlfn.MINIFS(Events!$L$5:$L$304,Events!$C$5:$C$304,"USD",Events!$D$5:$D$304,"High",Events!$L$5:$L$304,">="&NOW()))),Events!$L$5:$L$304,0))&" "&INDEX(Events!$F$5:$F$304,MATCH(MIN(IF(_xlfn.MINIFS(Events!$L$5:$L$304,Events!$C$5:$C$304,"GBP",Events!$D$5:$D$304,"High",Events!$L$5:$L$304,">="&NOW())=0,9000000000,_xlfn.MINIFS(Events!$L$5:$L$304,Events!$C$5:$C$304,"GBP",Events!$D$5:$D$304,"High",Events!$L$5:$L$304,">="&NOW())),IF(_xlfn.MINIFS(Events!$L$5:$L$304,Events!$C$5:$C$304,"USD",Events!$D$5:$D$304,"High",Events!$L$5:$L$304,">="&NOW())=0,9000000000,_xlfn.MINIFS(Events!$L$5:$L$304,Events!$C$5:$C$304,"USD",Events!$D$5:$D$304,"High",Events!$L$5:$L$304,">="&NOW()))),Events!$L$5:$L$304,0))),"none scheduled") -> Thu 15 Oct USD Core PPI m/m
A8: USDJPY | B8: =Bias!M7 -> FLAT | C8: LONG | D8: Rate gap wide (2Y spread ~286 bp) and BoJ pause expected for 30 Oct. But price 157.9 sits just under the 160 intervention line and speculators are net long yen — upside is capped. Model FLAT (score gap only +1). | F8: LONG | G8: Low | H8: =IF(TRIM(F8)="","User: —",IF(AND(UPPER(TRIM(B8))=UPPER(TRIM(C8)),UPPER(TRIM(C8))=UPPER(TRIM(F8))),"ALL AGREE",IF(OR(UPPER(TRIM(B8))=UPPER(TRIM(C8)),UPPER(TRIM(C8))=UPPER(TRIM(F8)),UPPER(TRIM(B8))=UPPER(TRIM(F8))),"2 OF 3","SPLIT"))) -> 2 OF 3 | I8: =IFERROR(IF(MIN(IF(_xlfn.MINIFS(Events!$L$5:$L$304,Events!$C$5:$C$304,"USD",Events!$D$5:$D$304,"High",Events!$L$5:$L$304,">="&NOW())=0,9000000000,_xlfn.MINIFS(Events!$L$5:$L$304,Events!$C$5:$C$304,"USD",Events!$D$5:$D$304,"High",Events!$L$5:$L$304,">="&NOW())),IF(_xlfn.MINIFS(Events!$L$5:$L$304,Events!$C$5:$C$304,"JPY",Events!$D$5:$D$304,"High",Events!$L$5:$L$304,">="&NOW())=0,9000000000,_xlfn.MINIFS(Events!$L$5:$L$304,Events!$C$5:$C$304,"JPY",Events!$D$5:$D$304,"High",Events!$L$5:$L$304,">="&NOW())))>900000000,"none scheduled",TEXT(MIN(IF(_xlfn.MINIFS(Events!$L$5:$L$304,Events!$C$5:$C$304,"USD",Events!$D$5:$D$304,"High",Events!$L$5:$L$304,">="&NOW())=0,9000000000,_xlfn.MINIFS(Events!$L$5:$L$304,Events!$C$5:$C$304,"USD",Events!$D$5:$D$304,"High",Events!$L$5:$L$304,">="&NOW())),IF(_xlfn.MINIFS(Events!$L$5:$L$304,Events!$C$5:$C$304,"JPY",Events!$D$5:$D$304,"High",Events!$L$5:$L$304,">="&NOW())=0,9000000000,_xlfn.MINIFS(Events!$L$5:$L$304,Events!$C$5:$C$304,"JPY",Events!$D$5:$D$304,"High",Events!$L$5:$L$304,">="&NOW()))),"ddd d mmm")&" "&INDEX(Events!$C$5:$C$304,MATCH(MIN(IF(_xlfn.MINIFS(Events!$L$5:$L$304,Events!$C$5:$C$304,"USD",Events!$D$5:$D$304,"High",Events!$L$5:$L$304,">="&NOW())=0,9000000000,_xlfn.MINIFS(Events!$L$5:$L$304,Events!$C$5:$C$304,"USD",Events!$D$5:$D$304,"High",Events!$L$5:$L$304,">="&NOW())),IF(_xlfn.MINIFS(Events!$L$5:$L$304,Events!$C$5:$C$304,"JPY",Events!$D$5:$D$304,"High",Events!$L$5:$L$304,">="&NOW())=0,9000000000,_xlfn.MINIFS(Events!$L$5:$L$304,Events!$C$5:$C$304,"JPY",Events!$D$5:$D$304,"High",Events!$L$5:$L$304,">="&NOW()))),Events!$L$5:$L$304,0))&" "&INDEX(Events!$F$5:$F$304,MATCH(MIN(IF(_xlfn.MINIFS(Events!$L$5:$L$304,Events!$C$5:$C$304,"USD",Events!$D$5:$D$304,"High",Events!$L$5:$L$304,">="&NOW())=0,9000000000,_xlfn.MINIFS(Events!$L$5:$L$304,Events!$C$5:$C$304,"USD",Events!$D$5:$D$304,"High",Events!$L$5:$L$304,">="&NOW())),IF(_xlfn.MINIFS(Events!$L$5:$L$304,Events!$C$5:$C$304,"JPY",Events!$D$5:$D$304,"High",Events!$L$5:$L$304,">="&NOW())=0,9000000000,_xlfn.MINIFS(Events!$L$5:$L$304,Events!$C$5:$C$304,"JPY",Events!$D$5:$D$304,"High",Events!$L$5:$L$304,">="&NOW()))),Events!$L$5:$L$304,0))),"none scheduled") -> Thu 15 Oct USD Core PPI m/m
A9: XAUUSD | B9: =Bias!M8 -> SHORT | C9: SHORT | D9: Real yields +26 bp, DXY +3%, price −2.6% on the month: drivers and price now agree. Matches model SHORT. Floor: CB buying ~170t YTD and the 4,000–4,065 zone. | F9: SHORT | G9: Medium | H9: =IF(TRIM(F9)="","User: —",IF(AND(UPPER(TRIM(B9))=UPPER(TRIM(C9)),UPPER(TRIM(C9))=UPPER(TRIM(F9))),"ALL AGREE",IF(OR(UPPER(TRIM(B9))=UPPER(TRIM(C9)),UPPER(TRIM(C9))=UPPER(TRIM(F9)),UPPER(TRIM(B9))=UPPER(TRIM(F9))),"2 OF 3","SPLIT"))) -> ALL AGREE | I9: =IFERROR(IF(MIN(IF(_xlfn.MINIFS(Events!$L$5:$L$304,Events!$C$5:$C$304,"USD",Events!$D$5:$D$304,"High",Events!$L$5:$L$304,">="&NOW())=0,9000000000,_xlfn.MINIFS(Events!$L$5:$L$304,Events!$C$5:$C$304,"USD",Events!$D$5:$D$304,"High",Events!$L$5:$L$304,">="&NOW())))>900000000,"none scheduled",TEXT(MIN(IF(_xlfn.MINIFS(Events!$L$5:$L$304,Events!$C$5:$C$304,"USD",Events!$D$5:$D$304,"High",Events!$L$5:$L$304,">="&NOW())=0,9000000000,_xlfn.MINIFS(Events!$L$5:$L$304,Events!$C$5:$C$304,"USD",Events!$D$5:$D$304,"High",Events!$L$5:$L$304,">="&NOW()))),"ddd d mmm")&" "&INDEX(Events!$C$5:$C$304,MATCH(MIN(IF(_xlfn.MINIFS(Events!$L$5:$L$304,Events!$C$5:$C$304,"USD",Events!$D$5:$D$304,"High",Events!$L$5:$L$304,">="&NOW())=0,9000000000,_xlfn.MINIFS(Events!$L$5:$L$304,Events!$C$5:$C$304,"USD",Events!$D$5:$D$304,"High",Events!$L$5:$L$304,">="&NOW()))),Events!$L$5:$L$304,0))&" "&INDEX(Events!$F$5:$F$304,MATCH(MIN(IF(_xlfn.MINIFS(Events!$L$5:$L$304,Events!$C$5:$C$304,"USD",Events!$D$5:$D$304,"High",Events!$L$5:$L$304,">="&NOW())=0,9000000000,_xlfn.MINIFS(Events!$L$5:$L$304,Events!$C$5:$C$304,"USD",Events!$D$5:$D$304,"High",Events!$L$5:$L$304,">="&NOW()))),Events!$L$5:$L$304,0))),"none scheduled") -> Thu 15 Oct USD Core PPI m/m
A10: AI bias = Claude’s read of the evidence below, refreshed by prompt P7. It is one input, not a signal — the model bias and the User’s read still decide. Agreement: all three the same = green.
A12: COUNTRY BY COUNTRY
A14: USD · United States · Federal Reserve
A15: WHAT THEY'RE SAYING | F15: Indicator | G15: Now | H15: Before | I15: Change | J15: Score
A16: Last decision | B16: 16 Sep 2026 — hiked 25 bp to 3.75–4.00% (first hike of the cycle) | F16: Policy rate (%) | G16: =Scorecard!C5 -> 4 | H16: 3.75 | I16: =IF(COUNT(G16,H16)<2,"",ROUND((G16-H16)*100,0)) -> 25
A17: Vote | B17: 12–0 unanimous | F17: Core CPI YoY (%) | G17: =Scorecard!E5 -> 2.57 | H17: =Scorecard!F5 -> 2.57 | I17: =IF(COUNT(G17,H17)<2,"",G17-H17) -> 0 | J17: =Scorecard!M5 -> 1
A18: Central bank is saying | B18: Warsh (16 Sep): "Today's policy action will support a timelier return to the Committee's 2 percent goal." Williams (Oct): one more hike this year should be enough. Warsh speaks 16 Oct. | F18: Headline CPI YoY (%) | G18: 3.72 | H18: 3.46 | I18: =IF(COUNT(G18,H18)<2,"",G18-H18) -> 0.26
A19: Next meeting | B19: =IF(Scorecard!D5="","not in Events list",TEXT(Scorecard!D5,"ddd d mmm yyyy")&" — in "&(Scorecard!D5-TODAY())&" days") -> Wed 28 Oct 2026 — in 13 days | F19: Unemployment (%) | G19: =Scorecard!H5 -> 4.2 | H19: =Scorecard!I5 -> 4.2 | I19: =IF(COUNT(G19,H19)<2,"",G19-H19) -> 0 | J19: =Scorecard!N5 -> 0
A20: Market pricing — next meeting | B20: Oct 28: ≈32–50% hike (CME FedWatch, 14 Oct — jumped from 22% after the hot CPI; snapshots vary through the day) | F20: Wage growth YoY (%) | G20: 3.02 | H20: 3.38 | I20: =IF(COUNT(G20,H20)<2,"",G20-H20) -> -0.36
A21: Market pricing — further out | B21: ≈90% at least one more hike by the 9 Dec meeting (CME FedWatch, 14 Oct). TD: Oct hike unlikely — 6 days before the 3 Nov midterms. | F21: GDP growth q/q (%) | G21: 0.4 | H21: 0.5 | I21: =IF(COUNT(G21,H21)<2,"",G21-H21) -> -0.1
A22: Treasury / government is saying | B22: Bessent backs Warsh but says core inflation is quiet and the pressure is energy-led headline. Treasury running bond buybacks to cap the 30Y (19-yr high). Japan cut UST holdings 3 months running (July TIC). | F22: Composite PMI | G22: =Scorecard!J5 -> 58.4 | J22: =Scorecard!O5 -> 1
A23: Fiscal & political calendar | B23: US midterms 3 Nov — FOMC decision lands 6 days before. Long-end yields at a 19-year high keep funding costs in focus. | F23: 2Y yield (%) | G23: =Scorecard!K5 -> 4.75 | H23: =Scorecard!L5 -> 4.65 | I23: =IF(COUNT(G23,H23)<2,"",ROUND((G23-H23)*100,0)) -> 10 | J23: =Scorecard!P5 -> 0
A24: AI read (Claude) | B24: HAWKISH | C24: High | D24: FOR: Sep CPI 3.7% (core 2.6%, both above forecast), PMI 58.4, December hike ~90% priced. AGAINST: 2Y only +12 bp in a month and wages cooling (3.0%) — an October pause before the midterms is possible. | F24: Real 2Y yield (2Y − core CPI) | G24: =IF(COUNT(Scorecard!K5,Scorecard!E5)<2,"",Scorecard!K5-Scorecard!E5) -> 2.18 | H24: =IF(COUNT(Scorecard!L5,Scorecard!F5)<2,"",Scorecard!L5-Scorecard!F5) -> 2.08 | I24: =IF(COUNT(G24,H24)<2,"",G24-H24) -> 0.1
A25: User read | F25: TOTAL score → stance | G25: =Scorecard!Q5 -> 2 | J25: =Scorecard!R5 -> HAWKISH
A28: EUR · Euro area · European Central Bank
A29: WHAT THEY'RE SAYING | F29: Indicator | G29: Now | H29: Before | I29: Change | J29: Score
A30: Last decision | B30: 10 Sep 2026 — hiked 25 bp; deposit rate 2.50% (effective 16 Sep) | F30: Policy rate (%) | G30: =Scorecard!C6 -> 2.5 | H30: 2.25 | I30: =IF(COUNT(G30,H30)<2,"",ROUND((G30-H30)*100,0)) -> 25
A31: Vote | B31: Not published (ECB does not publish votes) | F31: Core CPI YoY (%) | G31: =Scorecard!E6 -> 2.5 | H31: =Scorecard!F6 -> 2.4 | I31: =IF(COUNT(G31,H31)<2,"",G31-H31) -> 0.1 | J31: =Scorecard!M6 -> 1
A32: Central bank is saying | B32: Wunsch (14 Oct): "We are probably going to have to hike again" — but no bets given energy uncertainty. Lagarde: a "measured response". | F32: Headline CPI YoY (%) | G32: 3.8 | H32: 2.8 | I32: =IF(COUNT(G32,H32)<2,"",G32-H32) -> 1
A33: Next meeting | B33: =IF(Scorecard!D6="","not in Events list",TEXT(Scorecard!D6,"ddd d mmm yyyy")&" — in "&(Scorecard!D6-TODAY())&" days") -> Thu 29 Oct 2026 — in 14 days | F33: Unemployment (%) | G33: =Scorecard!H6 -> 6.4 | H33: =Scorecard!I6 -> 6.4 | I33: =IF(COUNT(G33,H33)<2,"",G33-H33) -> 0 | J33: =Scorecard!N6 -> 0
A34: Market pricing — next meeting | B34: Oct 29: hold expected — Reuters poll (5–8 Oct) 70 of 73 see 2.50% unchanged | F34: Wage growth YoY (%) | G34: 2.6 | I34: =IF(COUNT(G34,H34)<2,"",G34-H34)
A35: Market pricing — further out | B35: December +25 bp is the poll's base case; BNY sees the ECB possibly done for the year unless gas prices spike. | F35: GDP growth q/q (%) | G35: 0.6 | H35: 0 | I35: =IF(COUNT(G35,H35)<2,"",G35-H35) -> 0.6
A36: Treasury / government is saying | B36: Germany 2027 draft budget: €555bn spending, record investment, €118.7bn net borrowing, defence €109.7bn — fiscal support for growth. | F36: Composite PMI | G36: =Scorecard!J6 -> 53.1 | J36: =Scorecard!O6 -> 1
A37: Fiscal & political calendar | B37: EU leaders' summit 14–15 Oct. Political and fiscal turmoil in Europe drove the euro net short to a 2020 high (CFTC, 6 Oct). | F37: 2Y yield (%) | G37: =Scorecard!K6 -> 3.05 | H37: =Scorecard!L6 -> 3.26 | I37: =IF(COUNT(G37,H37)<2,"",ROUND((G37-H37)*100,0)) -> -21 | J37: =Scorecard!P6 -> -1
A38: AI read (Claude) | B38: NEUTRAL | C38: Medium | D38: FOR: core HICP turned up to 2.5%, headline 3.8%, PMI 53.1 (3½-yr high). AGAINST: October hike priced out, German 2Y −19 bp in a month and speculators heavily short EUR. Hawkish words, dovish pricing. | F38: Real 2Y yield (2Y − core CPI) | G38: =IF(COUNT(Scorecard!K6,Scorecard!E6)<2,"",Scorecard!K6-Scorecard!E6) -> 0.55 | H38: =IF(COUNT(Scorecard!L6,Scorecard!F6)<2,"",Scorecard!L6-Scorecard!F6) -> 0.86 | I38: =IF(COUNT(G38,H38)<2,"",G38-H38) -> -0.31
A39: User read | F39: TOTAL score → stance | G39: =Scorecard!Q6 -> 1 | J39: =Scorecard!R6 -> NEUTRAL
A42: GBP · United Kingdom · Bank of England
A43: WHAT THEY'RE SAYING | F43: Indicator | G43: Now | H43: Before | I43: Change | J43: Score
A44: Last decision | B44: 17 Sep 2026 — held Bank Rate at 3.75% | F44: Policy rate (%) | G44: =Scorecard!C7 -> 3.75 | H44: 3.75 | I44: =IF(COUNT(G44,H44)<2,"",ROUND((G44-H44)*100,0)) -> 0
A45: Vote | B45: 6–3 (three voted to hike to 4.00%) | F45: Core CPI YoY (%) | G45: =Scorecard!E7 -> 2.6 | H45: =Scorecard!F7 -> 2.6 | I45: =IF(COUNT(G45,H45)<2,"",G45-H45) -> 0 | J45: =Scorecard!M7 -> 1
A46: Central bank is saying | B46: Bailey has hinted a rise is likely; Sep minutes said policy "may have to tighten" if the energy shock persists. Bailey speaks 15–17 Oct. | F46: Headline CPI YoY (%) | G46: 3.1 | H46: 2.8 | I46: =IF(COUNT(G46,H46)<2,"",G46-H46) -> 0.3
A47: Next meeting | B47: =IF(Scorecard!D7="","not in Events list",TEXT(Scorecard!D7,"ddd d mmm yyyy")&" — in "&(Scorecard!D7-TODAY())&" days") -> Thu 5 Nov 2026 — in 21 days | F47: Unemployment (%) | G47: =Scorecard!H7 -> 4.9 | H47: =Scorecard!I7 -> 4.9 | I47: =IF(COUNT(G47,H47)<2,"",G47-H47) -> 0 | J47: =Scorecard!N7 -> 0
A48: Market pricing — next meeting | B48: Nov 5: ≈95% hike to 4.00% (SONIA OIS via BlueGamma, 15 Oct; was 81% early Oct). Reuters poll: 54 of 63 expect the hike. | F48: Wage growth YoY (%) | G48: 3.5 | H48: 3.4 | I48: =IF(COUNT(G48,H48)<2,"",G48-H48) -> 0.1
A49: Market pricing — further out | B49: Four 25 bp hikes priced by end-2027; economists split on one more in Q1 2027. 2Y gilt 4.85%, flat on the month. | F49: GDP growth q/q (%) | G49: 0.5 | H49: 0.6 | I49: =IF(COUNT(G49,H49)<2,"",G49-H49) -> -0.1
A50: Treasury / government is saying | B50: Chancellor Healey: wants headroom to absorb shocks. Rising gilt yields cut the fiscal cushion by ~£12bn; UK borrowing costs highest in the G7. | F50: Composite PMI | G50: =Scorecard!J7 -> 52 | J50: =Scorecard!O7 -> 1
A51: Fiscal & political calendar | B51: Autumn Budget expected 28 Oct (date from the 21 Sep run — not re-confirmed on 15 Oct) lands a week before the 5 Nov BoE decision. UK Sep CPI 21 Oct. | F51: 2Y yield (%) | G51: =Scorecard!K7 -> 4.85 | H51: =Scorecard!L7 -> 4.92 | I51: =IF(COUNT(G51,H51)<2,"",ROUND((G51-H51)*100,0)) -> -7 | J51: =Scorecard!P7 -> 0
A52: AI read (Claude) | B52: HAWKISH | C52: High | D52: FOR: a November hike is ~95% priced and widely forecast; headline CPI 3.1% and rising. AGAINST: it is fully in the price (2Y flat), GDP cooling (0.5% q/q) and Budget/gilt stress can hit sterling even with a hike. | F52: Real 2Y yield (2Y − core CPI) | G52: =IF(COUNT(Scorecard!K7,Scorecard!E7)<2,"",Scorecard!K7-Scorecard!E7) -> 2.25 | H52: =IF(COUNT(Scorecard!L7,Scorecard!F7)<2,"",Scorecard!L7-Scorecard!F7) -> 2.32 | I52: =IF(COUNT(G52,H52)<2,"",G52-H52) -> -0.07
A53: User read | F53: TOTAL score → stance | G53: =Scorecard!Q7 -> 2 | J53: =Scorecard!R7 -> HAWKISH
A56: JPY · Japan · Bank of Japan
A57: WHAT THEY'RE SAYING | F57: Indicator | G57: Now | H57: Before | I57: Change | J57: Score
A58: Last decision | B58: 18 Sep 2026 — hiked to 1.25% (31-year high) | F58: Policy rate (%) | G58: =Scorecard!C8 -> 1.25 | H58: 1 | I58: =IF(COUNT(G58,H58)<2,"",ROUND((G58-H58)*100,0)) -> 25
A59: Vote | B59: 7–2 (Asada and Sato wanted to hold) | F59: Core CPI YoY (%) | G59: =Scorecard!E8 -> 1.9 | H59: =Scorecard!F8 -> 1.8 | I59: =IF(COUNT(G59,H59)<2,"",G59-H59) -> 0.1 | J59: =Scorecard!M8 -> 0
A60: Central bank is saying | B60: Ueda (6 Oct): will keep raising rates as activity, prices and financial conditions warrant — no signal on timing. Reports say the BoJ leans to an October pause. | F60: Headline CPI YoY (%) | G60: 1.9 | I60: =IF(COUNT(G60,H60)<2,"",G60-H60)
A61: Next meeting | B61: =IF(Scorecard!D8="","not in Events list",TEXT(Scorecard!D8,"ddd d mmm yyyy")&" — in "&(Scorecard!D8-TODAY())&" days") -> Fri 30 Oct 2026 — in 15 days | F61: Unemployment (%) | G61: =Scorecard!H8 -> 2.5 | H61: =Scorecard!I8 -> 2.5 | I61: =IF(COUNT(G61,H61)<2,"",G61-H61) -> 0 | J61: =Scorecard!N8 -> 0
A62: Market pricing — next meeting | B62: Oct 30: ≈10% hike (OIS, per Futunn/BigGo reports ~13 Oct) — a pause is the base case | F62: Wage growth YoY (%) | G62: 4.7 | I62: =IF(COUNT(G62,H62)<2,"",G62-H62)
A63: Market pricing — further out | B63: ≈88% for a hike by December. Ex-director Momma puts October at 20–30%. Outlook Report 30 Oct. | F63: GDP growth q/q (%) | G63: 0.35 | H63: 0.45 | I63: =IF(COUNT(G63,H63)<2,"",G63-H63) -> -0.1
A64: Treasury / government is saying | B64: No new intervention since the record ¥15.4tn (30 Jul–26 Aug). Reserves fell another $29.1bn in Sep to $1.178tn. 160–164 still the intervention zone. | F64: Composite PMI | G64: =Scorecard!J8 -> 52.3 | J64: =Scorecard!O8 -> 1
A65: Fiscal & political calendar | B65: PM Takaichi favours expansionary fiscal policy and appointed the two dissenters — political pressure against fast hikes. | F65: 2Y yield (%) | G65: =Scorecard!K8 -> 1.9 | H65: =Scorecard!L8 -> 1.84 | I65: =IF(COUNT(G65,H65)<2,"",ROUND((G65-H65)*100,0)) -> 6 | J65: =Scorecard!P8 -> 0
A66: AI read (Claude) | B66: NEUTRAL | C66: Low | D66: FOR: Dec hike ~88% priced, wages strong, speculators net long yen (+62k, CFTC 6 Oct). AGAINST: core-core 1.9% under target, October pause expected, 2Y only +7 bp. Intervention caps yen weakness near 160. | F66: Real 2Y yield (2Y − core CPI) | G66: =IF(COUNT(Scorecard!K8,Scorecard!E8)<2,"",Scorecard!K8-Scorecard!E8) -> 0 | H66: =IF(COUNT(Scorecard!L8,Scorecard!F8)<2,"",Scorecard!L8-Scorecard!F8) -> 0.04 | I66: =IF(COUNT(G66,H66)<2,"",G66-H66) -> -0.04
A67: User read | F67: TOTAL score → stance | G67: =Scorecard!Q8 -> 1 | J67: =Scorecard!R8 -> NEUTRAL
A70: XAU · Gold · drivers from Risk & Gold
A71: READ | F71: Driver | G71: Now | H71: 1M ago | I71: Change | J71: Score
A72: AI read (Claude) | B72: DOVISH | C72: Medium | D72: Drivers and price now agree: real yields +26 bp, DXY +3.0% and gold −2.6% on the month (4,264 → 4,151). Central-bank buying (+39t Aug) is the floor; managed money is cutting longs. AGAINST: ETF holdings at a 4-yr high. | F72: US 10Y real yield (%) | G72: ='Risk & Gold'!B13 -> 2.88 | H72: ='Risk & Gold'!C13 -> 2.62 | I72: ='Risk & Gold'!D13 -> 26 | J72: ='Risk & Gold'!E13 -> -1
F73: Dollar index (DXY) | G73: ='Risk & Gold'!B14 -> 102.11 | H73: ='Risk & Gold'!C14 -> 99.48 | I73: ='Risk & Gold'!D14 -> 2.6437475 | J73: ='Risk & Gold'!E14 -> -1
F74: Risk regime | G74: ='Risk & Gold'!B15 -> RISK-ON | J74: ='Risk & Gold'!E15 -> 0
A75: User read | F75: Research score | G75: ='Risk & Gold'!B16 -> 0 | J75: ='Risk & Gold'!E16 -> 0
F76: GOLD TOTAL → bias | G76: ='Risk & Gold'!E17 -> -2 | J76: ='Risk & Gold'!B18 -> SHORT
A78: Stance words in the AI read: HAWKISH = supports the currency (for gold: supportive), DOVISH = weighs on it, NEUTRAL = no clear push. Numbers in grey/green come from Scorecard and Risk & Gold; blue numbers (headline CPI, wages, GDP, previous rate) are filled by Claude — hover the indicator name to see which series.

Sheet Compare
A1: Pair Compare — side by side | L1: ← Guide
A2: Pick any two currencies from the Scorecard. Every factor shows who wins and whether it backs the call.
K3: PICK THE PAIR
A4: Factor | B4: =L4 -> USD | C4: ◀ base | D4: quote ▶ | E4: =L5 -> GBP | F4: Gap (base − quote) | G4: Winner | H4: Backs the call? | I4: What it measures | K4: Base currency | L4: USD
A5: Inflation score (−1…+1) | B5: =IFERROR(IF(INDEX(Scorecard!$M$5:$M$12,MATCH($L$4,Scorecard!$A$5:$A$12,0))="","",INDEX(Scorecard!$M$5:$M$12,MATCH($L$4,Scorecard!$A$5:$A$12,0))),"") -> 1 | C5: =IF(F5="","",REPT("■",MIN(6,ROUND(MAX(0,F5)*1,0)))) | D5: =IF(F5="","",REPT("■",MIN(6,ROUND(MAX(0,-F5)*1,0)))) | E5: =IFERROR(IF(INDEX(Scorecard!$M$5:$M$12,MATCH($L$5,Scorecard!$A$5:$A$12,0))="","",INDEX(Scorecard!$M$5:$M$12,MATCH($L$5,Scorecard!$A$5:$A$12,0))),"") -> 1 | F5: =IF(OR(B5="",E5=""),"",B5-E5) -> 0 | G5: =IF(F5="","",IF(ABS(F5)<0.1,"LEVEL",IF(F5>0,$L$4,$L$5))) -> LEVEL | H5: =IF(OR(G5="",G5="LEVEL",$L$9=""),"—",IF(G5=$L$9,"BACKS THE CALL","AGAINST")) -> — | I5: Core CPI vs target and direction | K5: Quote currency | L5: GBP
A6: Labour score (−1…+1) | B6: =IFERROR(IF(INDEX(Scorecard!$N$5:$N$12,MATCH($L$4,Scorecard!$A$5:$A$12,0))="","",INDEX(Scorecard!$N$5:$N$12,MATCH($L$4,Scorecard!$A$5:$A$12,0))),"") -> 0 | C6: =IF(F6="","",REPT("■",MIN(6,ROUND(MAX(0,F6)*1,0)))) | D6: =IF(F6="","",REPT("■",MIN(6,ROUND(MAX(0,-F6)*1,0)))) | E6: =IFERROR(IF(INDEX(Scorecard!$N$5:$N$12,MATCH($L$5,Scorecard!$A$5:$A$12,0))="","",INDEX(Scorecard!$N$5:$N$12,MATCH($L$5,Scorecard!$A$5:$A$12,0))),"") -> 0 | F6: =IF(OR(B6="",E6=""),"",B6-E6) -> 0 | G6: =IF(F6="","",IF(ABS(F6)<0.1,"LEVEL",IF(F6>0,$L$4,$L$5))) -> LEVEL | H6: =IF(OR(G6="",G6="LEVEL",$L$9=""),"—",IF(G6=$L$9,"BACKS THE CALL","AGAINST")) -> — | I6: 3-month change in unemployment | K6: Pair | L6: =L4&L5 -> USDGBP
A7: Growth score (−1…+1) | B7: =IFERROR(IF(INDEX(Scorecard!$O$5:$O$12,MATCH($L$4,Scorecard!$A$5:$A$12,0))="","",INDEX(Scorecard!$O$5:$O$12,MATCH($L$4,Scorecard!$A$5:$A$12,0))),"") -> 1 | C7: =IF(F7="","",REPT("■",MIN(6,ROUND(MAX(0,F7)*1,0)))) | D7: =IF(F7="","",REPT("■",MIN(6,ROUND(MAX(0,-F7)*1,0)))) | E7: =IFERROR(IF(INDEX(Scorecard!$O$5:$O$12,MATCH($L$5,Scorecard!$A$5:$A$12,0))="","",INDEX(Scorecard!$O$5:$O$12,MATCH($L$5,Scorecard!$A$5:$A$12,0))),"") -> 1 | F7: =IF(OR(B7="",E7=""),"",B7-E7) -> 0 | G7: =IF(F7="","",IF(ABS(F7)<0.1,"LEVEL",IF(F7>0,$L$4,$L$5))) -> LEVEL | H7: =IF(OR(G7="",G7="LEVEL",$L$9=""),"—",IF(G7=$L$9,"BACKS THE CALL","AGAINST")) -> — | I7: Composite PMI | K7: Direction from scores | L7: =IFERROR(IF(OR(INDEX(Scorecard!$Q$5:$Q$12,MATCH($L$4,Scorecard!$A$5:$A$12,0))="",INDEX(Scorecard!$Q$5:$Q$12,MATCH($L$5,Scorecard!$A$5:$A$12,0))=""),"ENTER DATA",IF(INDEX(Scorecard!$Q$5:$Q$12,MATCH($L$4,Scorecard!$A$5:$A$12,0))-INDEX(Scorecard!$Q$5:$Q$12,MATCH($L$5,Scorecard!$A$5:$A$12,0))>=Guide!$B$26,"LONG",IF(INDEX(Scorecard!$Q$5:$Q$12,MATCH($L$4,Scorecard!$A$5:$A$12,0))-INDEX(Scorecard!$Q$5:$Q$12,MATCH($L$5,Scorecard!$A$5:$A$12,0))<=-Guide!$B$26,"SHORT","FLAT"))),"PICK CURRENCIES") -> FLAT
A8: Pricing score (−1…+1) | B8: =IFERROR(IF(INDEX(Scorecard!$P$5:$P$12,MATCH($L$4,Scorecard!$A$5:$A$12,0))="","",INDEX(Scorecard!$P$5:$P$12,MATCH($L$4,Scorecard!$A$5:$A$12,0))),"") -> 0 | C8: =IF(F8="","",REPT("■",MIN(6,ROUND(MAX(0,F8)*1,0)))) | D8: =IF(F8="","",REPT("■",MIN(6,ROUND(MAX(0,-F8)*1,0)))) | E8: =IFERROR(IF(INDEX(Scorecard!$P$5:$P$12,MATCH($L$5,Scorecard!$A$5:$A$12,0))="","",INDEX(Scorecard!$P$5:$P$12,MATCH($L$5,Scorecard!$A$5:$A$12,0))),"") -> 0 | F8: =IF(OR(B8="",E8=""),"",B8-E8) -> 0 | G8: =IF(F8="","",IF(ABS(F8)<0.1,"LEVEL",IF(F8>0,$L$4,$L$5))) -> LEVEL | H8: =IF(OR(G8="",G8="LEVEL",$L$9=""),"—",IF(G8=$L$9,"BACKS THE CALL","AGAINST")) -> — | I8: 1-month move in 2Y yield = market repricing | K8: Final bias on Bias board | L8: =IFERROR(INDEX(Bias!$M$5:$M$8,MATCH(L6,Bias!$A$5:$A$8,0)),"not on board") -> not on board
A9: 2Y yield (%) | B9: =IFERROR(IF(INDEX(Scorecard!$K$5:$K$12,MATCH($L$4,Scorecard!$A$5:$A$12,0))="","",INDEX(Scorecard!$K$5:$K$12,MATCH($L$4,Scorecard!$A$5:$A$12,0))),"") -> 4.75 | C9: =IF(F9="","",REPT("■",MIN(6,ROUND(MAX(0,F9)*2,0)))) | D9: =IF(F9="","",REPT("■",MIN(6,ROUND(MAX(0,-F9)*2,0)))) | E9: =IFERROR(IF(INDEX(Scorecard!$K$5:$K$12,MATCH($L$5,Scorecard!$A$5:$A$12,0))="","",INDEX(Scorecard!$K$5:$K$12,MATCH($L$5,Scorecard!$A$5:$A$12,0))),"") -> 4.85 | F9: =IF(OR(B9="",E9=""),"",B9-E9) -> -0.1 | G9: =IF(F9="","",IF(ABS(F9)<0.1,"LEVEL",IF(F9>0,$L$4,$L$5))) -> LEVEL | H9: =IF(OR(G9="",G9="LEVEL",$L$9=""),"—",IF(G9=$L$9,"BACKS THE CALL","AGAINST")) -> — | I9: Level — the carry edge | K9: Currency the call favours | L9: =IF(L7="LONG",L4,IF(L7="SHORT",L5,""))
A10: Real 2Y yield (%) | B10: =IFERROR(IF(OR(INDEX(Scorecard!$K$5:$K$12,MATCH($L$4,Scorecard!$A$5:$A$12,0))="",INDEX(Scorecard!$E$5:$E$12,MATCH($L$4,Scorecard!$A$5:$A$12,0))=""),"",INDEX(Scorecard!$K$5:$K$12,MATCH($L$4,Scorecard!$A$5:$A$12,0))-INDEX(Scorecard!$E$5:$E$12,MATCH($L$4,Scorecard!$A$5:$A$12,0))),"") -> 2.18 | C10: =IF(F10="","",REPT("■",MIN(6,ROUND(MAX(0,F10)*2,0)))) | D10: =IF(F10="","",REPT("■",MIN(6,ROUND(MAX(0,-F10)*2,0)))) | E10: =IFERROR(IF(OR(INDEX(Scorecard!$K$5:$K$12,MATCH($L$5,Scorecard!$A$5:$A$12,0))="",INDEX(Scorecard!$E$5:$E$12,MATCH($L$5,Scorecard!$A$5:$A$12,0))=""),"",INDEX(Scorecard!$K$5:$K$12,MATCH($L$5,Scorecard!$A$5:$A$12,0))-INDEX(Scorecard!$E$5:$E$12,MATCH($L$5,Scorecard!$A$5:$A$12,0))),"") -> 2.25 | F10: =IF(OR(B10="",E10=""),"",B10-E10) -> -0.07 | G10: =IF(F10="","",IF(ABS(F10)<0.1,"LEVEL",IF(F10>0,$L$4,$L$5))) -> LEVEL | H10: =IF(OR(G10="",G10="LEVEL",$L$9=""),"—",IF(G10=$L$9,"BACKS THE CALL","AGAINST")) -> — | I10: 2Y yield minus core CPI — inflation-adjusted return
A11: Policy rate (%) | B11: =IFERROR(IF(INDEX(Scorecard!$C$5:$C$12,MATCH($L$4,Scorecard!$A$5:$A$12,0))="","",INDEX(Scorecard!$C$5:$C$12,MATCH($L$4,Scorecard!$A$5:$A$12,0))),"") -> 4 | C11: =IF(F11="","",REPT("■",MIN(6,ROUND(MAX(0,F11)*2,0)))) -> ■ | D11: =IF(F11="","",REPT("■",MIN(6,ROUND(MAX(0,-F11)*2,0)))) | E11: =IFERROR(IF(INDEX(Scorecard!$C$5:$C$12,MATCH($L$5,Scorecard!$A$5:$A$12,0))="","",INDEX(Scorecard!$C$5:$C$12,MATCH($L$5,Scorecard!$A$5:$A$12,0))),"") -> 3.75 | F11: =IF(OR(B11="",E11=""),"",B11-E11) -> 0.25 | G11: =IF(F11="","",IF(ABS(F11)<0.1,"LEVEL",IF(F11>0,$L$4,$L$5))) -> USD | H11: =IF(OR(G11="",G11="LEVEL",$L$9=""),"—",IF(G11=$L$9,"BACKS THE CALL","AGAINST")) -> — | I11: Where the central bank is now
A12: TOTAL SCORE | B12: =IFERROR(IF(INDEX(Scorecard!$Q$5:$Q$12,MATCH($L$4,Scorecard!$A$5:$A$12,0))="","",INDEX(Scorecard!$Q$5:$Q$12,MATCH($L$4,Scorecard!$A$5:$A$12,0))),"") -> 2 | E12: =IFERROR(IF(INDEX(Scorecard!$Q$5:$Q$12,MATCH($L$5,Scorecard!$A$5:$A$12,0))="","",INDEX(Scorecard!$Q$5:$Q$12,MATCH($L$5,Scorecard!$A$5:$A$12,0))),"") -> 2 | F12: =IF(OR(B12="",E12=""),"",B12-E12) -> 0
A14: DOES THE EVIDENCE BACK THE DIRECTION?
A15: Positive scores = hawkish pressure = supports that currency. Yield rows: 1 block ≈ 0.5 percentage point. Copy this sheet to keep several pairs open side by side.
A16: Scoreboard | B16: =L4&" wins "&COUNTIF(G5:G11,L4)&" of 7, "&L5&" wins "&COUNTIF(G5:G11,L5)&", level on "&COUNTIF(G5:G11,"LEVEL") -> USD wins 1 of 7, GBP wins 0, level on 6
A17: Verdict | B17: =IF(L9="","No directional call — use as comparison only",IF(COUNTIF(H5:H11,"BACKS THE CALL")>=5,"STRONG — evidence backs the call",IF(COUNTIF(H5:H11,"BACKS THE CALL")>COUNTIF(H5:H11,"AGAINST"),"MODERATE — more for than against","WEAK — evidence does not back the call"))) -> No directional call — use as comparison only
A18: Strongest reason to own the base | B18: =IF(MAX(F5:F8)>0,INDEX(A5:A8,MATCH(MAX(F5:F8),F5:F8,0))&" (gap +"&MAX(F5:F8)&")","None in the four scores") -> None in the four scores
A19: Strongest reason to own the quote | B19: =IF(MIN(F5:F8)<0,INDEX(A5:A8,MATCH(MIN(F5:F8),F5:F8,0))&" (gap "&MIN(F5:F8)&")","None in the four scores") -> None in the four scores
A20: why lean this way? | B20: EXAMPLE: USD repricing hawkishly while ECB is on hold; spread widening in USD's favour
A21: What keeps conviction down? (price not confirming, crowded positioning, catalyst ahead) | B21: EXAMPLE: EUR/USD not breaking structure yet; CPI next week

Sheet Events
A1: Economic Events — the data behind the Calendar | M1: ← Guide
A2: Claude refreshes this list every 2 days (prompt P1: Forex Factory weekly feed + central-bank calendars). The User can add rows anywhere; keep it sorted by Date, then Time. Type drives the tag colour on the Calendar.
A4: Date | B4: Time (CET) | C4: Ccy | D4: Impact | E4: Type | F4: Event | G4: Forecast | H4: Previous | I4: Actual | J4: User notes | K4: Rank | L4: When | M4: Day slot
A5: 46286 | C5: JPY | D5: Holiday | E5: Holiday | F5: Bank Holiday | K5: =IF(A5="","",IF(D5="High",3,IF(OR(D5="Medium",D5="Holiday"),2,1))) -> 2 | L5: =IF(A5="","",A5+B5) -> 46286 | M5: =IF(A5="","",IF(K5>=Calendar!$AC$5,TEXT(A5,"yyyymmdd")&"|"&COUNTIFS($A$5:A5,A5,$K$5:K5,">="&Calendar!$AC$5),"")) -> 20260921|1
A6: 46286 | B6: 0.70833333 | C6: EUR | D6: Medium | E6: CB speech | F6: ECB President Lagarde Speaks | K6: =IF(A6="","",IF(D6="High",3,IF(OR(D6="Medium",D6="Holiday"),2,1))) -> 2 | L6: =IF(A6="","",A6+B6) -> 46286.708 | M6: =IF(A6="","",IF(K6>=Calendar!$AC$5,TEXT(A6,"yyyymmdd")&"|"&COUNTIFS($A$5:A6,A6,$K$5:K6,">="&Calendar!$AC$5),"")) -> 20260921|2
A7: 46287 | C7: JPY | D7: Holiday | E7: Holiday | F7: Bank Holiday | K7: =IF(A7="","",IF(D7="High",3,IF(OR(D7="Medium",D7="Holiday"),2,1))) -> 2 | L7: =IF(A7="","",A7+B7) -> 46287 | M7: =IF(A7="","",IF(K7>=Calendar!$AC$5,TEXT(A7,"yyyymmdd")&"|"&COUNTIFS($A$5:A7,A7,$K$5:K7,">="&Calendar!$AC$5),"")) -> 20260922|1
A8: 46287 | B8: 0.21527778 | C8: AUD | D8: High | E8: CB speech | F8: RBA Gov Bullock Speaks | K8: =IF(A8="","",IF(D8="High",3,IF(OR(D8="Medium",D8="Holiday"),2,1))) -> 3 | L8: =IF(A8="","",A8+B8) -> 46287.215 | M8: =IF(A8="","",IF(K8>=Calendar!$AC$5,TEXT(A8,"yyyymmdd")&"|"&COUNTIFS($A$5:A8,A8,$K$5:K8,">="&Calendar!$AC$5),"")) -> 20260922|2
A9: 46287 | B9: 0.54166667 | C9: EUR | D9: Medium | E9: CB speech | F9: ECB President Lagarde Speaks | K9: =IF(A9="","",IF(D9="High",3,IF(OR(D9="Medium",D9="Holiday"),2,1))) -> 2 | L9: =IF(A9="","",A9+B9) -> 46287.542 | M9: =IF(A9="","",IF(K9>=Calendar!$AC$5,TEXT(A9,"yyyymmdd")&"|"&COUNTIFS($A$5:A9,A9,$K$5:K9,">="&Calendar!$AC$5),"")) -> 20260922|3
A10: 46288 | C10: JPY | D10: Holiday | E10: Holiday | F10: Bank Holiday | K10: =IF(A10="","",IF(D10="High",3,IF(OR(D10="Medium",D10="Holiday"),2,1))) -> 2 | L10: =IF(A10="","",A10+B10) -> 46288 | M10: =IF(A10="","",IF(K10>=Calendar!$AC$5,TEXT(A10,"yyyymmdd")&"|"&COUNTIFS($A$5:A10,A10,$K$5:K10,">="&Calendar!$AC$5),"")) -> 20260923|1
A11: 46288 | B11: 0.38541667 | C11: EUR | D11: Medium | E11: Growth & business | F11: French Flash Manufacturing PMI | G11: 50.9 | H11: 51.5 | K11: =IF(A11="","",IF(D11="High",3,IF(OR(D11="Medium",D11="Holiday"),2,1))) -> 2 | L11: =IF(A11="","",A11+B11) -> 46288.385 | M11: =IF(A11="","",IF(K11>=Calendar!$AC$5,TEXT(A11,"yyyymmdd")&"|"&COUNTIFS($A$5:A11,A11,$K$5:K11,">="&Calendar!$AC$5),"")) -> 20260923|2
A12: 46288 | B12: 0.38541667 | C12: EUR | D12: Medium | E12: Growth & business | F12: French Flash Services PMI | G12: 48.4 | H12: 48.4 | K12: =IF(A12="","",IF(D12="High",3,IF(OR(D12="Medium",D12="Holiday"),2,1))) -> 2 | L12: =IF(A12="","",A12+B12) -> 46288.385 | M12: =IF(A12="","",IF(K12>=Calendar!$AC$5,TEXT(A12,"yyyymmdd")&"|"&COUNTIFS($A$5:A12,A12,$K$5:K12,">="&Calendar!$AC$5),"")) -> 20260923|3
A13: 46288 | B13: 0.39583333 | C13: EUR | D13: Medium | E13: Growth & business | F13: German Flash Manufacturing PMI | G13: 54.0 | H13: 54.1 | K13: =IF(A13="","",IF(D13="High",3,IF(OR(D13="Medium",D13="Holiday"),2,1))) -> 2 | L13: =IF(A13="","",A13+B13) -> 46288.396 | M13: =IF(A13="","",IF(K13>=Calendar!$AC$5,TEXT(A13,"yyyymmdd")&"|"&COUNTIFS($A$5:A13,A13,$K$5:K13,">="&Calendar!$AC$5),"")) -> 20260923|4
A14: 46288 | B14: 0.39583333 | C14: EUR | D14: Medium | E14: Growth & business | F14: German Flash Services PMI | G14: 49.9 | H14: 48.5 | K14: =IF(A14="","",IF(D14="High",3,IF(OR(D14="Medium",D14="Holiday"),2,1))) -> 2 | L14: =IF(A14="","",A14+B14) -> 46288.396 | M14: =IF(A14="","",IF(K14>=Calendar!$AC$5,TEXT(A14,"yyyymmdd")&"|"&COUNTIFS($A$5:A14,A14,$K$5:K14,">="&Calendar!$AC$5),"")) -> 20260923|5
A15: 46288 | B15: 0.4375 | C15: GBP | D15: Medium | E15: Growth & business | F15: Flash Manufacturing PMI | G15: 51.4 | H15: 51.5 | K15: =IF(A15="","",IF(D15="High",3,IF(OR(D15="Medium",D15="Holiday"),2,1))) -> 2 | L15: =IF(A15="","",A15+B15) -> 46288.438 | M15: =IF(A15="","",IF(K15>=Calendar!$AC$5,TEXT(A15,"yyyymmdd")&"|"&COUNTIFS($A$5:A15,A15,$K$5:K15,">="&Calendar!$AC$5),"")) -> 20260923|6
A16: 46288 | B16: 0.4375 | C16: GBP | D16: Medium | E16: Growth & business | F16: Flash Services PMI | G16: 52.0 | H16: 52.8 | K16: =IF(A16="","",IF(D16="High",3,IF(OR(D16="Medium",D16="Holiday"),2,1))) -> 2 | L16: =IF(A16="","",A16+B16) -> 46288.438 | M16: =IF(A16="","",IF(K16>=Calendar!$AC$5,TEXT(A16,"yyyymmdd")&"|"&COUNTIFS($A$5:A16,A16,$K$5:K16,">="&Calendar!$AC$5),"")) -> 20260923|7
A17: 46289 | B17: 0.14583333 | C17: AUD | D17: High | E17: Jobs | F17: Employment Change | G17: 20.9K | H17: -15.8K | K17: =IF(A17="","",IF(D17="High",3,IF(OR(D17="Medium",D17="Holiday"),2,1))) -> 3 | L17: =IF(A17="","",A17+B17) -> 46289.146 | M17: =IF(A17="","",IF(K17>=Calendar!$AC$5,TEXT(A17,"yyyymmdd")&"|"&COUNTIFS($A$5:A17,A17,$K$5:K17,">="&Calendar!$AC$5),"")) -> 20260924|1
A18: 46289 | B18: 0.14583333 | C18: AUD | D18: High | E18: Jobs | F18: Unemployment Rate | G18: 4.5% | H18: 4.5% | K18: =IF(A18="","",IF(D18="High",3,IF(OR(D18="Medium",D18="Holiday"),2,1))) -> 3 | L18: =IF(A18="","",A18+B18) -> 46289.146 | M18: =IF(A18="","",IF(K18>=Calendar!$AC$5,TEXT(A18,"yyyymmdd")&"|"&COUNTIFS($A$5:A18,A18,$K$5:K18,">="&Calendar!$AC$5),"")) -> 20260924|2
A19: 46289 | B19: 0.39583333 | C19: CHF | D19: High | E19: Central bank | F19: SNB Monetary Policy Assessment | K19: =IF(A19="","",IF(D19="High",3,IF(OR(D19="Medium",D19="Holiday"),2,1))) -> 3 | L19: =IF(A19="","",A19+B19) -> 46289.396 | M19: =IF(A19="","",IF(K19>=Calendar!$AC$5,TEXT(A19,"yyyymmdd")&"|"&COUNTIFS($A$5:A19,A19,$K$5:K19,">="&Calendar!$AC$5),"")) -> 20260924|3
A20: 46289 | B20: 0.39583333 | C20: CHF | D20: High | E20: Central bank | F20: SNB Policy Rate | G20: 0.00% | H20: 0.00% | K20: =IF(A20="","",IF(D20="High",3,IF(OR(D20="Medium",D20="Holiday"),2,1))) -> 3 | L20: =IF(A20="","",A20+B20) -> 46289.396 | M20: =IF(A20="","",IF(K20>=Calendar!$AC$5,TEXT(A20,"yyyymmdd")&"|"&COUNTIFS($A$5:A20,A20,$K$5:K20,">="&Calendar!$AC$5),"")) -> 20260924|4
A21: 46289 | B21: 0.41666667 | C21: CHF | D21: High | E21: Central bank | F21: SNB Press Conference | K21: =IF(A21="","",IF(D21="High",3,IF(OR(D21="Medium",D21="Holiday"),2,1))) -> 3 | L21: =IF(A21="","",A21+B21) -> 46289.417 | M21: =IF(A21="","",IF(K21>=Calendar!$AC$5,TEXT(A21,"yyyymmdd")&"|"&COUNTIFS($A$5:A21,A21,$K$5:K21,">="&Calendar!$AC$5),"")) -> 20260924|5
A22: 46289 | B22: 0.60416667 | C22: USD | D22: Medium | E22: Jobs | F22: Unemployment Claims | G22: 201K | H22: 196K | K22: =IF(A22="","",IF(D22="High",3,IF(OR(D22="Medium",D22="Holiday"),2,1))) -> 2 | L22: =IF(A22="","",A22+B22) -> 46289.604 | M22: =IF(A22="","",IF(K22>=Calendar!$AC$5,TEXT(A22,"yyyymmdd")&"|"&COUNTIFS($A$5:A22,A22,$K$5:K22,">="&Calendar!$AC$5),"")) -> 20260924|6
A23: 46290 | B23: 0.46875 | C23: GBP | D23: High | E23: CB speech | F23: BOE Gov Bailey Speaks | K23: =IF(A23="","",IF(D23="High",3,IF(OR(D23="Medium",D23="Holiday"),2,1))) -> 3 | L23: =IF(A23="","",A23+B23) -> 46290.469 | M23: =IF(A23="","",IF(K23>=Calendar!$AC$5,TEXT(A23,"yyyymmdd")&"|"&COUNTIFS($A$5:A23,A23,$K$5:K23,">="&Calendar!$AC$5),"")) -> 20260925|1
A24: 46290 | B24: 0.66666667 | C24: USD | D24: Medium | E24: Growth & business | F24: Revised UoM Consumer Sentiment | G24: 47.5 | H24: 47.8 | K24: =IF(A24="","",IF(D24="High",3,IF(OR(D24="Medium",D24="Holiday"),2,1))) -> 2 | L24: =IF(A24="","",A24+B24) -> 46290.667 | M24: =IF(A24="","",IF(K24>=Calendar!$AC$5,TEXT(A24,"yyyymmdd")&"|"&COUNTIFS($A$5:A24,A24,$K$5:K24,">="&Calendar!$AC$5),"")) -> 20260925|2
A25: 46290 | B25: 0.66666667 | C25: USD | D25: Medium | E25: Inflation | F25: Revised UoM Inflation Expectations | H25: 4.6% | K25: =IF(A25="","",IF(D25="High",3,IF(OR(D25="Medium",D25="Holiday"),2,1))) -> 2 | L25: =IF(A25="","",A25+B25) -> 46290.667 | M25: =IF(A25="","",IF(K25>=Calendar!$AC$5,TEXT(A25,"yyyymmdd")&"|"&COUNTIFS($A$5:A25,A25,$K$5:K25,">="&Calendar!$AC$5),"")) -> 20260925|3
A26: 46297 | B26: 0.60416667 | C26: USD | D26: High | E26: Jobs | F26: Non-Farm Employment Change (Sep) + Unemployment Rate | I26: Unemp 4.2% | K26: =IF(A26="","",IF(D26="High",3,IF(OR(D26="Medium",D26="Holiday"),2,1))) -> 3 | L26: =IF(A26="","",A26+B26) -> 46297.604 | M26: =IF(A26="","",IF(K26>=Calendar!$AC$5,TEXT(A26,"yyyymmdd")&"|"&COUNTIFS($A$5:A26,A26,$K$5:K26,">="&Calendar!$AC$5),"")) -> 20261002|1
A27: 46307 | C27: JPY | D27: Holiday | E27: Holiday | F27: Bank Holiday | K27: =IF(A27="","",IF(D27="High",3,IF(OR(D27="Medium",D27="Holiday"),2,1))) -> 2 | L27: =IF(A27="","",A27+B27) -> 46307 | M27: =IF(A27="","",IF(K27>=Calendar!$AC$5,TEXT(A27,"yyyymmdd")&"|"&COUNTIFS($A$5:A27,A27,$K$5:K27,">="&Calendar!$AC$5),"")) -> 20261012|1
A28: 46307 | C28: USD | D28: Holiday | E28: Holiday | F28: Bank Holiday | K28: =IF(A28="","",IF(D28="High",3,IF(OR(D28="Medium",D28="Holiday"),2,1))) -> 2 | L28: =IF(A28="","",A28+B28) -> 46307 | M28: =IF(A28="","",IF(K28>=Calendar!$AC$5,TEXT(A28,"yyyymmdd")&"|"&COUNTIFS($A$5:A28,A28,$K$5:K28,">="&Calendar!$AC$5),"")) -> 20261012|2
A29: 46309 | B29: 0.17361111 | C29: EUR | D29: Medium | E29: CB speech | F29: ECB President Lagarde Speaks | K29: =IF(A29="","",IF(D29="High",3,IF(OR(D29="Medium",D29="Holiday"),2,1))) -> 2 | L29: =IF(A29="","",A29+B29) -> 46309.174 | M29: =IF(A29="","",IF(K29>=Calendar!$AC$5,TEXT(A29,"yyyymmdd")&"|"&COUNTIFS($A$5:A29,A29,$K$5:K29,">="&Calendar!$AC$5),"")) -> 20261014|1
A30: 46309 | B30: 0.3125 | C30: GBP | D30: Medium | E30: CB speech | F30: BOE Gov Bailey Speaks | K30: =IF(A30="","",IF(D30="High",3,IF(OR(D30="Medium",D30="Holiday"),2,1))) -> 2 | L30: =IF(A30="","",A30+B30) -> 46309.312 | M30: =IF(A30="","",IF(K30>=Calendar!$AC$5,TEXT(A30,"yyyymmdd")&"|"&COUNTIFS($A$5:A30,A30,$K$5:K30,">="&Calendar!$AC$5),"")) -> 20261014|2
A31: 46309 | B31: 0.4375 | C31: EUR | D31: Medium | E31: CB speech | F31: ECB President Lagarde Speaks | K31: =IF(A31="","",IF(D31="High",3,IF(OR(D31="Medium",D31="Holiday"),2,1))) -> 2 | L31: =IF(A31="","",A31+B31) -> 46309.438 | M31: =IF(A31="","",IF(K31>=Calendar!$AC$5,TEXT(A31,"yyyymmdd")&"|"&COUNTIFS($A$5:A31,A31,$K$5:K31,">="&Calendar!$AC$5),"")) -> 20261014|3
A32: 46309 | B32: 0.51041667 | C32: EUR | D32: Medium | E32: Government | F32: EU Economic Summit | K32: =IF(A32="","",IF(D32="High",3,IF(OR(D32="Medium",D32="Holiday"),2,1))) -> 2 | L32: =IF(A32="","",A32+B32) -> 46309.51 | M32: =IF(A32="","",IF(K32>=Calendar!$AC$5,TEXT(A32,"yyyymmdd")&"|"&COUNTIFS($A$5:A32,A32,$K$5:K32,">="&Calendar!$AC$5),"")) -> 20261014|4
A33: 46309 | B33: 0.60416667 | C33: USD | D33: High | E33: Inflation | F33: Core CPI m/m | G33: 0.2% | H33: 0.3% | K33: =IF(A33="","",IF(D33="High",3,IF(OR(D33="Medium",D33="Holiday"),2,1))) -> 3 | L33: =IF(A33="","",A33+B33) -> 46309.604 | M33: =IF(A33="","",IF(K33>=Calendar!$AC$5,TEXT(A33,"yyyymmdd")&"|"&COUNTIFS($A$5:A33,A33,$K$5:K33,">="&Calendar!$AC$5),"")) -> 20261014|5
A34: 46309 | B34: 0.60416667 | C34: USD | D34: High | E34: Inflation | F34: Core CPI y/y | G34: 2.5% | H34: 2.4% | I34: 2.6% | K34: =IF(A34="","",IF(D34="High",3,IF(OR(D34="Medium",D34="Holiday"),2,1))) -> 3 | L34: =IF(A34="","",A34+B34) -> 46309.604 | M34: =IF(A34="","",IF(K34>=Calendar!$AC$5,TEXT(A34,"yyyymmdd")&"|"&COUNTIFS($A$5:A34,A34,$K$5:K34,">="&Calendar!$AC$5),"")) -> 20261014|6
A35: 46309 | B35: 0.60416667 | C35: USD | D35: High | E35: Inflation | F35: CPI m/m | G35: 0.6% | H35: 0.4% | K35: =IF(A35="","",IF(D35="High",3,IF(OR(D35="Medium",D35="Holiday"),2,1))) -> 3 | L35: =IF(A35="","",A35+B35) -> 46309.604 | M35: =IF(A35="","",IF(K35>=Calendar!$AC$5,TEXT(A35,"yyyymmdd")&"|"&COUNTIFS($A$5:A35,A35,$K$5:K35,">="&Calendar!$AC$5),"")) -> 20261014|7
A36: 46309 | B36: 0.60416667 | C36: USD | D36: High | E36: Inflation | F36: CPI y/y | G36: 3.6% | H36: 3.4% | I36: 3.7% | K36: =IF(A36="","",IF(D36="High",3,IF(OR(D36="Medium",D36="Holiday"),2,1))) -> 3 | L36: =IF(A36="","",A36+B36) -> 46309.604 | M36: =IF(A36="","",IF(K36>=Calendar!$AC$5,TEXT(A36,"yyyymmdd")&"|"&COUNTIFS($A$5:A36,A36,$K$5:K36,">="&Calendar!$AC$5),"")) -> 20261014|8
A37: 46310 | B37: 0.10416667 | C37: AUD | D37: High | E37: Jobs | F37: Employment Change | G37: 19.6K | H37: 39.5K | K37: =IF(A37="","",IF(D37="High",3,IF(OR(D37="Medium",D37="Holiday"),2,1))) -> 3 | L37: =IF(A37="","",A37+B37) -> 46310.104 | M37: =IF(A37="","",IF(K37>=Calendar!$AC$5,TEXT(A37,"yyyymmdd")&"|"&COUNTIFS($A$5:A37,A37,$K$5:K37,">="&Calendar!$AC$5),"")) -> 20261015|1
A38: 46310 | B38: 0.10416667 | C38: AUD | D38: High | E38: Jobs | F38: Unemployment Rate | G38: 4.6% | H38: 4.6% | K38: =IF(A38="","",IF(D38="High",3,IF(OR(D38="Medium",D38="Holiday"),2,1))) -> 3 | L38: =IF(A38="","",A38+B38) -> 46310.104 | M38: =IF(A38="","",IF(K38>=Calendar!$AC$5,TEXT(A38,"yyyymmdd")&"|"&COUNTIFS($A$5:A38,A38,$K$5:K38,">="&Calendar!$AC$5),"")) -> 20261015|2
A39: 46310 | B39: 0.33333333 | C39: GBP | D39: High | E39: Growth & business | F39: GDP m/m | G39: -0.1% | H39: 0.4% | K39: =IF(A39="","",IF(D39="High",3,IF(OR(D39="Medium",D39="Holiday"),2,1))) -> 3 | L39: =IF(A39="","",A39+B39) -> 46310.333 | M39: =IF(A39="","",IF(K39>=Calendar!$AC$5,TEXT(A39,"yyyymmdd")&"|"&COUNTIFS($A$5:A39,A39,$K$5:K39,">="&Calendar!$AC$5),"")) -> 20261015|3
A40: 46310 | B40: 0.39583333 | C40: GBP | D40: Medium | E40: CB speech | F40: BOE Gov Bailey Speaks | K40: =IF(A40="","",IF(D40="High",3,IF(OR(D40="Medium",D40="Holiday"),2,1))) -> 2 | L40: =IF(A40="","",A40+B40) -> 46310.396 | M40: =IF(A40="","",IF(K40>=Calendar!$AC$5,TEXT(A40,"yyyymmdd")&"|"&COUNTIFS($A$5:A40,A40,$K$5:K40,">="&Calendar!$AC$5),"")) -> 20261015|4
A41: 46310 | B41: 0.51041667 | C41: EUR | D41: Medium | E41: Government | F41: EU Economic Summit | K41: =IF(A41="","",IF(D41="High",3,IF(OR(D41="Medium",D41="Holiday"),2,1))) -> 2 | L41: =IF(A41="","",A41+B41) -> 46310.51 | M41: =IF(A41="","",IF(K41>=Calendar!$AC$5,TEXT(A41,"yyyymmdd")&"|"&COUNTIFS($A$5:A41,A41,$K$5:K41,">="&Calendar!$AC$5),"")) -> 20261015|5
A42: 46310 | B42: 0.60416667 | C42: USD | D42: High | E42: Inflation | F42: Core PPI m/m | G42: 0.3% | H42: 0.2% | K42: =IF(A42="","",IF(D42="High",3,IF(OR(D42="Medium",D42="Holiday"),2,1))) -> 3 | L42: =IF(A42="","",A42+B42) -> 46310.604 | M42: =IF(A42="","",IF(K42>=Calendar!$AC$5,TEXT(A42,"yyyymmdd")&"|"&COUNTIFS($A$5:A42,A42,$K$5:K42,">="&Calendar!$AC$5),"")) -> 20261015|6
A43: 46310 | B43: 0.60416667 | C43: USD | D43: High | E43: Growth & business | F43: Core Retail Sales m/m | G43: 0.6% | H43: 1.4% | K43: =IF(A43="","",IF(D43="High",3,IF(OR(D43="Medium",D43="Holiday"),2,1))) -> 3 | L43: =IF(A43="","",A43+B43) -> 46310.604 | M43: =IF(A43="","",IF(K43>=Calendar!$AC$5,TEXT(A43,"yyyymmdd")&"|"&COUNTIFS($A$5:A43,A43,$K$5:K43,">="&Calendar!$AC$5),"")) -> 20261015|7
A44: 46310 | B44: 0.60416667 | C44: USD | D44: High | E44: Inflation | F44: PPI m/m | G44: 0.6% | H44: 0.4% | K44: =IF(A44="","",IF(D44="High",3,IF(OR(D44="Medium",D44="Holiday"),2,1))) -> 3 | L44: =IF(A44="","",A44+B44) -> 46310.604 | M44: =IF(A44="","",IF(K44>=Calendar!$AC$5,TEXT(A44,"yyyymmdd")&"|"&COUNTIFS($A$5:A44,A44,$K$5:K44,">="&Calendar!$AC$5),"")) -> 20261015|8
A45: 46310 | B45: 0.60416667 | C45: USD | D45: High | E45: Growth & business | F45: Retail Sales m/m | G45: 0.3% | H45: 1.2% | K45: =IF(A45="","",IF(D45="High",3,IF(OR(D45="Medium",D45="Holiday"),2,1))) -> 3 | L45: =IF(A45="","",A45+B45) -> 46310.604 | M45: =IF(A45="","",IF(K45>=Calendar!$AC$5,TEXT(A45,"yyyymmdd")&"|"&COUNTIFS($A$5:A45,A45,$K$5:K45,">="&Calendar!$AC$5),"")) -> 20261015|9
A46: 46310 | B46: 0.60416667 | C46: USD | D46: Medium | E46: Growth & business | F46: Philly Fed Manufacturing Index | G46: 28.2 | H46: 37.8 | K46: =IF(A46="","",IF(D46="High",3,IF(OR(D46="Medium",D46="Holiday"),2,1))) -> 2 | L46: =IF(A46="","",A46+B46) -> 46310.604 | M46: =IF(A46="","",IF(K46>=Calendar!$AC$5,TEXT(A46,"yyyymmdd")&"|"&COUNTIFS($A$5:A46,A46,$K$5:K46,">="&Calendar!$AC$5),"")) -> 20261015|10
A47: 46310 | B47: 0.60416667 | C47: USD | D47: Medium | E47: Jobs | F47: Unemployment Claims | G47: 199K | H47: 197K | K47: =IF(A47="","",IF(D47="High",3,IF(OR(D47="Medium",D47="Holiday"),2,1))) -> 2 | L47: =IF(A47="","",A47+B47) -> 46310.604 | M47: =IF(A47="","",IF(K47>=Calendar!$AC$5,TEXT(A47,"yyyymmdd")&"|"&COUNTIFS($A$5:A47,A47,$K$5:K47,">="&Calendar!$AC$5),"")) -> 20261015|11
A48: 46311 | B48: 0.16666667 | C48: GBP | D48: High | E48: CB speech | F48: BOE Gov Bailey Speaks | K48: =IF(A48="","",IF(D48="High",3,IF(OR(D48="Medium",D48="Holiday"),2,1))) -> 3 | L48: =IF(A48="","",A48+B48) -> 46311.167 | M48: =IF(A48="","",IF(K48>=Calendar!$AC$5,TEXT(A48,"yyyymmdd")&"|"&COUNTIFS($A$5:A48,A48,$K$5:K48,">="&Calendar!$AC$5),"")) -> 20261016|1
A49: 46311 | B49: 0.22916667 | C49: USD | D49: High | E49: CB speech | F49: Fed Chairman Warsh Speaks | K49: =IF(A49="","",IF(D49="High",3,IF(OR(D49="Medium",D49="Holiday"),2,1))) -> 3 | L49: =IF(A49="","",A49+B49) -> 46311.229 | M49: =IF(A49="","",IF(K49>=Calendar!$AC$5,TEXT(A49,"yyyymmdd")&"|"&COUNTIFS($A$5:A49,A49,$K$5:K49,">="&Calendar!$AC$5),"")) -> 20261016|2
A50: 46312 | B50: 0.36458333 | C50: GBP | D50: Medium | E50: CB speech | F50: BOE Gov Bailey Speaks | K50: =IF(A50="","",IF(D50="High",3,IF(OR(D50="Medium",D50="Holiday"),2,1))) -> 2 | L50: =IF(A50="","",A50+B50) -> 46312.365 | M50: =IF(A50="","",IF(K50>=Calendar!$AC$5,TEXT(A50,"yyyymmdd")&"|"&COUNTIFS($A$5:A50,A50,$K$5:K50,">="&Calendar!$AC$5),"")) -> 20261017|1
A51: 46323 | B51: 0.79166667 | C51: USD | D51: High | E51: Central bank | F51: FOMC rate decision + press conference | K51: =IF(A51="","",IF(D51="High",3,IF(OR(D51="Medium",D51="Holiday"),2,1))) -> 3 | L51: =IF(A51="","",A51+B51) -> 46323.792 | M51: =IF(A51="","",IF(K51>=Calendar!$AC$5,TEXT(A51,"yyyymmdd")&"|"&COUNTIFS($A$5:A51,A51,$K$5:K51,">="&Calendar!$AC$5),"")) -> 20261028|1
A52: 46324 | B52: 0.59375 | C52: EUR | D52: High | E52: Central bank | F52: ECB rate decision + press conference | K52: =IF(A52="","",IF(D52="High",3,IF(OR(D52="Medium",D52="Holiday"),2,1))) -> 3 | L52: =IF(A52="","",A52+B52) -> 46324.594 | M52: =IF(A52="","",IF(K52>=Calendar!$AC$5,TEXT(A52,"yyyymmdd")&"|"&COUNTIFS($A$5:A52,A52,$K$5:K52,">="&Calendar!$AC$5),"")) -> 20261029|1
A53: 46325 | B53: 0.16666667 | C53: JPY | D53: High | E53: Central bank | F53: BoJ rate decision (no fixed time — usually 04:00–06:00) | K53: =IF(A53="","",IF(D53="High",3,IF(OR(D53="Medium",D53="Holiday"),2,1))) -> 3 | L53: =IF(A53="","",A53+B53) -> 46325.167 | M53: =IF(A53="","",IF(K53>=Calendar!$AC$5,TEXT(A53,"yyyymmdd")&"|"&COUNTIFS($A$5:A53,A53,$K$5:K53,">="&Calendar!$AC$5),"")) -> 20261030|1
A54: 46331 | B54: 0.54166667 | C54: GBP | D54: High | E54: Central bank | F54: BoE rate decision + Monetary Policy Report | K54: =IF(A54="","",IF(D54="High",3,IF(OR(D54="Medium",D54="Holiday"),2,1))) -> 3 | L54: =IF(A54="","",A54+B54) -> 46331.542 | M54: =IF(A54="","",IF(K54>=Calendar!$AC$5,TEXT(A54,"yyyymmdd")&"|"&COUNTIFS($A$5:A54,A54,$K$5:K54,">="&Calendar!$AC$5),"")) -> 20261105|1
A55: 46332 | B55: 0.60416667 | C55: USD | D55: High | E55: Jobs | F55: Non-Farm Employment Change (Oct) + Unemployment Rate | K55: =IF(A55="","",IF(D55="High",3,IF(OR(D55="Medium",D55="Holiday"),2,1))) -> 3 | L55: =IF(A55="","",A55+B55) -> 46332.604 | M55: =IF(A55="","",IF(K55>=Calendar!$AC$5,TEXT(A55,"yyyymmdd")&"|"&COUNTIFS($A$5:A55,A55,$K$5:K55,">="&Calendar!$AC$5),"")) -> 20261106|1
A56: 46336 | B56: 0.60416667 | C56: USD | D56: High | E56: Inflation | F56: CPI (Oct) | K56: =IF(A56="","",IF(D56="High",3,IF(OR(D56="Medium",D56="Holiday"),2,1))) -> 3 | L56: =IF(A56="","",A56+B56) -> 46336.604 | M56: =IF(A56="","",IF(K56>=Calendar!$AC$5,TEXT(A56,"yyyymmdd")&"|"&COUNTIFS($A$5:A56,A56,$K$5:K56,">="&Calendar!$AC$5),"")) -> 20261110|1
A57: 46360 | B57: 0.60416667 | C57: USD | D57: High | E57: Jobs | F57: Non-Farm Employment Change (Nov) + Unemployment Rate | K57: =IF(A57="","",IF(D57="High",3,IF(OR(D57="Medium",D57="Holiday"),2,1))) -> 3 | L57: =IF(A57="","",A57+B57) -> 46360.604 | M57: =IF(A57="","",IF(K57>=Calendar!$AC$5,TEXT(A57,"yyyymmdd")&"|"&COUNTIFS($A$5:A57,A57,$K$5:K57,">="&Calendar!$AC$5),"")) -> 20261204|1
A58: 46365 | B58: 0.83333333 | C58: USD | D58: High | E58: Central bank | F58: FOMC rate decision + projections (SEP) | K58: =IF(A58="","",IF(D58="High",3,IF(OR(D58="Medium",D58="Holiday"),2,1))) -> 3 | L58: =IF(A58="","",A58+B58) -> 46365.833 | M58: =IF(A58="","",IF(K58>=Calendar!$AC$5,TEXT(A58,"yyyymmdd")&"|"&COUNTIFS($A$5:A58,A58,$K$5:K58,">="&Calendar!$AC$5),"")) -> 20261209|1
A59: 46366 | B59: 0.60416667 | C59: USD | D59: High | E59: Inflation | F59: CPI (Nov) | K59: =IF(A59="","",IF(D59="High",3,IF(OR(D59="Medium",D59="Holiday"),2,1))) -> 3 | L59: =IF(A59="","",A59+B59) -> 46366.604 | M59: =IF(A59="","",IF(K59>=Calendar!$AC$5,TEXT(A59,"yyyymmdd")&"|"&COUNTIFS($A$5:A59,A59,$K$5:K59,">="&Calendar!$AC$5),"")) -> 20261210|1
... A62: 46374 | B62: 0.16666667 | C62: JPY | D62: High | E62: Central bank | F62: BoJ rate decision + Outlook (no fixed time) | K62: =IF(A62="","",IF(D62="High",3,IF(OR(D62="Medium",D62="Holiday"),2,1))) -> 3 | L62: =IF(A62="","",A62+B62) -> 46374.167 | M62: =IF(A62="","",IF(K62>=Calendar!$AC$5,TEXT(A62,"yyyymmdd")&"|"&COUNTIFS($A$5:A62,A62,$K$5:K62,">="&Calendar!$AC$5),"")) -> 20261218|1
K63: =IF(A63="","",IF(D63="High",3,IF(OR(D63="Medium",D63="Holiday"),2,1))) | L63: =IF(A63="","",A63+B63) | M63: =IF(A63="","",IF(K63>=Calendar!$AC$5,TEXT(A63,"yyyymmdd")&"|"&COUNTIFS($A$5:A63,A63,$K$5:K63,">="&Calendar!$AC$5),""))
K64: =IF(A64="","",IF(D64="High",3,IF(OR(D64="Medium",D64="Holiday"),2,1))) | L64: =IF(A64="","",A64+B64) | M64: =IF(A64="","",IF(K64>=Calendar!$AC$5,TEXT(A64,"yyyymmdd")&"|"&COUNTIFS($A$5:A64,A64,$K$5:K64,">="&Calendar!$AC$5),""))
K65: =IF(A65="","",IF(D65="High",3,IF(OR(D65="Medium",D65="Holiday"),2,1))) | L65: =IF(A65="","",A65+B65) | M65: =IF(A65="","",IF(K65>=Calendar!$AC$5,TEXT(A65,"yyyymmdd")&"|"&COUNTIFS($A$5:A65,A65,$K$5:K65,">="&Calendar!$AC$5),""))
K66: =IF(A66="","",IF(D66="High",3,IF(OR(D66="Medium",D66="Holiday"),2,1))) | L66: =IF(A66="","",A66+B66) | M66: =IF(A66="","",IF(K66>=Calendar!$AC$5,TEXT(A66,"yyyymmdd")&"|"&COUNTIFS($A$5:A66,A66,$K$5:K66,">="&Calendar!$AC$5),""))
K67: =IF(A67="","",IF(D67="High",3,IF(OR(D67="Medium",D67="Holiday"),2,1))) | L67: =IF(A67="","",A67+B67) | M67: =IF(A67="","",IF(K67>=Calendar!$AC$5,TEXT(A67,"yyyymmdd")&"|"&COUNTIFS($A$5:A67,A67,$K$5:K67,">="&Calendar!$AC$5),""))
K68: =IF(A68="","",IF(D68="High",3,IF(OR(D68="Medium",D68="Holiday"),2,1))) | L68: =IF(A68="","",A68+B68) | M68: =IF(A68="","",IF(K68>=Calendar!$AC$5,TEXT(A68,"yyyymmdd")&"|"&COUNTIFS($A$5:A68,A68,$K$5:K68,">="&Calendar!$AC$5),""))
K69: =IF(A69="","",IF(D69="High",3,IF(OR(D69="Medium",D69="Holiday"),2,1))) | L69: =IF(A69="","",A69+B69) | M69: =IF(A69="","",IF(K69>=Calendar!$AC$5,TEXT(A69,"yyyymmdd")&"|"&COUNTIFS($A$5:A69,A69,$K$5:K69,">="&Calendar!$AC$5),""))
K70: =IF(A70="","",IF(D70="High",3,IF(OR(D70="Medium",D70="Holiday"),2,1))) | L70: =IF(A70="","",A70+B70) | M70: =IF(A70="","",IF(K70>=Calendar!$AC$5,TEXT(A70,"yyyymmdd")&"|"&COUNTIFS($A$5:A70,A70,$K$5:K70,">="&Calendar!$AC$5),""))
K71: =IF(A71="","",IF(D71="High",3,IF(OR(D71="Medium",D71="Holiday"),2,1))) | L71: =IF(A71="","",A71+B71) | M71: =IF(A71="","",IF(K71>=Calendar!$AC$5,TEXT(A71,"yyyymmdd")&"|"&COUNTIFS($A$5:A71,A71,$K$5:K71,">="&Calendar!$AC$5),""))
K72: =IF(A72="","",IF(D72="High",3,IF(OR(D72="Medium",D72="Holiday"),2,1))) | L72: =IF(A72="","",A72+B72) | M72: =IF(A72="","",IF(K72>=Calendar!$AC$5,TEXT(A72,"yyyymmdd")&"|"&COUNTIFS($A$5:A72,A72,$K$5:K72,">="&Calendar!$AC$5),""))
K73: =IF(A73="","",IF(D73="High",3,IF(OR(D73="Medium",D73="Holiday"),2,1))) | L73: =IF(A73="","",A73+B73) | M73: =IF(A73="","",IF(K73>=Calendar!$AC$5,TEXT(A73,"yyyymmdd")&"|"&COUNTIFS($A$5:A73,A73,$K$5:K73,">="&Calendar!$AC$5),""))
K74: =IF(A74="","",IF(D74="High",3,IF(OR(D74="Medium",D74="Holiday"),2,1))) | L74: =IF(A74="","",A74+B74) | M74: =IF(A74="","",IF(K74>=Calendar!$AC$5,TEXT(A74,"yyyymmdd")&"|"&COUNTIFS($A$5:A74,A74,$K$5:K74,">="&Calendar!$AC$5),""))
... K304: =IF(A304="","",IF(D304="High",3,IF(OR(D304="Medium",D304="Holiday"),2,1))) | L304: =IF(A304="","",A304+B304) | M304: =IF(A304="","",IF(K304>=Calendar!$AC$5,TEXT(A304,"yyyymmdd")&"|"&COUNTIFS($A$5:A304,A304,$K$5:K304,">="&Calendar!$AC$5),""))

Sheet Scorecard
A1: Currency Scorecard | S1: ← Guide
A2: LIVE DATA as of 15 Oct 2026 — market inputs from TradingView, macro stats from official sources (Sources sheet). AUD, NZD, CAD, CHF not filled (User doesn't trade them yet).
A4: Currency | B4: Central bank | C4: Policy rate (%) | D4: Next meeting | E4: Core CPI YoY (%) | F4: Core CPI 3M ago (%) | G4: Inflation target (%) | H4: Unemployment (%) | I4: Unemployment 3M ago (%) | J4: Composite PMI | K4: 2Y yield (%) | L4: 2Y yield 1M ago (%) | M4: Inflation score | N4: Labour score | O4: Growth score | P4: Pricing score (2Y) | Q4: TOTAL | R4: STANCE | S4: Notes — what would change it?
A5: USD | B5: Fed | C5: 4 | D5: =IFERROR(1/(1/_xlfn.MINIFS(Events!$A$5:$A$304,Events!$C$5:$C$304,$A5,Events!$E$5:$E$304,"Central bank",Events!$A$5:$A$304,">="&TODAY())),"") -> 46323 | E5: 2.57 | F5: 2.57 | G5: 2 | H5: 4.2 | I5: 4.2 | J5: 58.4 | K5: 4.75 | L5: 4.65 | M5: =IF(COUNT(E5,F5,G5)<3,"",IF(AND(E5>G5,E5>=F5),1,IF(AND(E5<F5,E5<=G5+Guide!$B$20),-1,0))) -> 1 | N5: =IF(COUNT(H5,I5)<2,"",IF(H5-I5<=-Guide!$B$21,1,IF(H5-I5>=Guide!$B$21,-1,0))) -> 0 | O5: =IF(J5="","",IF(J5>=Guide!$B$22,1,IF(J5<=Guide!$B$23,-1,0))) -> 1 | P5: =IF(COUNT(K5,L5)<2,"",IF((K5-L5)*100>=Guide!$B$24,1,IF((K5-L5)*100<=-Guide!$B$24,-1,0))) -> 0 | Q5: =IF(COUNT(M5:P5)<4,"",SUM(M5:P5)) -> 2 | R5: =IF(Q5="","ENTER DATA",IF(Q5>=Guide!$B$25,"HAWKISH",IF(Q5<=-Guide!$B$25,"DOVISH","NEUTRAL"))) -> HAWKISH | S5: Sep CPI hot (3.7% headline, core 2.57% and rising) flips inflation to +1; PMI 58.4 = 5-yr high. 2Y +12 bp (<15) so pricing score 0 — a 2Y close above ~4.82 flips it back to +1. Labour now 0 (4.2% both).
A6: EUR | B6: ECB | C6: 2.5 | D6: =IFERROR(1/(1/_xlfn.MINIFS(Events!$A$5:$A$304,Events!$C$5:$C$304,$A6,Events!$E$5:$E$304,"Central bank",Events!$A$5:$A$304,">="&TODAY())),"") -> 46324 | E6: 2.5 | F6: 2.4 | G6: 2 | H6: 6.4 | I6: 6.4 | J6: 53.1 | K6: 3.05 | L6: 3.26 | M6: =IF(COUNT(E6,F6,G6)<3,"",IF(AND(E6>G6,E6>=F6),1,IF(AND(E6<F6,E6<=G6+Guide!$B$20),-1,0))) -> 1 | N6: =IF(COUNT(H6,I6)<2,"",IF(H6-I6<=-Guide!$B$21,1,IF(H6-I6>=Guide!$B$21,-1,0))) -> 0 | O6: =IF(J6="","",IF(J6>=Guide!$B$22,1,IF(J6<=Guide!$B$23,-1,0))) -> 1 | P6: =IF(COUNT(K6,L6)<2,"",IF((K6-L6)*100>=Guide!$B$24,1,IF((K6-L6)*100<=-Guide!$B$24,-1,0))) -> -1 | Q6: =IF(COUNT(M6:P6)<4,"",SUM(M6:P6)) -> 1 | R6: =IF(Q6="","ENTER DATA",IF(Q6>=Guide!$B$25,"HAWKISH",IF(Q6<=-Guide!$B$25,"DOVISH","NEUTRAL"))) -> NEUTRAL | S6: Core HICP turned up (2.5% from 2.4%) = +1; PMI 53.1 = 3½-yr high. But German 2Y −19 bp as Oct hike priced out (Reuters poll: hold 29 Oct, hike Dec) = −1. A Dec hike signal from Lagarde lifts the 2Y and the total.
A7: GBP | B7: BoE | C7: 3.75 | D7: =IFERROR(1/(1/_xlfn.MINIFS(Events!$A$5:$A$304,Events!$C$5:$C$304,$A7,Events!$E$5:$E$304,"Central bank",Events!$A$5:$A$304,">="&TODAY())),"") -> 46331 | E7: 2.6 | F7: 2.6 | G7: 2 | H7: 4.9 | I7: 4.9 | J7: 52 | K7: 4.85 | L7: 4.92 | M7: =IF(COUNT(E7,F7,G7)<3,"",IF(AND(E7>G7,E7>=F7),1,IF(AND(E7<F7,E7<=G7+Guide!$B$20),-1,0))) -> 1 | N7: =IF(COUNT(H7,I7)<2,"",IF(H7-I7<=-Guide!$B$21,1,IF(H7-I7>=Guide!$B$21,-1,0))) -> 0 | O7: =IF(J7="","",IF(J7>=Guide!$B$22,1,IF(J7<=Guide!$B$23,-1,0))) -> 1 | P7: =IF(COUNT(K7,L7)<2,"",IF((K7-L7)*100>=Guide!$B$24,1,IF((K7-L7)*100<=-Guide!$B$24,-1,0))) -> 0 | Q7: =IF(COUNT(M7:P7)<4,"",SUM(M7:P7)) -> 2 | R7: =IF(Q7="","ENTER DATA",IF(Q7>=Guide!$B$25,"HAWKISH",IF(Q7<=-Guide!$B$25,"DOVISH","NEUTRAL"))) -> HAWKISH | S7: Nov 5 hike ~95% priced (OIS) yet 2Y flat (−5 bp) — already in the price, pricing score 0. Sep CPI (21 Oct) above 3.1% or Budget (28 Oct) gilt stress would move it.
A8: JPY | B8: BoJ | C8: 1.25 | D8: =IFERROR(1/(1/_xlfn.MINIFS(Events!$A$5:$A$304,Events!$C$5:$C$304,$A8,Events!$E$5:$E$304,"Central bank",Events!$A$5:$A$304,">="&TODAY())),"") -> 46325 | E8: 1.9 | F8: 1.8 | G8: 2 | H8: 2.5 | I8: 2.5 | J8: 52.3 | K8: 1.9 | L8: 1.84 | M8: =IF(COUNT(E8,F8,G8)<3,"",IF(AND(E8>G8,E8>=F8),1,IF(AND(E8<F8,E8<=G8+Guide!$B$20),-1,0))) -> 0 | N8: =IF(COUNT(H8,I8)<2,"",IF(H8-I8<=-Guide!$B$21,1,IF(H8-I8>=Guide!$B$21,-1,0))) -> 0 | O8: =IF(J8="","",IF(J8>=Guide!$B$22,1,IF(J8<=Guide!$B$23,-1,0))) -> 1 | P8: =IF(COUNT(K8,L8)<2,"",IF((K8-L8)*100>=Guide!$B$24,1,IF((K8-L8)*100<=-Guide!$B$24,-1,0))) -> 0 | Q8: =IF(COUNT(M8:P8)<4,"",SUM(M8:P8)) -> 1 | R8: =IF(Q8="","ENTER DATA",IF(Q8>=Guide!$B$25,"HAWKISH",IF(Q8<=-Guide!$B$25,"DOVISH","NEUTRAL"))) -> NEUTRAL | S8: 2Y only +7 bp (<15) as Oct hike odds fell to ~10% (Dec ~88%) → pricing 0, stance drops to NEUTRAL. Core-core 1.9% still under 2%. Sep CPI (~23 Oct) ≥2.0% or a hawkish Ueda flips it back.
A9: AUD | B9: RBA | D9: =IFERROR(1/(1/_xlfn.MINIFS(Events!$A$5:$A$304,Events!$C$5:$C$304,$A9,Events!$E$5:$E$304,"Central bank",Events!$A$5:$A$304,">="&TODAY())),"") | G9: 2.5 | M9: =IF(COUNT(E9,F9,G9)<3,"",IF(AND(E9>G9,E9>=F9),1,IF(AND(E9<F9,E9<=G9+Guide!$B$20),-1,0))) | N9: =IF(COUNT(H9,I9)<2,"",IF(H9-I9<=-Guide!$B$21,1,IF(H9-I9>=Guide!$B$21,-1,0))) | O9: =IF(J9="","",IF(J9>=Guide!$B$22,1,IF(J9<=Guide!$B$23,-1,0))) | P9: =IF(COUNT(K9,L9)<2,"",IF((K9-L9)*100>=Guide!$B$24,1,IF((K9-L9)*100<=-Guide!$B$24,-1,0))) | Q9: =IF(COUNT(M9:P9)<4,"",SUM(M9:P9)) | R9: =IF(Q9="","ENTER DATA",IF(Q9>=Guide!$B$25,"HAWKISH",IF(Q9<=-Guide!$B$25,"DOVISH","NEUTRAL"))) -> ENTER DATA
A10: NZD | B10: RBNZ | D10: =IFERROR(1/(1/_xlfn.MINIFS(Events!$A$5:$A$304,Events!$C$5:$C$304,$A10,Events!$E$5:$E$304,"Central bank",Events!$A$5:$A$304,">="&TODAY())),"") | G10: 2 | M10: =IF(COUNT(E10,F10,G10)<3,"",IF(AND(E10>G10,E10>=F10),1,IF(AND(E10<F10,E10<=G10+Guide!$B$20),-1,0))) | N10: =IF(COUNT(H10,I10)<2,"",IF(H10-I10<=-Guide!$B$21,1,IF(H10-I10>=Guide!$B$21,-1,0))) | O10: =IF(J10="","",IF(J10>=Guide!$B$22,1,IF(J10<=Guide!$B$23,-1,0))) | P10: =IF(COUNT(K10,L10)<2,"",IF((K10-L10)*100>=Guide!$B$24,1,IF((K10-L10)*100<=-Guide!$B$24,-1,0))) | Q10: =IF(COUNT(M10:P10)<4,"",SUM(M10:P10)) | R10: =IF(Q10="","ENTER DATA",IF(Q10>=Guide!$B$25,"HAWKISH",IF(Q10<=-Guide!$B$25,"DOVISH","NEUTRAL"))) -> ENTER DATA
A11: CAD | B11: BoC | D11: =IFERROR(1/(1/_xlfn.MINIFS(Events!$A$5:$A$304,Events!$C$5:$C$304,$A11,Events!$E$5:$E$304,"Central bank",Events!$A$5:$A$304,">="&TODAY())),"") | G11: 2 | M11: =IF(COUNT(E11,F11,G11)<3,"",IF(AND(E11>G11,E11>=F11),1,IF(AND(E11<F11,E11<=G11+Guide!$B$20),-1,0))) | N11: =IF(COUNT(H11,I11)<2,"",IF(H11-I11<=-Guide!$B$21,1,IF(H11-I11>=Guide!$B$21,-1,0))) | O11: =IF(J11="","",IF(J11>=Guide!$B$22,1,IF(J11<=Guide!$B$23,-1,0))) | P11: =IF(COUNT(K11,L11)<2,"",IF((K11-L11)*100>=Guide!$B$24,1,IF((K11-L11)*100<=-Guide!$B$24,-1,0))) | Q11: =IF(COUNT(M11:P11)<4,"",SUM(M11:P11)) | R11: =IF(Q11="","ENTER DATA",IF(Q11>=Guide!$B$25,"HAWKISH",IF(Q11<=-Guide!$B$25,"DOVISH","NEUTRAL"))) -> ENTER DATA
A12: CHF | B12: SNB | D12: =IFERROR(1/(1/_xlfn.MINIFS(Events!$A$5:$A$304,Events!$C$5:$C$304,$A12,Events!$E$5:$E$304,"Central bank",Events!$A$5:$A$304,">="&TODAY())),"") | G12: 1 | M12: =IF(COUNT(E12,F12,G12)<3,"",IF(AND(E12>G12,E12>=F12),1,IF(AND(E12<F12,E12<=G12+Guide!$B$20),-1,0))) | N12: =IF(COUNT(H12,I12)<2,"",IF(H12-I12<=-Guide!$B$21,1,IF(H12-I12>=Guide!$B$21,-1,0))) | O12: =IF(J12="","",IF(J12>=Guide!$B$22,1,IF(J12<=Guide!$B$23,-1,0))) | P12: =IF(COUNT(K12,L12)<2,"",IF((K12-L12)*100>=Guide!$B$24,1,IF((K12-L12)*100<=-Guide!$B$24,-1,0))) | Q12: =IF(COUNT(M12:P12)<4,"",SUM(M12:P12)) | R12: =IF(Q12="","ENTER DATA",IF(Q12>=Guide!$B$25,"HAWKISH",IF(Q12<=-Guide!$B$25,"DOVISH","NEUTRAL"))) -> ENTER DATA

Sheet Risk & Gold
A1: Risk Regime & Gold | F1: ← Guide
A2: LIVE DATA as of 15 Oct 2026 — VIX, S&P, DXY from TradingView; real yield from FRED. Re-check weekly.
A4: RISK REGIME (borrowed from the User’s investing Layer 3 VIX rules)
A5: VIX | B5: 17.53 | C5: VIX < calm level (Guide) and S&P above its 200-day = RISK-ON
A6: S&P 500 close | B6: 7718.94 | C6: VIX > stress level = RISK-OFF
A7: S&P 500 200-day average | B7: 7263.43 | C7: Anything in between = CAUTION
A8: REGIME | B8: =IF(COUNT(B5:B7)<3,"ENTER DATA",IF(B5>Guide!$B$29,"RISK-OFF",IF(OR(B5>=Guide!$B$28,B6<B7),"CAUTION","RISK-ON"))) -> RISK-ON | C8: RISK-OFF: no trades against JPY/safe havens · CAUTION: size down / A+ only · RISK-ON: normal
A11: GOLD DRIVERS
A12: Driver | B12: Now | C12: 1 month ago | D12: Change | E12: Score | F12: Notes
A13: US 10Y real yield (%) — FRED DFII10 | B13: 2.88 | C13: 2.62 | D13: =IF(COUNT(B13:C13)<2,"",(B13-C13)*100) -> 26 | E13: =IF(D13="","",IF(D13<=-Guide!$B$30,1,IF(D13>=Guide!$B$30,-1,0))) -> -1 | F13: Real yield up 26 bp in a month (2.62 → 2.88, 13 Oct) after the hot Sep CPI revived Fed hike bets — strong headwind for gold.
A14: Dollar index — ICE DXY (use the SAME series for both cells) | B14: 102.11 | C14: 99.48 | D14: =IF(COUNT(B14:C14)<2,"",(B14/C14-1)*100) -> 2.6437475 | E14: =IF(D14="","",IF(D14<=-Guide!$B$31,1,IF(D14>=Guide!$B$31,-1,0))) -> -1 | F14: DXY +2.64% on the month (99.48 → 102.11, TradingView TVC:DXY) — Fed repricing and a record EUR net short. Headwind.
A15: Risk regime | B15: =B8 -> RISK-ON | E15: =IF(B15="RISK-OFF",1,0) -> 0 | F15: Risk-off adds safe-haven demand
A16: Research (CB buying, geopolitics, ETF flows) | B16: 0 | E16: =B16 -> 0 | F16: Research score 0 kept (User's call). Claude draft 15 Oct: WGC — central banks +39t in Aug (China, Uzbekistan, Poland), ~170t YTD: floor intact. CFTC week to 6 Oct: managed-money gold net long −8% to a 3-month low (115k). ETF holdings at a 4-yr high. Net: still 0.
A17: GOLD TOTAL | E17: =IF(COUNT(E13:E16)<4,"",SUM(E13:E16)) -> -2
A18: GOLD BIAS | B18: =IF(E17="","ENTER DATA",IF(E17>=Guide!$B$32,"LONG",IF(E17<=-Guide!$B$32,"SHORT","FLAT"))) -> SHORT

Sheet Key Levels
A1: Key Levels — where big players have shown their hand | L1: ← Guide
A2: ⚠ Levels marked 'verify' come from memory or an older note — check them on the chart before relying on them.
A4: CURRENT PRICES (update weekly) | E4: HOW EACH TYPE BEHAVES
A5: Instrument | B5: Price | C5: Updated | E5: Type | F5: How it behaves
A6: USDJPY | B6: 157.97 | C6: 46310 | E6: Policy line | F6: A government/central bank acted here. Don't hold positions into it; they react to SPEED of the move, not just the number. Caps a trend, rarely reverses it.
A7: XAUUSD | B7: 4147.13 | C7: 46310 | E7: Options / GEX | F7: Big strikes or expiries. Pin price near expiry (positive gamma) or accelerate moves (negative gamma). Only valid until the expiry date.
A8: EURUSD | B8: 1.1211 | C8: 46310 | E8: Structural | F8: Prior-year/all-time highs & lows, round numbers. Stops cluster here → expect a sweep; trade the rejection, not the break.
A9: GBPUSD | B9: 1.3248 | C9: 46310 | E9: Session | F9: PDH/PDL, Asia/London range. Intraday only — refresh daily.
A10: NAS100 | B10: 29950.82 | C10: 46310
A12: Instrument | B12: Level | C12: Zone other edge | D12: Type | E12: Strength (1–3) | F12: What happened here | G12: Source | H12: Date set | I12: Last tested | J12: Reaction when tested | K12: Distance (%) | L12: Status
A13: USDJPY | B13: 164 | C13: 163 | D13: Policy line | E13: 3 | F13: Japan (joined by the US) bought yen after USD/JPY crossed 163 and neared 164 | G13: CNBC / Wikipedia, Aug 2026 | H13: 46234 | J13: Fell to ~155 within days | K13: =IF(OR(A13="",B13=""),"",IFERROR(IF(INDEX($B$6:$B$10,MATCH(A13,$A$6:$A$10,0))="","",(B13/INDEX($B$6:$B$10,MATCH(A13,$A$6:$A$10,0))-1)*100),"")) -> 3.8171805 | L13: =IF(K13="","",IF(ABS(K13)<=Guide!$B$33,"NEAR — watch",IF(K13>0,"above price","below price"))) -> above price
A14: USDJPY | B14: 161.95 | D14: Policy line | E14: 2 | F14: July 2024 high, intervention followed | G14: Claude from memory — verify | H14: 45484 | K14: =IF(OR(A14="",B14=""),"",IFERROR(IF(INDEX($B$6:$B$10,MATCH(A14,$A$6:$A$10,0))="","",(B14/INDEX($B$6:$B$10,MATCH(A14,$A$6:$A$10,0))-1)*100),"")) -> 2.5194657 | L14: =IF(K14="","",IF(ABS(K14)<=Guide!$B$33,"NEAR — watch",IF(K14>0,"above price","below price"))) -> above price
A15: USDJPY | B15: 160.2 | D15: Policy line | E15: 2 | F15: April 2024 high, intervention followed | G15: Claude from memory — verify | H15: 45411 | K15: =IF(OR(A15="",B15=""),"",IFERROR(IF(INDEX($B$6:$B$10,MATCH(A15,$A$6:$A$10,0))="","",(B15/INDEX($B$6:$B$10,MATCH(A15,$A$6:$A$10,0))-1)*100),"")) -> 1.4116604 | L15: =IF(K15="","",IF(ABS(K15)<=Guide!$B$33,"NEAR — watch",IF(K15>0,"above price","below price"))) -> above price
A16: USDJPY | B16: 160 | D16: Policy line | E16: 3 | F16: Widely cited political 'line in the sand'; MoF calls moves toward 160 disorderly | G16: OMFIF / CNBC, Aug 2026 | K16: =IF(OR(A16="",B16=""),"",IFERROR(IF(INDEX($B$6:$B$10,MATCH(A16,$A$6:$A$10,0))="","",(B16/INDEX($B$6:$B$10,MATCH(A16,$A$6:$A$10,0))-1)*100),"")) -> 1.2850541 | L16: =IF(K16="","",IF(ABS(K16)<=Guide!$B$33,"NEAR — watch",IF(K16>0,"above price","below price"))) -> above price
A17: USDJPY | B17: 155.3 | D17: Structural | E17: 2 | F17: Post-intervention low; retested early September | G17: CNBC, Sep 2026 | H17: 46237 | I17: 46268 | J17: Held (~155.28) | K17: =IF(OR(A17="",B17=""),"",IFERROR(IF(INDEX($B$6:$B$10,MATCH(A17,$A$6:$A$10,0))="","",(B17/INDEX($B$6:$B$10,MATCH(A17,$A$6:$A$10,0))-1)*100),"")) -> -1.6901943 | L17: =IF(K17="","",IF(ABS(K17)<=Guide!$B$33,"NEAR — watch",IF(K17>0,"above price","below price"))) -> below price
A18: USDJPY | B18: 151.95 | D18: Policy line | E18: 1 | F18: October 2022 intervention high | G18: Claude from memory — verify | H18: 44855 | K18: =IF(OR(A18="",B18=""),"",IFERROR(IF(INDEX($B$6:$B$10,MATCH(A18,$A$6:$A$10,0))="","",(B18/INDEX($B$6:$B$10,MATCH(A18,$A$6:$A$10,0))-1)*100),"")) -> -3.8108502 | L18: =IF(K18="","",IF(ABS(K18)<=Guide!$B$33,"NEAR — watch",IF(K18>0,"above price","below price"))) -> below price
A19: USDJPY | B19: 145.9 | D19: Policy line | E19: 1 | F19: September 2022 first intervention | G19: Claude from memory — verify | H19: 44826 | K19: =IF(OR(A19="",B19=""),"",IFERROR(IF(INDEX($B$6:$B$10,MATCH(A19,$A$6:$A$10,0))="","",(B19/INDEX($B$6:$B$10,MATCH(A19,$A$6:$A$10,0))-1)*100),"")) -> -7.6406913 | L19: =IF(K19="","",IF(ABS(K19)<=Guide!$B$33,"NEAR — watch",IF(K19>0,"above price","below price"))) -> below price
A20: XAUUSD | B20: 5602 | D20: Structural | E20: 3 | F20: All-time high | G20: User context doc (Jul 2026) — verify | H20: 46051 | K20: =IF(OR(A20="",B20=""),"",IFERROR(IF(INDEX($B$6:$B$10,MATCH(A20,$A$6:$A$10,0))="","",(B20/INDEX($B$6:$B$10,MATCH(A20,$A$6:$A$10,0))-1)*100),"")) -> 35.08137 | L20: =IF(K20="","",IF(ABS(K20)<=Guide!$B$33,"NEAR — watch",IF(K20>0,"above price","below price"))) -> above price
A21: XAUUSD | B21: 4563 | D21: Structural | E21: 2 | F21: End-of-August close after a 13% monthly rally — September has pulled back from here | G21: World Gold Council, Aug 2026 commentary | H21: 46265 | K21: =IF(OR(A21="",B21=""),"",IFERROR(IF(INDEX($B$6:$B$10,MATCH(A21,$A$6:$A$10,0))="","",(B21/INDEX($B$6:$B$10,MATCH(A21,$A$6:$A$10,0))-1)*100),"")) -> 10.027899 | L21: =IF(K21="","",IF(ABS(K21)<=Guide!$B$33,"NEAR — watch",IF(K21>0,"above price","below price"))) -> above price
A22: XAUUSD | B22: 4439.8 | D22: Structural | E22: 1 | F22: Weekly high, broke above 4,400 after the Fed hike | G22: Yahoo Finance, 18 Sep 2026 | H22: 46283 | K22: =IF(OR(A22="",B22=""),"",IFERROR(IF(INDEX($B$6:$B$10,MATCH(A22,$A$6:$A$10,0))="","",(B22/INDEX($B$6:$B$10,MATCH(A22,$A$6:$A$10,0))-1)*100),"")) -> 7.0571697 | L22: =IF(K22="","",IF(ABS(K22)<=Guide!$B$33,"NEAR — watch",IF(K22>0,"above price","below price"))) -> above price
A23: XAUUSD | B23: 4261 | D23: Structural | E23: 2 | F23: Support zone at the near six-week low on Fed day (16 Sep) | G23: FX Leaders / Trading Economics, Sep 2026 | H23: 46281 | I23: 46281 | J23: Held — rebounded ~2% next day | K23: =IF(OR(A23="",B23=""),"",IFERROR(IF(INDEX($B$6:$B$10,MATCH(A23,$A$6:$A$10,0))="","",(B23/INDEX($B$6:$B$10,MATCH(A23,$A$6:$A$10,0))-1)*100),"")) -> 2.7457543 | L23: =IF(K23="","",IF(ABS(K23)<=Guide!$B$33,"NEAR — watch",IF(K23>0,"above price","below price"))) -> above price
A24: XAUUSD | B24: 4000 | C24: 4065 | D24: Structural | E24: 2 | F24: Range floor attributed to central-bank buying (as of July) | G24: User context doc (Jul 2026) — re-verify, may be stale | K24: =IF(OR(A24="",B24=""),"",IFERROR(IF(INDEX($B$6:$B$10,MATCH(A24,$A$6:$A$10,0))="","",(B24/INDEX($B$6:$B$10,MATCH(A24,$A$6:$A$10,0))-1)*100),"")) -> -3.5477547 | L24: =IF(K24="","",IF(ABS(K24)<=Guide!$B$33,"NEAR — watch",IF(K24>0,"above price","below price"))) -> below price
K25: =IF(OR(A25="",B25=""),"",IFERROR(IF(INDEX($B$6:$B$10,MATCH(A25,$A$6:$A$10,0))="","",(B25/INDEX($B$6:$B$10,MATCH(A25,$A$6:$A$10,0))-1)*100),"")) | L25: =IF(K25="","",IF(ABS(K25)<=Guide!$B$33,"NEAR — watch",IF(K25>0,"above price","below price")))
K26: =IF(OR(A26="",B26=""),"",IFERROR(IF(INDEX($B$6:$B$10,MATCH(A26,$A$6:$A$10,0))="","",(B26/INDEX($B$6:$B$10,MATCH(A26,$A$6:$A$10,0))-1)*100),"")) | L26: =IF(K26="","",IF(ABS(K26)<=Guide!$B$33,"NEAR — watch",IF(K26>0,"above price","below price")))
K27: =IF(OR(A27="",B27=""),"",IFERROR(IF(INDEX($B$6:$B$10,MATCH(A27,$A$6:$A$10,0))="","",(B27/INDEX($B$6:$B$10,MATCH(A27,$A$6:$A$10,0))-1)*100),"")) | L27: =IF(K27="","",IF(ABS(K27)<=Guide!$B$33,"NEAR — watch",IF(K27>0,"above price","below price")))
K28: =IF(OR(A28="",B28=""),"",IFERROR(IF(INDEX($B$6:$B$10,MATCH(A28,$A$6:$A$10,0))="","",(B28/INDEX($B$6:$B$10,MATCH(A28,$A$6:$A$10,0))-1)*100),"")) | L28: =IF(K28="","",IF(ABS(K28)<=Guide!$B$33,"NEAR — watch",IF(K28>0,"above price","below price")))
K29: =IF(OR(A29="",B29=""),"",IFERROR(IF(INDEX($B$6:$B$10,MATCH(A29,$A$6:$A$10,0))="","",(B29/INDEX($B$6:$B$10,MATCH(A29,$A$6:$A$10,0))-1)*100),"")) | L29: =IF(K29="","",IF(ABS(K29)<=Guide!$B$33,"NEAR — watch",IF(K29>0,"above price","below price")))
K30: =IF(OR(A30="",B30=""),"",IFERROR(IF(INDEX($B$6:$B$10,MATCH(A30,$A$6:$A$10,0))="","",(B30/INDEX($B$6:$B$10,MATCH(A30,$A$6:$A$10,0))-1)*100),"")) | L30: =IF(K30="","",IF(ABS(K30)<=Guide!$B$33,"NEAR — watch",IF(K30>0,"above price","below price")))
K31: =IF(OR(A31="",B31=""),"",IFERROR(IF(INDEX($B$6:$B$10,MATCH(A31,$A$6:$A$10,0))="","",(B31/INDEX($B$6:$B$10,MATCH(A31,$A$6:$A$10,0))-1)*100),"")) | L31: =IF(K31="","",IF(ABS(K31)<=Guide!$B$33,"NEAR — watch",IF(K31>0,"above price","below price")))
K32: =IF(OR(A32="",B32=""),"",IFERROR(IF(INDEX($B$6:$B$10,MATCH(A32,$A$6:$A$10,0))="","",(B32/INDEX($B$6:$B$10,MATCH(A32,$A$6:$A$10,0))-1)*100),"")) | L32: =IF(K32="","",IF(ABS(K32)<=Guide!$B$33,"NEAR — watch",IF(K32>0,"above price","below price")))
K33: =IF(OR(A33="",B33=""),"",IFERROR(IF(INDEX($B$6:$B$10,MATCH(A33,$A$6:$A$10,0))="","",(B33/INDEX($B$6:$B$10,MATCH(A33,$A$6:$A$10,0))-1)*100),"")) | L33: =IF(K33="","",IF(ABS(K33)<=Guide!$B$33,"NEAR — watch",IF(K33>0,"above price","below price")))
K34: =IF(OR(A34="",B34=""),"",IFERROR(IF(INDEX($B$6:$B$10,MATCH(A34,$A$6:$A$10,0))="","",(B34/INDEX($B$6:$B$10,MATCH(A34,$A$6:$A$10,0))-1)*100),"")) | L34: =IF(K34="","",IF(ABS(K34)<=Guide!$B$33,"NEAR — watch",IF(K34>0,"above price","below price")))
K35: =IF(OR(A35="",B35=""),"",IFERROR(IF(INDEX($B$6:$B$10,MATCH(A35,$A$6:$A$10,0))="","",(B35/INDEX($B$6:$B$10,MATCH(A35,$A$6:$A$10,0))-1)*100),"")) | L35: =IF(K35="","",IF(ABS(K35)<=Guide!$B$33,"NEAR — watch",IF(K35>0,"above price","below price")))
K36: =IF(OR(A36="",B36=""),"",IFERROR(IF(INDEX($B$6:$B$10,MATCH(A36,$A$6:$A$10,0))="","",(B36/INDEX($B$6:$B$10,MATCH(A36,$A$6:$A$10,0))-1)*100),"")) | L36: =IF(K36="","",IF(ABS(K36)<=Guide!$B$33,"NEAR — watch",IF(K36>0,"above price","below price")))
... K52: =IF(OR(A52="",B52=""),"",IFERROR(IF(INDEX($B$6:$B$10,MATCH(A52,$A$6:$A$10,0))="","",(B52/INDEX($B$6:$B$10,MATCH(A52,$A$6:$A$10,0))-1)*100),"")) | L52: =IF(K52="","",IF(ABS(K52)<=Guide!$B$33,"NEAR — watch",IF(K52>0,"above price","below price")))

Sheet Journal
A1: Bias Journal | K1: ← Guide | M1: Trade Journal
A2: One row per bias deduced | M2: One row per trade. Blue = User types · grey = formula. Hover a header for what to write. Summary updates by itself.
M3: Account ($) | O3: Closed trades | P3: =COUNTIF($AH$5:$AH$205,"WIN")+COUNTIF($AH$5:$AH$205,"LOSS")+COUNTIF($AH$5:$AH$205,"BE") -> 0 | Q3: Win rate | R3: =IFERROR(COUNTIF($AH$5:$AH$205,"WIN")/(COUNTIF($AH$5:$AH$205,"WIN")+COUNTIF($AH$5:$AH$205,"LOSS")+COUNTIF($AH$5:$AH$205,"BE")),"") | S3: Avg R (expectancy) | T3: =IFERROR(AVERAGE($AG$5:$AG$205),"") | U3: Profit factor | V3: =IFERROR(SUMIF($AF$5:$AF$205,">0")/-SUMIF($AF$5:$AF$205,"<0"),"") | W3: Net P&L ($) | X3: =SUM($AF$5:$AF$205) -> 0 | Y3: Win rate WITH bias | Z3: =IFERROR(COUNTIFS($U$5:$U$205,"WITH",$AH$5:$AH$205,"WIN")/(COUNTIFS($U$5:$U$205,"WITH",$AH$5:$AH$205,"WIN")+COUNTIFS($U$5:$U$205,"WITH",$AH$5:$AH$205,"LOSS")+COUNTIFS($U$5:$U$205,"WITH",$AH$5:$AH$205,"BE")),"") | AA3: Win rate AGAINST / no bias | AB3: =IFERROR((COUNTIFS($U$5:$U$205,"AGAINST",$AH$5:$AH$205,"WIN")+COUNTIFS($U$5:$U$205,"NO PERMISSION",$AH$5:$AH$205,"WIN"))/(COUNTIFS($U$5:$U$205,"<>WITH",$U$5:$U$205,"?*",$AH$5:$AH$205,"WIN")+COUNTIFS($U$5:$U$205,"<>WITH",$U$5:$U$205,"?*",$AH$5:$AH$205,"LOSS")+COUNTIFS($U$5:$U$205,"<>WITH",$U$5:$U$205,"?*",$AH$5:$AH$205,"BE")),"") | AC3: Plan followed | AD3: =IFERROR(COUNTIF($AJ$5:$AJ$205,"Yes")/COUNTA($AJ$5:$AJ$205),"")
A4: Date | B4: Instrument | C4: Bias | D4: Score | E4: Risk regime | F4: Key driver | G4: Next catalyst | H4: Invalidation | I4: Outcome after 1 week | J4: Was the bias right? | K4: Lesson | M4: Trade # | N4: Date opened | O4: Instrument | P4: Direction | Q4: Setup / strategy | R4: Timeframe | S4: Session | T4: Macro bias at entry | U4: With bias? | V4: Entry price | W4: Stop loss | X4: Take profit | Y4: Size (lots / units) | Z4: Risk ($) | AA4: Risk (% acct) | AB4: Planned R:R | AC4: Date closed | AD4: Exit price | AE4: Exit reason | AF4: P&L ($) | AG4: R multiple | AH4: Result | AI4: Days held | AJ4: Followed plan? | AK4: Emotion | AL4: Setup grade | AM4: Mistakes | AN4: Lesson / notes | AO4: Screenshot
A5: 46284 | B5: XAUUSD | C5: FLAT | D5: 0 | E5: RISK-ON | F5: Tailwinds (CB buying, ETF inflows, Gulf risk) cancelled by real yields at 18-yr high (first Fed hike in 3 yrs) | G5: Next Fed meeting / US CPI | H5: Long if real yields −15 bp or DXY −1% | U5: =IF(OR(P5="",T5=""),"",IF(OR(AND(P5="Long",T5="LONG"),AND(P5="Short",T5="SHORT")),"WITH",IF(OR(T5="LONG",T5="SHORT"),"AGAINST","NO PERMISSION"))) | AA5: =IF(OR(Z5="",$N$3=""),"",Z5/$N$3) | AB5: =IF(COUNT(V5,W5,X5)<3,"",IFERROR(ABS(X5-V5)/ABS(V5-W5),"")) | AG5: =IF(OR(AF5="",Z5=""),"",IFERROR(AF5/Z5,"")) | AH5: =IF(N5="","",IF(AF5="","OPEN",IF(AF5>0,"WIN",IF(AF5<0,"LOSS","BE")))) | AI5: =IF(OR(N5="",AC5=""),"",AC5-N5)
A6: 46287 | B6: TTWO | C6: SHORT | E6: RISK-ON | F6: GTA 6 and strong defended levels around 187.6. wait until end october before release to catch move | G6: release 19 November 2026 | H6: Short for medium term for now and long if 206 level proves strong. Wait for potential retracement into upside then look for lon | I6: Entered position on 12th of October | J6: Yes | K6: The price has been rangy since September and only recently on the 26th of October broke out of the range. On that move out of the range I entered for a long after what I thought was a sharp retracement. When looking at the daily, we are still in a bearish trend, so I should have waited for more confirmation on the daily trend, although there was a fractal break of structure. Follow the confluences for all trades! | U6: =IF(OR(P6="",T6=""),"",IF(OR(AND(P6="Long",T6="LONG"),AND(P6="Short",T6="SHORT")),"WITH",IF(OR(T6="LONG",T6="SHORT"),"AGAINST","NO PERMISSION"))) | AA6: =IF(OR(Z6="",$N$3=""),"",Z6/$N$3) | AB6: =IF(COUNT(V6,W6,X6)<3,"",IFERROR(ABS(X6-V6)/ABS(V6-W6),"")) | AG6: =IF(OR(AF6="",Z6=""),"",IFERROR(AF6/Z6,"")) | AH6: =IF(N6="","",IF(AF6="","OPEN",IF(AF6>0,"WIN",IF(AF6<0,"LOSS","BE")))) | AI6: =IF(OR(N6="",AC6=""),"",AC6-N6)
U7: =IF(OR(P7="",T7=""),"",IF(OR(AND(P7="Long",T7="LONG"),AND(P7="Short",T7="SHORT")),"WITH",IF(OR(T7="LONG",T7="SHORT"),"AGAINST","NO PERMISSION"))) | AA7: =IF(OR(Z7="",$N$3=""),"",Z7/$N$3) | AB7: =IF(COUNT(V7,W7,X7)<3,"",IFERROR(ABS(X7-V7)/ABS(V7-W7),"")) | AG7: =IF(OR(AF7="",Z7=""),"",IFERROR(AF7/Z7,"")) | AH7: =IF(N7="","",IF(AF7="","OPEN",IF(AF7>0,"WIN",IF(AF7<0,"LOSS","BE")))) | AI7: =IF(OR(N7="",AC7=""),"",AC7-N7)
U8: =IF(OR(P8="",T8=""),"",IF(OR(AND(P8="Long",T8="LONG"),AND(P8="Short",T8="SHORT")),"WITH",IF(OR(T8="LONG",T8="SHORT"),"AGAINST","NO PERMISSION"))) | AA8: =IF(OR(Z8="",$N$3=""),"",Z8/$N$3) | AB8: =IF(COUNT(V8,W8,X8)<3,"",IFERROR(ABS(X8-V8)/ABS(V8-W8),"")) | AG8: =IF(OR(AF8="",Z8=""),"",IFERROR(AF8/Z8,"")) | AH8: =IF(N8="","",IF(AF8="","OPEN",IF(AF8>0,"WIN",IF(AF8<0,"LOSS","BE")))) | AI8: =IF(OR(N8="",AC8=""),"",AC8-N8)
U9: =IF(OR(P9="",T9=""),"",IF(OR(AND(P9="Long",T9="LONG"),AND(P9="Short",T9="SHORT")),"WITH",IF(OR(T9="LONG",T9="SHORT"),"AGAINST","NO PERMISSION"))) | AA9: =IF(OR(Z9="",$N$3=""),"",Z9/$N$3) | AB9: =IF(COUNT(V9,W9,X9)<3,"",IFERROR(ABS(X9-V9)/ABS(V9-W9),"")) | AG9: =IF(OR(AF9="",Z9=""),"",IFERROR(AF9/Z9,"")) | AH9: =IF(N9="","",IF(AF9="","OPEN",IF(AF9>0,"WIN",IF(AF9<0,"LOSS","BE")))) | AI9: =IF(OR(N9="",AC9=""),"",AC9-N9)
U10: =IF(OR(P10="",T10=""),"",IF(OR(AND(P10="Long",T10="LONG"),AND(P10="Short",T10="SHORT")),"WITH",IF(OR(T10="LONG",T10="SHORT"),"AGAINST","NO PERMISSION"))) | AA10: =IF(OR(Z10="",$N$3=""),"",Z10/$N$3) | AB10: =IF(COUNT(V10,W10,X10)<3,"",IFERROR(ABS(X10-V10)/ABS(V10-W10),"")) | AG10: =IF(OR(AF10="",Z10=""),"",IFERROR(AF10/Z10,"")) | AH10: =IF(N10="","",IF(AF10="","OPEN",IF(AF10>0,"WIN",IF(AF10<0,"LOSS","BE")))) | AI10: =IF(OR(N10="",AC10=""),"",AC10-N10)
U11: =IF(OR(P11="",T11=""),"",IF(OR(AND(P11="Long",T11="LONG"),AND(P11="Short",T11="SHORT")),"WITH",IF(OR(T11="LONG",T11="SHORT"),"AGAINST","NO PERMISSION"))) | AA11: =IF(OR(Z11="",$N$3=""),"",Z11/$N$3) | AB11: =IF(COUNT(V11,W11,X11)<3,"",IFERROR(ABS(X11-V11)/ABS(V11-W11),"")) | AG11: =IF(OR(AF11="",Z11=""),"",IFERROR(AF11/Z11,"")) | AH11: =IF(N11="","",IF(AF11="","OPEN",IF(AF11>0,"WIN",IF(AF11<0,"LOSS","BE")))) | AI11: =IF(OR(N11="",AC11=""),"",AC11-N11)
U12: =IF(OR(P12="",T12=""),"",IF(OR(AND(P12="Long",T12="LONG"),AND(P12="Short",T12="SHORT")),"WITH",IF(OR(T12="LONG",T12="SHORT"),"AGAINST","NO PERMISSION"))) | AA12: =IF(OR(Z12="",$N$3=""),"",Z12/$N$3) | AB12: =IF(COUNT(V12,W12,X12)<3,"",IFERROR(ABS(X12-V12)/ABS(V12-W12),"")) | AG12: =IF(OR(AF12="",Z12=""),"",IFERROR(AF12/Z12,"")) | AH12: =IF(N12="","",IF(AF12="","OPEN",IF(AF12>0,"WIN",IF(AF12<0,"LOSS","BE")))) | AI12: =IF(OR(N12="",AC12=""),"",AC12-N12)
U13: =IF(OR(P13="",T13=""),"",IF(OR(AND(P13="Long",T13="LONG"),AND(P13="Short",T13="SHORT")),"WITH",IF(OR(T13="LONG",T13="SHORT"),"AGAINST","NO PERMISSION"))) | AA13: =IF(OR(Z13="",$N$3=""),"",Z13/$N$3) | AB13: =IF(COUNT(V13,W13,X13)<3,"",IFERROR(ABS(X13-V13)/ABS(V13-W13),"")) | AG13: =IF(OR(AF13="",Z13=""),"",IFERROR(AF13/Z13,"")) | AH13: =IF(N13="","",IF(AF13="","OPEN",IF(AF13>0,"WIN",IF(AF13<0,"LOSS","BE")))) | AI13: =IF(OR(N13="",AC13=""),"",AC13-N13)
U14: =IF(OR(P14="",T14=""),"",IF(OR(AND(P14="Long",T14="LONG"),AND(P14="Short",T14="SHORT")),"WITH",IF(OR(T14="LONG",T14="SHORT"),"AGAINST","NO PERMISSION"))) | AA14: =IF(OR(Z14="",$N$3=""),"",Z14/$N$3) | AB14: =IF(COUNT(V14,W14,X14)<3,"",IFERROR(ABS(X14-V14)/ABS(V14-W14),"")) | AG14: =IF(OR(AF14="",Z14=""),"",IFERROR(AF14/Z14,"")) | AH14: =IF(N14="","",IF(AF14="","OPEN",IF(AF14>0,"WIN",IF(AF14<0,"LOSS","BE")))) | AI14: =IF(OR(N14="",AC14=""),"",AC14-N14)
U15: =IF(OR(P15="",T15=""),"",IF(OR(AND(P15="Long",T15="LONG"),AND(P15="Short",T15="SHORT")),"WITH",IF(OR(T15="LONG",T15="SHORT"),"AGAINST","NO PERMISSION"))) | AA15: =IF(OR(Z15="",$N$3=""),"",Z15/$N$3) | AB15: =IF(COUNT(V15,W15,X15)<3,"",IFERROR(ABS(X15-V15)/ABS(V15-W15),"")) | AG15: =IF(OR(AF15="",Z15=""),"",IFERROR(AF15/Z15,"")) | AH15: =IF(N15="","",IF(AF15="","OPEN",IF(AF15>0,"WIN",IF(AF15<0,"LOSS","BE")))) | AI15: =IF(OR(N15="",AC15=""),"",AC15-N15)
U16: =IF(OR(P16="",T16=""),"",IF(OR(AND(P16="Long",T16="LONG"),AND(P16="Short",T16="SHORT")),"WITH",IF(OR(T16="LONG",T16="SHORT"),"AGAINST","NO PERMISSION"))) | AA16: =IF(OR(Z16="",$N$3=""),"",Z16/$N$3) | AB16: =IF(COUNT(V16,W16,X16)<3,"",IFERROR(ABS(X16-V16)/ABS(V16-W16),"")) | AG16: =IF(OR(AF16="",Z16=""),"",IFERROR(AF16/Z16,"")) | AH16: =IF(N16="","",IF(AF16="","OPEN",IF(AF16>0,"WIN",IF(AF16<0,"LOSS","BE")))) | AI16: =IF(OR(N16="",AC16=""),"",AC16-N16)
U17: =IF(OR(P17="",T17=""),"",IF(OR(AND(P17="Long",T17="LONG"),AND(P17="Short",T17="SHORT")),"WITH",IF(OR(T17="LONG",T17="SHORT"),"AGAINST","NO PERMISSION"))) | AA17: =IF(OR(Z17="",$N$3=""),"",Z17/$N$3) | AB17: =IF(COUNT(V17,W17,X17)<3,"",IFERROR(ABS(X17-V17)/ABS(V17-W17),"")) | AG17: =IF(OR(AF17="",Z17=""),"",IFERROR(AF17/Z17,"")) | AH17: =IF(N17="","",IF(AF17="","OPEN",IF(AF17>0,"WIN",IF(AF17<0,"LOSS","BE")))) | AI17: =IF(OR(N17="",AC17=""),"",AC17-N17)
U18: =IF(OR(P18="",T18=""),"",IF(OR(AND(P18="Long",T18="LONG"),AND(P18="Short",T18="SHORT")),"WITH",IF(OR(T18="LONG",T18="SHORT"),"AGAINST","NO PERMISSION"))) | AA18: =IF(OR(Z18="",$N$3=""),"",Z18/$N$3) | AB18: =IF(COUNT(V18,W18,X18)<3,"",IFERROR(ABS(X18-V18)/ABS(V18-W18),"")) | AG18: =IF(OR(AF18="",Z18=""),"",IFERROR(AF18/Z18,"")) | AH18: =IF(N18="","",IF(AF18="","OPEN",IF(AF18>0,"WIN",IF(AF18<0,"LOSS","BE")))) | AI18: =IF(OR(N18="",AC18=""),"",AC18-N18)
... U205: =IF(OR(P205="",T205=""),"",IF(OR(AND(P205="Long",T205="LONG"),AND(P205="Short",T205="SHORT")),"WITH",IF(OR(T205="LONG",T205="SHORT"),"AGAINST","NO PERMISSION"))) | AA205: =IF(OR(Z205="",$N$3=""),"",Z205/$N$3) | AB205: =IF(COUNT(V205,W205,X205)<3,"",IFERROR(ABS(X205-V205)/ABS(V205-W205),"")) | AG205: =IF(OR(AF205="",Z205=""),"",IFERROR(AF205/Z205,"")) | AH205: =IF(N205="","",IF(AF205="","OPEN",IF(AF205>0,"WIN",IF(AF205<0,"LOSS","BE")))) | AI205: =IF(OR(N205="",AC205=""),"",AC205-N205)

Sheet Hub
A1: Hub — where to go for everything that doesn't live in this workbook | H1: ← Guide
A2: Click a link, read, then write ONE line back here. The detail stays at the source; only the conclusion comes back. Claude refreshes sections A–C with prompts P2, P4 and P6.
A4: COUNTRY HUB
A5: Currency | B5: Situation in one line | C5: Main theme / risk | D5: Last checked | E5: Status | F5: Central bank | G5: Data + calendar | H5: News
A6: USD | B6: Fed at 3.75–4.00%; Sep CPI 3.7% (core 2.6%) beat forecasts, PMI 58.4; hike odds ~30–50% for 28 Oct and ~90% by December. | C6: Hot inflation vs midterm timing — does Warsh hike on 28 Oct or wait for December? | D6: 46310 | E6: =IF(D6="","NOT CHECKED",IF(TODAY()-D6>14,"STALE","OK")) -> OK | F6: Fed ↗ | G6: Trading Econ ↗ | H6: News ↗
A7: EUR | B7: ECB at 2.50%; core HICP up to 2.5%, headline 3.8%, PMI 53.1; markets and economists expect a hold on 29 Oct, hike in December. | C7: Hawkish talk (Wunsch) but October hike priced out; EUR speculative short at a 2020 high = squeeze risk. | D7: 46310 | E7: =IF(D7="","NOT CHECKED",IF(TODAY()-D7>14,"STALE","OK")) -> OK | F7: ECB ↗ | G7: Trading Econ ↗ | H7: News ↗
A8: GBP | B8: BoE at 3.75%; Nov 5 hike ~95% priced; headline CPI 3.1%, PMI 52.0, GDP slowing to 0.5% q/q. | C8: Budget (28 Oct) and gilt stress vs a near-certain November hike. | D8: 46310 | E8: =IF(D8="","NOT CHECKED",IF(TODAY()-D8>14,"STALE","OK")) -> OK | F8: BoE ↗ | G8: Trading Econ ↗ | H8: News ↗
A9: JPY | B9: BoJ at 1.25%; October hike odds ~10% (December ~88%); USD/JPY 157.9 just below the 160 line; no new intervention since August. | C9: Pause in October keeps the rate gap wide; 160–164 intervention zone caps the upside. | D9: 46310 | E9: =IF(D9="","NOT CHECKED",IF(TODAY()-D9>14,"STALE","OK")) -> OK | F9: BoJ ↗ | G9: Trading Econ ↗ | H9: News ↗
A10: AUD | E10: =IF(D10="","NOT CHECKED",IF(TODAY()-D10>14,"STALE","OK")) -> NOT CHECKED | F10: RBA ↗ | G10: Trading Econ ↗ | H10: News ↗
A11: NZD | E11: =IF(D11="","NOT CHECKED",IF(TODAY()-D11>14,"STALE","OK")) -> NOT CHECKED | F11: RBNZ ↗ | G11: Trading Econ ↗ | H11: News ↗
A12: CAD | E12: =IF(D12="","NOT CHECKED",IF(TODAY()-D12>14,"STALE","OK")) -> NOT CHECKED | F12: BoC ↗ | G12: Trading Econ ↗ | H12: News ↗
A13: CHF | E13: =IF(D13="","NOT CHECKED",IF(TODAY()-D13>14,"STALE","OK")) -> NOT CHECKED | F13: SNB ↗ | G13: Trading Econ ↗ | H13: News ↗
A14: Only fill the currencies the User trades. STALE = more than 14 days since the last read-up.
A16: WHO HOLDS WHAT (governments, central banks and big positioning)
A17: What | B17: Why it matters | C17: What changed? (one line) | D17: Last checked | E17: Updates | F17: Source
A18: Foreign holders of US Treasuries (Japan, China, UK…) | B18: Big holders selling = pressure on US yields and the dollar. Japan selling can signal FX defence. | C18: July TIC: foreigners net SOLD $27.9bn of long-term US securities. | D18: 46286 | E18: Monthly | F18: US Treasury TIC ↗
A19: Central-bank gold reserves / buying | B19: The main support under gold. Slower buying weakens the floor in Key Levels. | C19: WGC: central banks +39t in August (China, Uzbekistan, Poland 8t); ~170t YTD — buying picked up again. | D19: 46310 | E19: Monthly | F19: World Gold Council ↗
A20: Reserve currency shares (USD, EUR, JPY…) | B20: Slow structural trend — is the world diversifying away from the dollar? | C20: COFER Q1 2026: USD share up to 57.1% (from 56.4%), EUR 20.0% — no move away from the dollar. | D20: 46286 | E20: Quarterly | F20: IMF COFER ↗
A21: Japan FX intervention amounts | B21: Confirms when and how much Japan acted → update USDJPY policy lines. | C21: MoF: no new intervention since the record ¥15.4tn (30 Jul–26 Aug). FX reserves −$29.1bn in Sep to $1.178tn. | D21: 46310 | E21: Monthly | F21: Japan MoF ↗
A22: Speculator positioning (CFTC COT) | B22: Not governments, but shows crowded trades that can snap back. | C22: Week to 6 Oct: yen net long +62k (up 6.9k); EUR net short ~99k = 2020 high; gold managed-money net long −8% to 115k (3-month low). | D22: 46310 | E22: Weekly (Fri) | F22: CFTC ↗
A24: WHERE IS MONEY MOVING? (risk-on vs risk-off barometer (weekly))
A25: Gauge | B25: Reads RISK-ON when… | C25: Read | D25: Where to check
A26: AUD/JPY | B26: Rising — money leaving the safe-haven yen for higher-yielding AUD | C26: NEUTRAL | D26: TradingView ↗
A27: Copper ÷ gold | B27: Rising — growth metal beating the safe-haven metal. In TradingView type: HG1!/GC1! | C27: RISK-ON | D27: TradingView ↗
A28: US high-yield credit spread | B28: Falling — lenders relaxed about risky borrowers (FRED BAMLH0A0HYM2) | C28: RISK-OFF | D28: FRED ↗
A29: Discretionary ÷ staples stocks | B29: Rising — investors buying 'wants' over 'needs'. In TradingView type: XLY/XLP | C29: RISK-OFF | D29: TradingView ↗
A30: Asset-class scoreboard | B30: Stocks & commodities lead, bonds/gold/yen lag. Shows the week's leaders at a glance. | C30: RISK-ON | D30: Finviz futures ↗
A31: Sentiment | B31: Greed. (Extreme greed = crowded, watch for reversal.) | C31: NEUTRAL | D31: CNN Fear & Greed ↗
A33: Barometer result | B33: =COUNTIF(C26:C31,"RISK-ON")&" risk-on · "&COUNTIF(C26:C31,"RISK-OFF")&" risk-off · "&COUNTIF(C26:C31,"NEUTRAL")&" neutral" -> 2 risk-on · 2 risk-off · 2 neutral | C33: =IF(COUNTA(C26:C31)<6,"ENTER READS",IF(COUNTIF(C26:C31,"RISK-ON")-COUNTIF(C26:C31,"RISK-OFF")>=2,"RISK-ON",IF(COUNTIF(C26:C31,"RISK-OFF")-COUNTIF(C26:C31,"RISK-ON")>=2,"RISK-OFF","MIXED"))) -> MIXED
A34: VIX regime (Risk & Gold) | C34: ='Risk & Gold'!B8 -> RISK-ON
A35: Do they agree? | C35: =IF(OR(C33="MIXED",C34="CAUTION"),"PARTLY — size down",IF(C33=C34,"YES","NO — trust neither, size down")) -> PARTLY — size down
A37: D. PROMPTS
A38: All update prompts now live on the Prompts sheet ↗ — P4 Country deep-dive, P2 Markets, P3 Scorecard stats, P5 Key levels, P6 Who holds what, P1 Events, P7 AI bias, P0 Full cycle.

Sheet Sources
A1: Sources — where every input comes from | G1: ← Guide
A2: One fixed source per input, used every time, so week-on-week changes are like for like. “Filled by” says who updates each input: Claude (blue) or User (orange).
A4: Sheet | B4: Cells | C4: Input | D4: Filled by | E4: Fixed source | F4: Series / rule | G4: How often
A5: Scorecard | B5: C5:C12 | C5: Policy rate (%) | D5: Claude | E5: Central bank official statement | F5: Fed: upper bound of target range · ECB: deposit facility rate · BoE: Bank Rate · BoJ: short-term policy rate · RBA cash rate · RBNZ OCR · BoC overnight rate · SNB policy rate | G5: After each meeting
A6: Scorecard | B6: D5:D12 | C6: Next meeting | D6: Formula | E6: Events sheet | F6: Next row with Type "Central bank" for that currency | G6: Automatic
A7: Scorecard | B7: E5:F12 | C7: Core CPI YoY now / 3M ago (%) | D7: Claude | E7: US: BLS via FRED · EUR: Eurostat · GBP: ONS · JPY: Statistics Bureau of Japan | F7: US: CPILFESL % YoY · EUR: HICP excl. energy, food, alcohol & tobacco (prc_hicp_minr) · GBP: CPI excl. energy, food, alcohol & tobacco (DKO8) · JPY: CPI excl. fresh food & energy ("core-core"). 3M ago = the month three months before the latest, as currently published | G7: Monthly, on release
A8: Scorecard | B8: G5:G12 | C8: Inflation target (%) | D8: Claude | E8: Central bank mandate | F8: Band midpoint for RBA / RBNZ / SNB | G8: Check yearly
A9: Scorecard | B9: H5:I12 | C9: Unemployment now / 3M ago (%) | D9: Claude | E9: US: BLS via FRED · EUR: Eurostat · GBP: ONS · JPY: Statistics Bureau | F9: US: UNRATE · EUR: une_rt_m euro area, SA · GBP: ILO rate 3-month avg (MGSX) · JPY: Labour Force Survey, SA | G9: Monthly, on release
A10: Scorecard | B10: J5:J12 | C10: Composite PMI | D10: Claude | E10: S&P Global (US, UK, Japan) · HCOB (Eurozone) | F10: Composite Output Index, FINAL print (flash is ignored) | G10: Monthly, ~3rd working day
A11: Scorecard | B11: K5:L12 | C11: 2Y yield now / 1M ago (%) | D11: Claude | E11: TradingView | F11: TVC:US02Y · TVC:DE02Y (German 2Y) · TVC:GB02Y · TVC:JP02Y. 1M ago = TradingView close ÷ (1 + Perf.1M) — npm run tradingview | G11: Weekly
A12: Scorecard | B12: S5:S12 | C12: Notes — what would change it? | D12: Claude | E12: From the numbers + latest central-bank statement | F12: One line: which print would flip a score | G12: Weekly
A13: Risk & Gold | B13: B5 | C13: VIX | D13: Claude | E13: TradingView | F13: TVC:VIX, latest | G13: Weekly
A14: Risk & Gold | B14: B6:B7 | C14: S&P 500 close / 200-day average | D14: Claude | E14: TradingView | F14: SP:SPX latest close; 200-day = SMA200 (daily) on TradingView | G14: Weekly
A15: Risk & Gold | B15: B13:C13 | C15: US 10Y real yield now / 1M ago | D15: Claude | E15: FRED | F15: DFII10 | G15: Weekly
... A38: Update Log | B38: H5:H204 | C38: User check | D38: User | E38: — | F38: OK / Question / Revert after reading the run | G38: After each run

Sheet Update Log
A1: Update Log — every run, newest at the top | H1: ← Guide
A2: Claude adds one row per run (scheduled or on request). The User can add a row after editing inputs by hand.
A4: Run (Amsterdam) | B4: Prompt | C4: Run by | D4: Sheets touched | E4: Key changes (old → new) | F4: Stance / bias flips | G4: NOT UPDATED / flags | H4: User check
A5: 46310.604 | B5: P2 (source switch) | C5: Claude (on request) | D5: Scorecard, Risk & Gold, Key Levels, Hub, Sources, Prompts, Guide | E5: Market source switched IBKR / Investing.com / FRED / Bundesbank / MoF → TradingView (scanner, npm run tradingview). US 2Y 4.79 → 4.75; US 2Y 1M ago 4.67 → 4.65; EUR 2Y 3.07 → 3.05; GBP 2Y 1M ago 4.9 → 4.92; JPY 2Y 1.93 → 1.9; JPY 2Y 1M ago 1.86 → 1.84; VIX 15.27 → 17.53; DXY 102.55 → 102.11; DXY 1M ago 99.61 → 99.48; USDJPY price 157.91 → 157.97; XAUUSD price 4150.8 → 4147.13; EURUSD price 1.1215 → 1.1211; GBPUSD price 1.3256 → 1.3248; NAS100 price None → 29950.82; Hub AUD/JPY RISK-OFF → NEUTRAL | F5: No score / stance / FINAL BIAS flips: pricing scores unchanged (US +10 bp, EUR −21 bp, GBP −8 bp, JPY +6 bp). Regime still RISK-ON but VIX 17.5 is just under the 18 calm level. Barometer AUD/JPY RISK-OFF → NEUTRAL. | G5: Kept on FRED: US 10Y real yield (DFII10) and HY spread — no TradingView equivalent. Macro stats stay on official sources (TradingView ECONOMICS definitions differ). NAS100 now filled. CNN Fear & Greed still blocked.
A6: 46310.583 | B6: P0 (on request) | C6: Claude (on request) | D6: Scorecard, Risk & Gold, Key Levels, Hub, Events, Bias Builder, Journal (new trade journal), Guide, Sources | E6: US core CPI 2.45 → 2.57; US core CPI 3M ago 2.82 → 2.57; US unemp 4.1 → 4.2; US unemp 3M ago 4.3 → 4.2; US PMI 56 → 58.4; US 2Y 4.67 → 4.79; US 2Y 1M ago 4.19 → 4.67; EUR core HICP 2.4 → 2.5; EUR core 3M ago 2.6 → 2.4; EUR PMI 52 → 53.1; EUR 2Y 3.21 → 3.07; EUR 2Y 1M ago 2.8 → 3.26; UK PMI 52.5 → 52.0; UK 2Y 4.84 → 4.85; UK 2Y 1M ago 4.37 → 4.9; JP unemp 2.4 → 2.5; JP PMI 53.5 → 52.3; JP 2Y 1.87 → 1.93; JP 2Y 1M ago 1.7 → 1.86; VIX 14.81 → 15.27; S&P 500 7650.5 → 7718.94; S&P 200d 7183.05 → 7263.43; US 10Y real 2.61 → 2.88; US 10Y real 1M ago 2.44 → 2.62; DXY 100.32 → 102.55; DXY 1M ago 98.8 → 99.61; USDJPY price 157.41 → 157.91; XAUUSD price 4344.99 → 4150.8; EURUSD price 1.147 → 1.1215; GBPUSD price 1.3371 → 1.3256; US headline CPI 3.35 → 3.72; US headline CPI 3M ago 4.17 → 3.46; US wages 3.1 → 3.02; US wages 3M ago 3.3 → 3.38; EUR headline HICP 3.2 → 3.8; EUR headline 3M ago 3.2 → 2.8; UK GDP q/q 0.4 → 0.5; AI bias: EURUSD SHORT (kept), GBPUSD FLAT, USDJPY LONG (Low), XAUUSD FLAT → SHORT; AI reads: GBP confidence Medium → High, gold NEUTRAL → DOVISH; Hub C27 RISK-OFF → RISK-ON; Hub C28 NEUTRAL → RISK-OFF; Hub C29 NEUTRAL → RISK-OFF; Hub C30 RISK-OFF → RISK-ON; Events: +24 Forex Factory rows (12–17 Oct), generic 'CPI (Sep)' replaced by detail rows, Actuals filled for US CPI Sep and NFP Sep | F6: Scorecard: inflation score USD −1→+1, EUR −1→+1; pricing USD/GBP/JPY +1→0, EUR +1→−1; labour USD +1→0. Stances: JPY HAWKISH→NEUTRAL; USD/GBP HAWKISH, EUR NEUTRAL unchanged. FINAL BIAS unchanged: EURUSD/GBPUSD/USDJPY FLAT, gold SHORT. Risk regime RISK-ON (VIX 15.3, S&P above 200d). AI gold bias FLAT→SHORT. | G6: NOT UPDATED: CNN Fear & Greed (site blocked, Hub C31 kept); NAS100 price (no IBKR permission); TIC Aug and IMF COFER (no new release found); UK CPI/labour, Japan CPI, GDP (no new release since last run); Events beyond this week (FF next-week feed 404) and 4-month CB calendar not re-verified; UK Budget date 28 Oct not re-confirmed. Bias sheet N5/N8 last reviewed 19 Sep = EXPIRED — User review needed. Formulas not recalculated by LibreOffice (not installed) — recalculated by Excel on open.
A7: 46286.802 | B7: build | C7: Claude (on request) | D7: Scorecard, Risk & Gold, Key Levels, Hub, Events, Calendar, Bias Builder | E7: First live fill (21 Sep): Scorecard USD/EUR/GBP/JPY; VIX 14.81, S&P 7,650.5 vs 200d 7,183; real yield 2.44 → 2.61; DXY 98.80 → 100.32; Events Sep–Dec; Bias Builder evidence + AI bias. | F7: Stances: USD, GBP, JPY HAWKISH, EUR NEUTRAL. EURUSD / GBPUSD / USDJPY FLAT; gold SHORT (model). | G7: Hub sentiment (CNN F&G blocked); BoJ October pricing not verified; AUD/NZD/CAD/CHF empty; NAS100 price.

Sheet Prompts
A1: Prompts — every update cycle, ready to copy or schedule | E1: ← Guide
A2: P0 is the one to schedule (every 2 days). P1–P9 run on their own when the User wants one part refreshed. Replace [CURRENCY] / [EVENT] before running. Claude follows the UPDATE RULES below on every run.
A4: UPDATE RULES (apply to every prompt)
A5: 1 | B5: Work on the newest Macro_Tracker_v*.xlsx in OneDrive › Desktop › Trading System. If it is open/locked in Excel, do NOT overwrite it: stop and report the planned changes instead.
A6: 2 | B6: Back up first: copy it to backups/<file>_backup_<YYYY-MM-DD_HHMM>_<prompt ID>.xlsx.
A7: 3 | B7: Write ONLY cells whose Sources row says “Claude” (blue input cells). Never write cells marked “User”: Bias N/Q, User bias, User read, Compare, Journal, Guide thresholds, Events “User notes”, Calendar settings. “Claude drafts → User confirms” cells: put the draft in the note cell and leave the value unless it is empty.
A8: 4 | B8: Use ONLY the fixed source listed on the Sources sheet for each input. If a source is down or a number cannot be verified, keep the old value and log it as “NOT UPDATED — reason”. Never estimate or fill from memory.
A9: 5 | B9: Units: percentages as plain numbers (3.1 = 3.1%); yields in %; dates as real dates, never =TODAY(). Never type into grey or green cells — they are formulas.
A10: 6 | B10: Keep all formulas, formatting, colours and layout. Only the Events table and the Key Levels table may gain rows. Keep Events sorted by Date, then Time; never delete a row that has User notes.
A11: 7 | B11: Times in Amsterdam time (CET/CEST).
A12: 8 | B12: After writing: recalculate, confirm zero formula errors, and update the “LIVE DATA as of …” line on every sheet touched.
A13: 9 | B13: Log the run: add one row to the Update Log sheet (date/time, prompt ID, run by, sheets touched, key changes old → new, stance/bias flips, anything NOT UPDATED). End the reply with the same summary.
A14: 10 | B14: Anything written into the workbook refers to the human as “User” (never “you”). The AI is “Claude”.
A16: PROMPTS
A17: ID | B17: Update cycle | C17: When | D17: What it updates | E17: Prompt — copy this whole cell
A18: P0 | B18: FULL CYCLE (scheduled) | C18: Every 2 days, 07:00 Amsterdam. Also on demand. | D18: Everything below, in order. P5 only on Sundays, P6 only on the first run of the month. | E18: Workbook: the newest Macro_Tracker_v*.xlsx in OneDrive › Desktop › Trading System (on the User’s computer; a copy may also live in the cloud later). Before starting, read the workbook’s Prompts sheet (UPDATE RULES) and Sources sheet (one fixed source per input + who fills each cell) and follow both exactly. Run the Macro Tracker FULL CYCLE for today. Do these prompts from the Prompts sheet in this order, as one run with one backup and one Update Log row: (1) P1 Events; (2) P2 Markets; (3) P3 Macro data — only for indicators with a new release since the last Update Log row; (4) P4 Country deep-dive for every currency that had a central-bank decision, central-bank speech, budget or tier-1 release since the last run, or whose Hub “Last checked” is older than 7 days; (5) if today is Sunday, P5 Key levels; (6) if this is the first run this month, P6 Who holds what; (7) P7 AI bias — always last. Finish with a 5-line summary: what changed, which Scorecard stances or FINAL BIAS values flipped, where the AI bias now disagrees with the model or the User bias, the next 3 high-impact events, and anything NOT UPDATED.
A19: P1 | B19: EVENTS & CALENDAR | C19: Inside P0 (every 2 days). Manually: Sunday evening. | D19: Events!A:I (never J = User notes). Calendar updates itself. | E19: Workbook: the newest Macro_Tracker_v*.xlsx in OneDrive › Desktop › Trading System (on the User’s computer; a copy may also live in the cloud later). Before starting, read the workbook’s Prompts sheet (UPDATE RULES) and Sources sheet (one fixed source per input + who fills each cell) and follow both exactly. Update the Events sheet. 1) Download the Forex Factory weekly feed (nfs.faireconomy.media/ff_calendar_thisweek.json, and ff_calendar_nextweek.json when it exists). 2) Keep: every High-impact event; Medium-impact for USD, EUR, GBP, JPY, CNY; bank holidays for USD, EUR, GBP, JPY. Convert times to Amsterdam time. 3) Set Type with the calendar key: Central bank (decisions/press conferences), CB speech (central-bank speakers, minutes), Government (budgets, auctions, treasury, finance ministers), Inflation, Jobs, Growth & business, Holiday. 4) Make sure the next 4 months of Fed, ECB, BoE and BoJ decisions, US CPI and jobs dates (BLS schedule) and national budgets are listed (official calendars). 5) For events that already happened, fill Actual from the official release. 6) Remove duplicates; delete Claude rows older than 30 days unless they have User notes; keep the table sorted. Log: events added / updated / removed.
A20: P2 | B20: MARKETS (prices, yields, risk) | C20: Inside P0 (every 2 days). | D20: Risk & Gold B5:B7, B13:C14, F13:F14 · Scorecard K5:L12 · Key Levels B6:C10 · Hub C26:C31. | E20: Workbook: the newest Macro_Tracker_v*.xlsx in OneDrive › Desktop › Trading System (on the User’s computer; a copy may also live in the cloud later). Before starting, read the workbook’s Prompts sheet (UPDATE RULES) and Sources sheet (one fixed source per input + who fills each cell) and follow both exactly. Update the market inputs. First run `npm run tradingview` in the Trading System folder — it writes data/tradingview/<date>.json with every price, 1-month value, 200-day SMA and barometer read used below. Risk & Gold: VIX (TradingView TVC:VIX), S&P 500 close and 200-day SMA (TradingView SP:SPX), US 10Y real yield now and ~1 month ago (FRED DFII10), ICE DXY now and ~1 month ago (TradingView TVC:DXY, same series in both cells); rewrite the F13/F14 driver notes in one line each. Scorecard 2Y yield now and 1 month ago for every currency row that has data (TradingView TVC:US02Y, TVC:DE02Y, TVC:GB02Y, TVC:JP02Y); “1 month ago” = derived from TradingView Perf.1M. Key Levels: current price + today’s date for every instrument in A6:A10 (TradingView). Hub risk barometer C26:C31 using the fixed rules on the Sources sheet (1-month change: AUD/JPY, CPER÷GLD, XLY÷XLP, HY spread, asset leader, CNN Fear & Greed). Log old → new for each number and any Scorecard pricing-score, risk-regime or gold-bias flip.
A21: P3 | B21: MACRO DATA (Scorecard stats) | C21: Inside P0 when a release happened. Manually after CPI / jobs / PMI / GDP. | D21: Scorecard C, E:J, S · Bias Builder blue indicator cells (headline CPI, wages, GDP, previous policy rate). | E21: Workbook: the newest Macro_Tracker_v*.xlsx in OneDrive › Desktop › Trading System (on the User’s computer; a copy may also live in the cloud later). Before starting, read the workbook’s Prompts sheet (UPDATE RULES) and Sources sheet (one fixed source per input + who fills each cell) and follow both exactly. Update the macro statistics for USD, EUR, GBP, JPY (and any other Scorecard row the User has started filling). Only change a number if a NEW official release came out. Scorecard: policy rate (after a decision), core CPI YoY now + the month 3 months earlier, unemployment now + 3 months earlier, composite PMI FINAL print — using the exact series on the Sources sheet (US FRED; Eurostat; ONS; Statistics Bureau of Japan core-core; S&P Global / HCOB). Bias Builder: headline CPI now + 3 months earlier, wage growth, GDP q/q latest + previous quarter, previous policy rate after a decision. If a currency’s score or STANCE changes, rewrite its Scorecard Notes (S) in one line: which print would flip it next. Log each changed number old → new and every score / stance flip.
A22: P4 | B22: COUNTRY DEEP-DIVE [CURRENCY] | C22: On demand, and inside P0 after a central-bank or tier-1 event. | D22: Bias Builder block for that currency (narrative rows + AI read) · Hub row (situation, theme, last checked) · Scorecard S · new catalysts into Events. | E22: Workbook: the newest Macro_Tracker_v*.xlsx in OneDrive › Desktop › Trading System (on the User’s computer; a copy may also live in the cloud later). Before starting, read the workbook’s Prompts sheet (UPDATE RULES) and Sources sheet (one fixed source per input + who fills each cell) and follow both exactly. Country deep-dive for [CURRENCY] as of today. Research with current sources: 1) the central bank’s last decision, vote split and the key guidance line (quote it); 2) latest inflation, jobs and growth prints vs expectations; 3) what the market prices for the next meeting and further out (probability + as-of date, from the source on the Sources sheet); 4) what the treasury / finance ministry / government is saying, plus fiscal and political events; 5) FX intervention and big official holders; 6) the next 3 catalysts with dates. Write it into the [CURRENCY] block on Bias Builder (Last decision, Vote, Central bank is saying, Market pricing next / further out, Treasury / government, Fiscal & political calendar, AI read stance + confidence + one-paragraph reasoning), the Hub row (Situation in one line, Main theme / risk, Last checked = today) and Scorecard Notes. Add any missing catalysts to Events. In the reply: the full brief, then ONE line for the Hub and what would change the picture.
A23: P5 | B23: KEY LEVELS REVIEW | C23: Sundays (inside P0). Manually before a trading week. | D23: Key Levels B6:C10, rows 13–52 (I “Last tested”, J “Reaction”, new proposed rows). | E23: Workbook: the newest Macro_Tracker_v*.xlsx in OneDrive › Desktop › Trading System (on the User’s computer; a copy may also live in the cloud later). Before starting, read the workbook’s Prompts sheet (UPDATE RULES) and Sources sheet (one fixed source per input + who fills each cell) and follow both exactly. Review the Key Levels sheet. 1) Update current prices and dates (TradingView — npm run tradingview; daily history from the TradingView chart). 2) For every level, check the daily history since its “Last tested” date: if price traded within the NEAR distance on the Guide sheet, set Last tested to that date and describe the reaction in a few words (held / broke / swept and reversed). 3) For rows whose Source says “verify”, confirm the level from price history or an official source and replace “verify” with the source — or flag it. 4) Propose up to 3 new levels per instrument (policy lines, big option strikes/expiries, prior highs/lows) as new rows with Source “Claude proposal <date>”. Never delete or edit a row the User added or changed. Log levels tested, verified and proposed.
A24: P6 | B24: WHO HOLDS WHAT | C24: Monthly (first P0 run of the month). | D24: Hub C18:D22. | E24: Workbook: the newest Macro_Tracker_v*.xlsx in OneDrive › Desktop › Trading System (on the User’s computer; a copy may also live in the cloud later). Before starting, read the workbook’s Prompts sheet (UPDATE RULES) and Sources sheet (one fixed source per input + who fills each cell) and follow both exactly. Update Hub section B (Who holds what). For each row write one line “what changed” from the latest release and set Last checked to today: US Treasury TIC (foreign holdings / flows, Japan and China), World Gold Council central-bank gold statistics, IMF COFER reserve shares (quarterly — keep the old line if no new quarter), Japan MoF monthly FX intervention amounts, CFTC Commitments of Traders (speculative positioning in JPY, EUR, GBP, gold, USD). Log anything that changes the gold research score or a currency story.
A25: P7 | B25: AI BIAS | C25: Always last in P0. Manually after any update. | D25: Bias Builder C6:C9, D6:D9, G6:G9 · AI read rows in every block (stance, confidence, reasoning) · gold AI read. | E25: Workbook: the newest Macro_Tracker_v*.xlsx in OneDrive › Desktop › Trading System (on the User’s computer; a copy may also live in the cloud later). Before starting, read the workbook’s Prompts sheet (UPDATE RULES) and Sources sheet (one fixed source per input + who fills each cell) and follow both exactly. Refresh the AI bias on the Bias Builder sheet using only what is in the workbook now (Scorecard, Bias Builder blocks, Risk & Gold, Key Levels, Events, Hub). For each currency block set the AI read stance (HAWKISH / NEUTRAL / DOVISH), confidence (High / Medium / Low) and a 2–3 sentence reasoning that names the strongest point FOR and AGAINST. For each pair set AI bias (LONG / SHORT / FLAT), the key driver in ≤2 lines and confidence; say explicitly when the AI bias disagrees with the model FINAL BIAS and why. Gold: AI read + reasoning from the Risk & Gold drivers vs price. Never touch User bias or User read. Reply with a table: pair · model · AI · User · agreement · what would flip the AI bias.
A26: P8 | B26: AFTER-EVENT UPDATE [EVENT] | C26: Manually, right after a tier-1 release or a central-bank decision. | D26: Events Actual · affected Scorecard / Bias Builder numbers · that currency’s Bias Builder block · AI bias for affected pairs. | E26: Workbook: the newest Macro_Tracker_v*.xlsx in OneDrive › Desktop › Trading System (on the User’s computer; a copy may also live in the cloud later). Before starting, read the workbook’s Prompts sheet (UPDATE RULES) and Sources sheet (one fixed source per input + who fills each cell) and follow both exactly. After-event update for [EVENT, e.g. “US CPI Oct” or “BoE decision”]. 1) Fill Actual on the Events row (official release) and note forecast vs actual. 2) Update only the Scorecard / Bias Builder numbers this release changes (P3 rules). 3) If it was a central-bank decision or speech, rerun P4 for that currency. 4) Rerun P7 for the pairs that contain that currency. Reply in 5 lines: surprise vs forecast, what moved in the workbook, stance / bias flips, what the market did, next catalyst.
A27: P9 | B27: WHAT CHANGED? (read-only) | C27: Any time. | D27: Nothing — read only. | E27: Workbook: the newest Macro_Tracker_v*.xlsx in OneDrive › Desktop › Trading System (on the User’s computer; a copy may also live in the cloud later). Read-only check of the Macro Tracker (do not write anything). Summarise: the last 3 Update Log rows; current FINAL BIAS, AI bias and User bias per pair and where they disagree; every Scorecard stance; the risk regime and barometer; any stale input (Hub Last checked > 14 days, LIVE DATA stamps > 3 days old, Bias status EXPIRED / NOT REVIEWED); and the high-impact events in the next 7 days from the Events sheet.
A29: SCHEDULING
B30: • Schedule only P0. It already calls the others at the right frequency (P5 on Sundays, P6 monthly).
B31: • Every 2 days at 07:00 Amsterdam (05:00 UTC in summer, 06:00 UTC in winter) gives fresh data before the London open.
B32: • The workbook lives on the User’s computer, so a scheduled run needs that computer on and linked (or the workbook moved to cloud storage later).
B33: • If Excel has the file open when a run starts, the run will not overwrite it — it reports the planned changes instead (rule 1). Close the workbook overnight.
B34: • User can run any single prompt by copying it from column E (replace [CURRENCY] / [EVENT]).
